Workbook

Sheet README
B1: A TINY LLM IN A SPREADSHEET, WITH ITS TRAINING OPENED UP
B2: A working next-word predictor trained on Alice in Wonderland: 10-word context, learned attention, live backpropagation.
B4: WHAT THIS IS
B5: A real (very small) neural language model. It reads the last 10 words, blends them with attention weights it
B6: learned by itself, passes them through a hidden layer, and scores all 2627 words of the book's vocabulary.
B7: It was trained by gradient descent on 26,673 ten-word windows from the book, and this workbook does not just
B8: run the model: the Training Example and Backpropagation tabs recompute a real training step, live.
B10: START HERE
B11: Prompt tab: type up to 10 words in the yellow cells, watch every step, read the prediction.
B12: Training Example tab: one real passage from the book, the forward pass, and the loss.
B13: Backpropagation tab: the actual gradients for that example, computed with MMULT, ending in a weight update.
B14: Circuits & Activations tab: a live trace of WHY the model picked its word, neuron by neuron.
... B40: so you never have to distribute words across cells by hand.

Sheet Prompt
B1: A TINY LLM: TYPE WORDS, WATCH IT THINK
B2: Yellow cells are inputs. Ten-word context; the model learned its own attention weights. Read top to bottom.
B4: STEP 1 · YOUR PROMPT (up to 10 words; blanks become <unk> and are ignored)
B5: w1 (oldest) | C5: w2 | D5: w3 | E5: w4 | F5: w5 | G5: w6 | H5: w7 | I5: w8 | J5: w9 | K5: w10 (latest)
B6: and | C6: whether | D6: the | E6: pleasure | F6: of | G6: making | H6: a | I6: daisy | J6: chain | K6: would
B7: or paste a sentence: | M7: =IF($C$7="",0,LEN(TRIM($C$7))-LEN(SUBSTITUTE(TRIM($C$7)," ",""))+1) -> 0
B8: If the sentence cell is filled, its LAST 10 words are used and the word cells above are ignored; clear it to use the cells. Default prompt: the book's second sentence, cut off; the true next word is "be".
B9: STEP 2 · TOKENIZE (find each word's row in the Vocabulary tab)
B10: =IF($C$7="",TRIM(SUBSTITUTE(SUBSTITUTE(SUBSTITUTE(SUBSTITUTE(LOWER(B6),".",""),",",""),"!",""),"?","")),IF($M$7-10+1<1,"",TRIM(SUBSTITUTE(SUBSTITUTE(SUBSTITUTE(SUBSTITUTE(LOWER(TRIM(MID(SUBSTITUTE(TRIM($C$7)," ",REPT(" ",LEN($C$7))),($M$7-10+1-1)*LEN($C$7)+1,LEN($C$7)))),".",""),",",""),"!",""),"?","")))) -> and | C10: =IF($C$7="",TRIM(SUBSTITUTE(SUBSTITUTE(SUBSTITUTE(SUBSTITUTE(LOWER(C6),".",""),",",""),"!",""),"?","")),IF($M$7-10+2<1,"",TRIM(SUBSTITUTE(SUBSTITUTE(SUBSTITUTE(SUBSTITUTE(LOWER(TRIM(MID(SUBSTITUTE(TRIM($C$7)," ",REPT(" ",LEN($C$7))),($M$7-10+2-1)*LEN($C$7)+1,LEN($C$7)))),".",""),",",""),"!",""),"?","")))) -> whether | D10: =IF($C$7="",TRIM(SUBSTITUTE(SUBSTITUTE(SUBSTITUTE(SUBSTITUTE(LOWER(D6),".",""),",",""),"!",""),"?","")),IF($M$7-10+3<1,"",TRIM(SUBSTITUTE(SUBSTITUTE(SUBSTITUTE(SUBSTITUTE(LOWER(TRIM(MID(SUBSTITUTE(TRIM($C$7)," ",REPT(" ",LEN($C$7))),($M$7-10+3-1)*LEN($C$7)+1,LEN($C$7)))),".",""),",",""),"!",""),"?","")))) -> the | E10: =IF($C$7="",TRIM(SUBSTITUTE(SUBSTITUTE(SUBSTITUTE(SUBSTITUTE(LOWER(E6),".",""),",",""),"!",""),"?","")),IF($M$7-10+4<1,"",TRIM(SUBSTITUTE(SUBSTITUTE(SUBSTITUTE(SUBSTITUTE(LOWER(TRIM(MID(SUBSTITUTE(TRIM($C$7)," ",REPT(" ",LEN($C$7))),($M$7-10+4-1)*LEN($C$7)+1,LEN($C$7)))),".",""),",",""),"!",""),"?","")))) -> pleasure | F10: =IF($C$7="",TRIM(SUBSTITUTE(SUBSTITUTE(SUBSTITUTE(SUBSTITUTE(LOWER(F6),".",""),",",""),"!",""),"?","")),IF($M$7-10+5<1,"",TRIM(SUBSTITUTE(SUBSTITUTE(SUBSTITUTE(SUBSTITUTE(LOWER(TRIM(MID(SUBSTITUTE(TRIM($C$7)," ",REPT(" ",LEN($C$7))),($M$7-10+5-1)*LEN($C$7)+1,LEN($C$7)))),".",""),",",""),"!",""),"?","")))) -> of | G10: =IF($C$7="",TRIM(SUBSTITUTE(SUBSTITUTE(SUBSTITUTE(SUBSTITUTE(LOWER(G6),".",""),",",""),"!",""),"?","")),IF($M$7-10+6<1,"",TRIM(SUBSTITUTE(SUBSTITUTE(SUBSTITUTE(SUBSTITUTE(LOWER(TRIM(MID(SUBSTITUTE(TRIM($C$7)," ",REPT(" ",LEN($C$7))),($M$7-10+6-1)*LEN($C$7)+1,LEN($C$7)))),".",""),",",""),"!",""),"?","")))) -> making | H10: =IF($C$7="",TRIM(SUBSTITUTE(SUBSTITUTE(SUBSTITUTE(SUBSTITUTE(LOWER(H6),".",""),",",""),"!",""),"?","")),IF($M$7-10+7<1,"",TRIM(SUBSTITUTE(SUBSTITUTE(SUBSTITUTE(SUBSTITUTE(LOWER(TRIM(MID(SUBSTITUTE(TRIM($C$7)," ",REPT(" ",LEN($C$7))),($M$7-10+7-1)*LEN($C$7)+1,LEN($C$7)))),".",""),",",""),"!",""),"?","")))) -> a | I10: =IF($C$7="",TRIM(SUBSTITUTE(SUBSTITUTE(SUBSTITUTE(SUBSTITUTE(LOWER(I6),".",""),",",""),"!",""),"?","")),IF($M$7-10+8<1,"",TRIM(SUBSTITUTE(SUBSTITUTE(SUBSTITUTE(SUBSTITUTE(LOWER(TRIM(MID(SUBSTITUTE(TRIM($C$7)," ",REPT(" ",LEN($C$7))),($M$7-10+8-1)*LEN($C$7)+1,LEN($C$7)))),".",""),",",""),"!",""),"?","")))) -> daisy | J10: =IF($C$7="",TRIM(SUBSTITUTE(SUBSTITUTE(SUBSTITUTE(SUBSTITUTE(LOWER(J6),".",""),",",""),"!",""),"?","")),IF($M$7-10+9<1,"",TRIM(SUBSTITUTE(SUBSTITUTE(SUBSTITUTE(SUBSTITUTE(LOWER(TRIM(MID(SUBSTITUTE(TRIM($C$7)," ",REPT(" ",LEN($C$7))),($M$7-10+9-1)*LEN($C$7)+1,LEN($C$7)))),".",""),",",""),"!",""),"?","")))) -> chain | K10: =IF($C$7="",TRIM(SUBSTITUTE(SUBSTITUTE(SUBSTITUTE(SUBSTITUTE(LOWER(K6),".",""),",",""),"!",""),"?","")),IF($M$7-10+10<1,"",TRIM(SUBSTITUTE(SUBSTITUTE(SUBSTITUTE(SUBSTITUTE(LOWER(TRIM(MID(SUBSTITUTE(TRIM($C$7)," ",REPT(" ",LEN($C$7))),($M$7-10+10-1)*LEN($C$7)+1,LEN($C$7)))),".",""),",",""),"!",""),"?","")))) -> would
B11: =IFERROR(MATCH(B10,Vocabulary!$B$2:$B$2629,0),1) -> 3 | C11: =IFERROR(MATCH(C10,Vocabulary!$B$2:$B$2629,0),1) -> 328 | D11: =IFERROR(MATCH(D10,Vocabulary!$B$2:$B$2629,0),1) -> 2 | E11: =IFERROR(MATCH(E10,Vocabulary!$B$2:$B$2629,0),1) -> 1081 | F11: =IFERROR(MATCH(F10,Vocabulary!$B$2:$B$2629,0),1) -> 8 | G11: =IFERROR(MATCH(G10,Vocabulary!$B$2:$B$2629,0),1) -> 425 | H11: =IFERROR(MATCH(H10,Vocabulary!$B$2:$B$2629,0),1) -> 5 | I11: =IFERROR(MATCH(I10,Vocabulary!$B$2:$B$2629,0),1) -> 1490 | ... K11: =IFERROR(MATCH(K10,Vocabulary!$B$2:$B$2629,0),1) -> 48
B12: =IF(ISNUMBER(MATCH(B10,Vocabulary!$B$2:$B$2629,0)),"ok","<unk>") -> ok | C12: =IF(ISNUMBER(MATCH(C10,Vocabulary!$B$2:$B$2629,0)),"ok","<unk>") -> ok | D12: =IF(ISNUMBER(MATCH(D10,Vocabulary!$B$2:$B$2629,0)),"ok","<unk>") -> ok | E12: =IF(ISNUMBER(MATCH(E10,Vocabulary!$B$2:$B$2629,0)),"ok","<unk>") -> ok | F12: =IF(ISNUMBER(MATCH(F10,Vocabulary!$B$2:$B$2629,0)),"ok","<unk>") -> ok | G12: =IF(ISNUMBER(MATCH(G10,Vocabulary!$B$2:$B$2629,0)),"ok","<unk>") -> ok | H12: =IF(ISNUMBER(MATCH(H10,Vocabulary!$B$2:$B$2629,0)),"ok","<unk>") -> ok | I12: =IF(ISNUMBER(MATCH(I10,Vocabulary!$B$2:$B$2629,0)),"ok","<unk>") -> ok | ... K12: =IF(ISNUMBER(MATCH(K10,Vocabulary!$B$2:$B$2629,0)),"ok","<unk>") -> ok
B13: Row 10: cleaned (lowercase, strip . , ! ?). Row 11: token ID via MATCH. Full story on the Tokenizer tab.
B15: STEP 3 · EMBEDDINGS (each token ID looks up its learned row of 16 numbers: a 10 x 16 block)
B16: token | C16: d1 | D16: d2 | E16: d3 | F16: d4 | G16: d5 | H16: d6 | I16: d7 | J16: d8 | K16: d9 | L16: d10 | M16: d11 | N16: d12 | O16: d13 | P16: d14 | Q16: d15 | R16: d16
B17: =B10 -> and | C17: =INDEX(Embeddings!$C$2:$R$2629,B$11,COLUMN()-2) -> -0.25765 | D17: =INDEX(Embeddings!$C$2:$R$2629,B$11,COLUMN()-2) -> -0.27206 | E17: =INDEX(Embeddings!$C$2:$R$2629,B$11,COLUMN()-2) -> 1.0304 | F17: =INDEX(Embeddings!$C$2:$R$2629,B$11,COLUMN()-2) -> -0.35624 | G17: =INDEX(Embeddings!$C$2:$R$2629,B$11,COLUMN()-2) -> 0.0815 | H17: =INDEX(Embeddings!$C$2:$R$2629,B$11,COLUMN()-2) -> 0.64867 | I17: =INDEX(Embeddings!$C$2:$R$2629,B$11,COLUMN()-2) -> 0.45802 | J17: =INDEX(Embeddings!$C$2:$R$2629,B$11,COLUMN()-2) -> -0.48542 | K17: =INDEX(Embeddings!$C$2:$R$2629,B$11,COLUMN()-2) -> -0.40933 | L17: =INDEX(Embeddings!$C$2:$R$2629,B$11,COLUMN()-2) -> 0.10557 | M17: =INDEX(Embeddings!$C$2:$R$2629,B$11,COLUMN()-2) -> -0.48216 | N17: =INDEX(Embeddings!$C$2:$R$2629,B$11,COLUMN()-2) -> -0.51501 | O17: =INDEX(Embeddings!$C$2:$R$2629,B$11,COLUMN()-2) -> 0.07698 | P17: =INDEX(Embeddings!$C$2:$R$2629,B$11,COLUMN()-2) -> -0.14712 | Q17: =INDEX(Embeddings!$C$2:$R$2629,B$11,COLUMN()-2) -> 0.73348 | R17: =INDEX(Embeddings!$C$2:$R$2629,B$11,COLUMN()-2) -> -0.33239
B18: =C10 -> whether | C18: =INDEX(Embeddings!$C$2:$R$2629,C$11,COLUMN()-2) -> -1.86254 | D18: =INDEX(Embeddings!$C$2:$R$2629,C$11,COLUMN()-2) -> 0.23212 | E18: =INDEX(Embeddings!$C$2:$R$2629,C$11,COLUMN()-2) -> -1.32472 | F18: =INDEX(Embeddings!$C$2:$R$2629,C$11,COLUMN()-2) -> -1.14225 | G18: =INDEX(Embeddings!$C$2:$R$2629,C$11,COLUMN()-2) -> -0.22653 | H18: =INDEX(Embeddings!$C$2:$R$2629,C$11,COLUMN()-2) -> 0.53177 | I18: =INDEX(Embeddings!$C$2:$R$2629,C$11,COLUMN()-2) -> -0.55961 | J18: =INDEX(Embeddings!$C$2:$R$2629,C$11,COLUMN()-2) -> 0.06918 | K18: =INDEX(Embeddings!$C$2:$R$2629,C$11,COLUMN()-2) -> -0.95933 | L18: =INDEX(Embeddings!$C$2:$R$2629,C$11,COLUMN()-2) -> -2.22461 | M18: =INDEX(Embeddings!$C$2:$R$2629,C$11,COLUMN()-2) -> 1.23668 | N18: =INDEX(Embeddings!$C$2:$R$2629,C$11,COLUMN()-2) -> 2.11572 | O18: =INDEX(Embeddings!$C$2:$R$2629,C$11,COLUMN()-2) -> 0.28465 | P18: =INDEX(Embeddings!$C$2:$R$2629,C$11,COLUMN()-2) -> 0.11699 | Q18: =INDEX(Embeddings!$C$2:$R$2629,C$11,COLUMN()-2) -> 0.29215 | R18: =INDEX(Embeddings!$C$2:$R$2629,C$11,COLUMN()-2) -> -1.01482
B19: =D10 -> the | C19: =INDEX(Embeddings!$C$2:$R$2629,D$11,COLUMN()-2) -> -0.24612 | D19: =INDEX(Embeddings!$C$2:$R$2629,D$11,COLUMN()-2) -> -0.69257 | E19: =INDEX(Embeddings!$C$2:$R$2629,D$11,COLUMN()-2) -> -1.11074 | F19: =INDEX(Embeddings!$C$2:$R$2629,D$11,COLUMN()-2) -> -0.52835 | G19: =INDEX(Embeddings!$C$2:$R$2629,D$11,COLUMN()-2) -> -0.49587 | H19: =INDEX(Embeddings!$C$2:$R$2629,D$11,COLUMN()-2) -> 0.16979 | I19: =INDEX(Embeddings!$C$2:$R$2629,D$11,COLUMN()-2) -> -1.56429 | J19: =INDEX(Embeddings!$C$2:$R$2629,D$11,COLUMN()-2) -> -0.73668 | K19: =INDEX(Embeddings!$C$2:$R$2629,D$11,COLUMN()-2) -> 0.62002 | L19: =INDEX(Embeddings!$C$2:$R$2629,D$11,COLUMN()-2) -> 0.80283 | M19: =INDEX(Embeddings!$C$2:$R$2629,D$11,COLUMN()-2) -> -0.61923 | N19: =INDEX(Embeddings!$C$2:$R$2629,D$11,COLUMN()-2) -> -0.87934 | O19: =INDEX(Embeddings!$C$2:$R$2629,D$11,COLUMN()-2) -> -0.30187 | P19: =INDEX(Embeddings!$C$2:$R$2629,D$11,COLUMN()-2) -> 0.67991 | Q19: =INDEX(Embeddings!$C$2:$R$2629,D$11,COLUMN()-2) -> -0.28704 | R19: =INDEX(Embeddings!$C$2:$R$2629,D$11,COLUMN()-2) -> 0.23597
B20: =E10 -> pleasure | C20: =INDEX(Embeddings!$C$2:$R$2629,E$11,COLUMN()-2) -> -0.27592 | D20: =INDEX(Embeddings!$C$2:$R$2629,E$11,COLUMN()-2) -> -0.46226 | E20: =INDEX(Embeddings!$C$2:$R$2629,E$11,COLUMN()-2) -> -1.79933 | F20: =INDEX(Embeddings!$C$2:$R$2629,E$11,COLUMN()-2) -> -1.45504 | G20: =INDEX(Embeddings!$C$2:$R$2629,E$11,COLUMN()-2) -> 0.34007 | H20: =INDEX(Embeddings!$C$2:$R$2629,E$11,COLUMN()-2) -> -1.05535 | I20: =INDEX(Embeddings!$C$2:$R$2629,E$11,COLUMN()-2) -> 1.10641 | J20: =INDEX(Embeddings!$C$2:$R$2629,E$11,COLUMN()-2) -> 2.07358 | K20: =INDEX(Embeddings!$C$2:$R$2629,E$11,COLUMN()-2) -> 1.63027 | L20: =INDEX(Embeddings!$C$2:$R$2629,E$11,COLUMN()-2) -> 1.75805 | M20: =INDEX(Embeddings!$C$2:$R$2629,E$11,COLUMN()-2) -> -1.96145 | N20: =INDEX(Embeddings!$C$2:$R$2629,E$11,COLUMN()-2) -> -1.09477 | O20: =INDEX(Embeddings!$C$2:$R$2629,E$11,COLUMN()-2) -> -0.12867 | P20: =INDEX(Embeddings!$C$2:$R$2629,E$11,COLUMN()-2) -> 1.84758 | Q20: =INDEX(Embeddings!$C$2:$R$2629,E$11,COLUMN()-2) -> 0.02697 | R20: =INDEX(Embeddings!$C$2:$R$2629,E$11,COLUMN()-2) -> -3.24116
B21: =F10 -> of | C21: =INDEX(Embeddings!$C$2:$R$2629,F$11,COLUMN()-2) -> -0.05844 | D21: =INDEX(Embeddings!$C$2:$R$2629,F$11,COLUMN()-2) -> -0.69847 | E21: =INDEX(Embeddings!$C$2:$R$2629,F$11,COLUMN()-2) -> -0.01318 | F21: =INDEX(Embeddings!$C$2:$R$2629,F$11,COLUMN()-2) -> 0.69573 | G21: =INDEX(Embeddings!$C$2:$R$2629,F$11,COLUMN()-2) -> 0.40065 | H21: =INDEX(Embeddings!$C$2:$R$2629,F$11,COLUMN()-2) -> -0.26492 | I21: =INDEX(Embeddings!$C$2:$R$2629,F$11,COLUMN()-2) -> 1.42647 | J21: =INDEX(Embeddings!$C$2:$R$2629,F$11,COLUMN()-2) -> -0.65642 | K21: =INDEX(Embeddings!$C$2:$R$2629,F$11,COLUMN()-2) -> -0.65223 | L21: =INDEX(Embeddings!$C$2:$R$2629,F$11,COLUMN()-2) -> -0.7729 | M21: =INDEX(Embeddings!$C$2:$R$2629,F$11,COLUMN()-2) -> -0.26861 | N21: =INDEX(Embeddings!$C$2:$R$2629,F$11,COLUMN()-2) -> -0.03118 | O21: =INDEX(Embeddings!$C$2:$R$2629,F$11,COLUMN()-2) -> 0.01131 | P21: =INDEX(Embeddings!$C$2:$R$2629,F$11,COLUMN()-2) -> 0.69797 | Q21: =INDEX(Embeddings!$C$2:$R$2629,F$11,COLUMN()-2) -> -0.25873 | R21: =INDEX(Embeddings!$C$2:$R$2629,F$11,COLUMN()-2) -> 0.80276
B22: =G10 -> making | C22: =INDEX(Embeddings!$C$2:$R$2629,G$11,COLUMN()-2) -> 0.85812 | D22: =INDEX(Embeddings!$C$2:$R$2629,G$11,COLUMN()-2) -> 0.66564 | E22: =INDEX(Embeddings!$C$2:$R$2629,G$11,COLUMN()-2) -> 2.47402 | F22: =INDEX(Embeddings!$C$2:$R$2629,G$11,COLUMN()-2) -> 0.86201 | G22: =INDEX(Embeddings!$C$2:$R$2629,G$11,COLUMN()-2) -> -0.22479 | H22: =INDEX(Embeddings!$C$2:$R$2629,G$11,COLUMN()-2) -> 0.12082 | I22: =INDEX(Embeddings!$C$2:$R$2629,G$11,COLUMN()-2) -> 2.06183 | J22: =INDEX(Embeddings!$C$2:$R$2629,G$11,COLUMN()-2) -> 0.30828 | K22: =INDEX(Embeddings!$C$2:$R$2629,G$11,COLUMN()-2) -> 1.30011 | L22: =INDEX(Embeddings!$C$2:$R$2629,G$11,COLUMN()-2) -> -0.72049 | M22: =INDEX(Embeddings!$C$2:$R$2629,G$11,COLUMN()-2) -> 0.16129 | N22: =INDEX(Embeddings!$C$2:$R$2629,G$11,COLUMN()-2) -> 0.33156 | O22: =INDEX(Embeddings!$C$2:$R$2629,G$11,COLUMN()-2) -> -0.0888 | P22: =INDEX(Embeddings!$C$2:$R$2629,G$11,COLUMN()-2) -> 1.73543 | Q22: =INDEX(Embeddings!$C$2:$R$2629,G$11,COLUMN()-2) -> -0.67013 | R22: =INDEX(Embeddings!$C$2:$R$2629,G$11,COLUMN()-2) -> 0.25614
B23: =H10 -> a | C23: =INDEX(Embeddings!$C$2:$R$2629,H$11,COLUMN()-2) -> 0.44645 | D23: =INDEX(Embeddings!$C$2:$R$2629,H$11,COLUMN()-2) -> 0.35822 | E23: =INDEX(Embeddings!$C$2:$R$2629,H$11,COLUMN()-2) -> -0.33882 | F23: =INDEX(Embeddings!$C$2:$R$2629,H$11,COLUMN()-2) -> 0.46646 | G23: =INDEX(Embeddings!$C$2:$R$2629,H$11,COLUMN()-2) -> -0.49398 | H23: =INDEX(Embeddings!$C$2:$R$2629,H$11,COLUMN()-2) -> -0.35397 | I23: =INDEX(Embeddings!$C$2:$R$2629,H$11,COLUMN()-2) -> -1.67177 | J23: =INDEX(Embeddings!$C$2:$R$2629,H$11,COLUMN()-2) -> -1.32692 | K23: =INDEX(Embeddings!$C$2:$R$2629,H$11,COLUMN()-2) -> -0.02545 | L23: =INDEX(Embeddings!$C$2:$R$2629,H$11,COLUMN()-2) -> 0.24869 | M23: =INDEX(Embeddings!$C$2:$R$2629,H$11,COLUMN()-2) -> 0.63082 | N23: =INDEX(Embeddings!$C$2:$R$2629,H$11,COLUMN()-2) -> -0.58007 | O23: =INDEX(Embeddings!$C$2:$R$2629,H$11,COLUMN()-2) -> -0.04389 | P23: =INDEX(Embeddings!$C$2:$R$2629,H$11,COLUMN()-2) -> 0.52169 | Q23: =INDEX(Embeddings!$C$2:$R$2629,H$11,COLUMN()-2) -> -0.25329 | R23: =INDEX(Embeddings!$C$2:$R$2629,H$11,COLUMN()-2) -> 1.71116
B24: =I10 -> daisy | C24: =INDEX(Embeddings!$C$2:$R$2629,I$11,COLUMN()-2) -> -1.76346 | D24: =INDEX(Embeddings!$C$2:$R$2629,I$11,COLUMN()-2) -> 1.60316 | E24: =INDEX(Embeddings!$C$2:$R$2629,I$11,COLUMN()-2) -> 0.59665 | F24: =INDEX(Embeddings!$C$2:$R$2629,I$11,COLUMN()-2) -> -1.48118 | G24: =INDEX(Embeddings!$C$2:$R$2629,I$11,COLUMN()-2) -> -2.45447 | H24: =INDEX(Embeddings!$C$2:$R$2629,I$11,COLUMN()-2) -> 0.63032 | I24: =INDEX(Embeddings!$C$2:$R$2629,I$11,COLUMN()-2) -> -1.51319 | J24: =INDEX(Embeddings!$C$2:$R$2629,I$11,COLUMN()-2) -> -4.36859 | K24: =INDEX(Embeddings!$C$2:$R$2629,I$11,COLUMN()-2) -> 1.34154 | L24: =INDEX(Embeddings!$C$2:$R$2629,I$11,COLUMN()-2) -> 0.5695 | M24: =INDEX(Embeddings!$C$2:$R$2629,I$11,COLUMN()-2) -> 1.10327 | N24: =INDEX(Embeddings!$C$2:$R$2629,I$11,COLUMN()-2) -> 0.36804 | O24: =INDEX(Embeddings!$C$2:$R$2629,I$11,COLUMN()-2) -> -0.98829 | P24: =INDEX(Embeddings!$C$2:$R$2629,I$11,COLUMN()-2) -> -2.72809 | Q24: =INDEX(Embeddings!$C$2:$R$2629,I$11,COLUMN()-2) -> 1.36047 | R24: =INDEX(Embeddings!$C$2:$R$2629,I$11,COLUMN()-2) -> -2.40981
B25: =J10 -> chain | C25: =INDEX(Embeddings!$C$2:$R$2629,J$11,COLUMN()-2) -> 0.8676 | D25: =INDEX(Embeddings!$C$2:$R$2629,J$11,COLUMN()-2) -> -2.48009 | E25: =INDEX(Embeddings!$C$2:$R$2629,J$11,COLUMN()-2) -> 2.44397 | F25: =INDEX(Embeddings!$C$2:$R$2629,J$11,COLUMN()-2) -> -0.95178 | G25: =INDEX(Embeddings!$C$2:$R$2629,J$11,COLUMN()-2) -> -0.14695 | H25: =INDEX(Embeddings!$C$2:$R$2629,J$11,COLUMN()-2) -> -0.59088 | I25: =INDEX(Embeddings!$C$2:$R$2629,J$11,COLUMN()-2) -> -1.10541 | J25: =INDEX(Embeddings!$C$2:$R$2629,J$11,COLUMN()-2) -> 3.07254 | K25: =INDEX(Embeddings!$C$2:$R$2629,J$11,COLUMN()-2) -> -0.17528 | L25: =INDEX(Embeddings!$C$2:$R$2629,J$11,COLUMN()-2) -> -0.0514 | M25: =INDEX(Embeddings!$C$2:$R$2629,J$11,COLUMN()-2) -> 3.08607 | N25: =INDEX(Embeddings!$C$2:$R$2629,J$11,COLUMN()-2) -> 1.03136 | O25: =INDEX(Embeddings!$C$2:$R$2629,J$11,COLUMN()-2) -> -0.16113 | P25: =INDEX(Embeddings!$C$2:$R$2629,J$11,COLUMN()-2) -> -1.35821 | Q25: =INDEX(Embeddings!$C$2:$R$2629,J$11,COLUMN()-2) -> -0.29553 | R25: =INDEX(Embeddings!$C$2:$R$2629,J$11,COLUMN()-2) -> -1.30229
B26: =K10 -> would | C26: =INDEX(Embeddings!$C$2:$R$2629,K$11,COLUMN()-2) -> -1.41172 | D26: =INDEX(Embeddings!$C$2:$R$2629,K$11,COLUMN()-2) -> 0.07554 | E26: =INDEX(Embeddings!$C$2:$R$2629,K$11,COLUMN()-2) -> 1.95098 | F26: =INDEX(Embeddings!$C$2:$R$2629,K$11,COLUMN()-2) -> 1.14602 | G26: =INDEX(Embeddings!$C$2:$R$2629,K$11,COLUMN()-2) -> -0.13432 | H26: =INDEX(Embeddings!$C$2:$R$2629,K$11,COLUMN()-2) -> -0.98694 | I26: =INDEX(Embeddings!$C$2:$R$2629,K$11,COLUMN()-2) -> 1.75483 | J26: =INDEX(Embeddings!$C$2:$R$2629,K$11,COLUMN()-2) -> -0.87026 | K26: =INDEX(Embeddings!$C$2:$R$2629,K$11,COLUMN()-2) -> 0.58196 | L26: =INDEX(Embeddings!$C$2:$R$2629,K$11,COLUMN()-2) -> 1.0168 | M26: =INDEX(Embeddings!$C$2:$R$2629,K$11,COLUMN()-2) -> 0.63619 | N26: =INDEX(Embeddings!$C$2:$R$2629,K$11,COLUMN()-2) -> 0.24306 | O26: =INDEX(Embeddings!$C$2:$R$2629,K$11,COLUMN()-2) -> 0.92581 | P26: =INDEX(Embeddings!$C$2:$R$2629,K$11,COLUMN()-2) -> 1.38879 | Q26: =INDEX(Embeddings!$C$2:$R$2629,K$11,COLUMN()-2) -> 0.59301 | R26: =INDEX(Embeddings!$C$2:$R$2629,K$11,COLUMN()-2) -> -1.98864
B27: Learned vectors: the model's "meaning" for each word. <unk> (token 1) is all zeros so it contributes nothing.
B29: STEP 4 · ATTENTION: THE MODEL LEARNED THESE SCORES ITSELF
B30: -1.22 | C30: -0.89 | D30: -0.88 | E30: -0.94 | F30: -0.79 | G30: -0.58 | H30: -0.22 | I30: 0.17 | J30: 0.65 | K30: 1.46
B31: =EXP(B30)/SUMPRODUCT(EXP($B$30:$K$30)) -> 0.027503276 | C31: =EXP(C30)/SUMPRODUCT(EXP($B$30:$K$30)) -> 0.03825618 | D31: =EXP(D30)/SUMPRODUCT(EXP($B$30:$K$30)) -> 0.038640661 | E31: =EXP(E30)/SUMPRODUCT(EXP($B$30:$K$30)) -> 0.036390404 | F31: =EXP(F30)/SUMPRODUCT(EXP($B$30:$K$30)) -> 0.042279617 | G31: =EXP(G30)/SUMPRODUCT(EXP($B$30:$K$30)) -> 0.052159436 | H31: =EXP(H30)/SUMPRODUCT(EXP($B$30:$K$30)) -> 0.074761654 | I31: =EXP(I30)/SUMPRODUCT(EXP($B$30:$K$30)) -> 0.11042153 | ... K31: =EXP(K30)/SUMPRODUCT(EXP($B$30:$K$30)) -> 0.40113784
B32: Row 30: raw scores, exactly as gradient descent left them (editable). Row 31: their softmax. Nobody told the model recency matters; it learned the 2.7% -> 40% ramp from the data alone.
B34: STEP 5 · MIX INTO ONE CONTEXT VECTOR (MMULT #1: 1x10 times 10x16 = 1x16)
B35: context c = | C35: {=MMULT(B31:K31,C17:R26)} -> -0.62842094 | D35: -0.24546148 | E35: 1.257038 | F35: 0.10870256 | G35: -0.39605677 | H35: -0.45676224 | I35: 0.35345643 | J35: -0.35777534 | K35: 0.4239627 | L35: 0.4227204 | M35: 0.91069347 | N35: 0.28775189 | O35: 0.22272053 | P35: 0.26645162 | Q35: 0.29177747 | R35: -1.2777709
B37: STEP 6 · HIDDEN LAYER (MMULT #2: c times the 16x16 matrix, then TANH)
B38: c x W = | C38: {=MMULT(C35:R35,'Hidden Weights'!$C$3:$R$18)} -> -1.2949063 | D38: 9.0517968 | E38: 5.2510643 | F38: 0.72483897 | G38: -6.1625198 | H38: -3.9246647 | I38: 0.37511529 | J38: -21.316641 | K38: 4.4904264 | L38: 8.1100411 | M38: 4.5693928 | N38: -1.530197 | O38: 13.118653 | P38: 4.8262008 | Q38: -5.7804551 | R38: -3.3920319
B39: h = TANH: | C39: =TANH(C38) -> -0.8604061 | D39: =TANH(D38) -> 0.99999997 | E39: =TANH(E38) -> 0.99994505 | F39: =TANH(F38) -> 0.61989773 | G39: =TANH(G38) -> -0.99999112 | H39: =TANH(H38) -> -0.99922028 | I39: =TANH(I38) -> 0.35845788 | J39: =TANH(J38) -> -1 | ... R39: =TANH(R38) -> -0.99773922
B40: TANH squashes into -1..1: the nonlinearity that makes this a neural network instead of one big matrix.
B42: STEP 7 · SCORE EVERY WORD (MMULT #3, on the Prediction tab)
B43: One array formula multiplies the 2627 x 16 Output Weights by TRANSPOSE(h): 2628 scores at once.
B44: Softmax with temperature turns scores into probabilities. See the Prediction tab for every word's score.
B45: temperature | C45: 1 | D45: <- editable. 0.3 = confident, 3.0 = chaotic.
B47: STEP 8 · THE PREDICTION
B48: next word: | C48: =C52 -> be | E48: probability: | F48: =D52 -> 0.78953467
B51: rank | C51: word | D51: probability | E51: p as a bar
B52: 1 | C52: =INDEX(Prediction!$B$6:$B$2633,MATCH(LARGE(Prediction!$F$6:$F$2633,B52),Prediction!$F$6:$F$2633,0)) -> be | D52: =INDEX(Prediction!$E$6:$E$2633,MATCH(LARGE(Prediction!$F$6:$F$2633,B52),Prediction!$F$6:$F$2633,0)) -> 0.78953467 | E52: =REPT("|",MAX(1,ROUND(D52*60,0))) -> |||||||||||||||||||||||||||||||||||||||||||||||
B53: 2 | C53: =INDEX(Prediction!$B$6:$B$2633,MATCH(LARGE(Prediction!$F$6:$F$2633,B53),Prediction!$F$6:$F$2633,0)) -> talk | D53: =INDEX(Prediction!$E$6:$E$2633,MATCH(LARGE(Prediction!$F$6:$F$2633,B53),Prediction!$F$6:$F$2633,0)) -> 0.076571429 | E53: =REPT("|",MAX(1,ROUND(D53*60,0))) -> |||||
B54: 3 | C54: =INDEX(Prediction!$B$6:$B$2633,MATCH(LARGE(Prediction!$F$6:$F$2633,B54),Prediction!$F$6:$F$2633,0)) -> stand | D54: =INDEX(Prediction!$E$6:$E$2633,MATCH(LARGE(Prediction!$F$6:$F$2633,B54),Prediction!$F$6:$F$2633,0)) -> 0.021721932 | E54: =REPT("|",MAX(1,ROUND(D54*60,0))) -> |
B55: 4 | C55: =INDEX(Prediction!$B$6:$B$2633,MATCH(LARGE(Prediction!$F$6:$F$2633,B55),Prediction!$F$6:$F$2633,0)) -> have | D55: =INDEX(Prediction!$E$6:$E$2633,MATCH(LARGE(Prediction!$F$6:$F$2633,B55),Prediction!$F$6:$F$2633,0)) -> 0.02051383 | E55: =REPT("|",MAX(1,ROUND(D55*60,0))) -> |
B56: 5 | C56: =INDEX(Prediction!$B$6:$B$2633,MATCH(LARGE(Prediction!$F$6:$F$2633,B56),Prediction!$F$6:$F$2633,0)) -> go | D56: =INDEX(Prediction!$E$6:$E$2633,MATCH(LARGE(Prediction!$F$6:$F$2633,B56),Prediction!$F$6:$F$2633,0)) -> 0.012784734 | E56: =REPT("|",MAX(1,ROUND(D56*60,0))) -> |
B57: 6 | C57: =INDEX(Prediction!$B$6:$B$2633,MATCH(LARGE(Prediction!$F$6:$F$2633,B57),Prediction!$F$6:$F$2633,0)) -> remember | D57: =INDEX(Prediction!$E$6:$E$2633,MATCH(LARGE(Prediction!$F$6:$F$2633,B57),Prediction!$F$6:$F$2633,0)) -> 0.011738078 | E57: =REPT("|",MAX(1,ROUND(D57*60,0))) -> |
B58: 7 | C58: =INDEX(Prediction!$B$6:$B$2633,MATCH(LARGE(Prediction!$F$6:$F$2633,B58),Prediction!$F$6:$F$2633,0)) -> make | D58: =INDEX(Prediction!$E$6:$E$2633,MATCH(LARGE(Prediction!$F$6:$F$2633,B58),Prediction!$F$6:$F$2633,0)) -> 0.01072029 | E58: =REPT("|",MAX(1,ROUND(D58*60,0))) -> |
B59: 8 | C59: =INDEX(Prediction!$B$6:$B$2633,MATCH(LARGE(Prediction!$F$6:$F$2633,B59),Prediction!$F$6:$F$2633,0)) -> met | D59: =INDEX(Prediction!$E$6:$E$2633,MATCH(LARGE(Prediction!$F$6:$F$2633,B59),Prediction!$F$6:$F$2633,0)) -> 0.0055612278 | E59: =REPT("|",MAX(1,ROUND(D59*60,0))) -> |
B60: 9 | C60: =INDEX(Prediction!$B$6:$B$2633,MATCH(LARGE(Prediction!$F$6:$F$2633,B60),Prediction!$F$6:$F$2633,0)) -> do | D60: =INDEX(Prediction!$E$6:$E$2633,MATCH(LARGE(Prediction!$F$6:$F$2633,B60),Prediction!$F$6:$F$2633,0)) -> 0.0047766998 | E60: =REPT("|",MAX(1,ROUND(D60*60,0))) -> |
B61: 10 | C61: =INDEX(Prediction!$B$6:$B$2633,MATCH(LARGE(Prediction!$F$6:$F$2633,B61),Prediction!$F$6:$F$2633,0)) -> offer | D61: =INDEX(Prediction!$E$6:$E$2633,MATCH(LARGE(Prediction!$F$6:$F$2633,B61),Prediction!$F$6:$F$2633,0)) -> 0.0041922216 | E61: =REPT("|",MAX(1,ROUND(D61*60,0))) -> |
B63: Now visit Training Example and Backpropagation to see how the model got its weights, and Circuits & Activations to see why it chose this word.

Sheet Training Example
B1: ONE REAL TRAINING EXAMPLE, LIVE
B2: Training data is just the book, cut into 10-word windows plus the word that came next. Here is one of the 26,673.
B4: THE EXAMPLE (yellow = editable; the default is a real passage from chapter 1)
B5: w1 | C5: w2 | D5: w3 | E5: w4 | F5: w5 | G5: w6 | H5: w7 | I5: w8 | J5: w9 | K5: w10
B6: there | C6: was | D6: nothing | E6: so | F6: very | G6: remarkable | H6: in | I6: that | J6: nor | K6: did
B7: target (the word that ACTUALLY came next in the book):
B8: alice | C8: <- "...nor did Alice think it so very much out of the way..."
B10: FORWARD PASS (identical math to the Prompt tab)
B11: =IFERROR(MATCH(TRIM(SUBSTITUTE(SUBSTITUTE(SUBSTITUTE(SUBSTITUTE(LOWER(B6),".",""),",",""),"!",""),"?","")),Vocabulary!$B$2:$B$2629,0),1) -> 57 | C11: =IFERROR(MATCH(TRIM(SUBSTITUTE(SUBSTITUTE(SUBSTITUTE(SUBSTITUTE(LOWER(C6),".",""),",",""),"!",""),"?","")),Vocabulary!$B$2:$B$2629,0),1) -> 14 | D11: =IFERROR(MATCH(TRIM(SUBSTITUTE(SUBSTITUTE(SUBSTITUTE(SUBSTITUTE(LOWER(D6),".",""),",",""),"!",""),"?","")),Vocabulary!$B$2:$B$2629,0),1) -> 131 | E11: =IFERROR(MATCH(TRIM(SUBSTITUTE(SUBSTITUTE(SUBSTITUTE(SUBSTITUTE(LOWER(E6),".",""),",",""),"!",""),"?","")),Vocabulary!$B$2:$B$2629,0),1) -> 25 | F11: =IFERROR(MATCH(TRIM(SUBSTITUTE(SUBSTITUTE(SUBSTITUTE(SUBSTITUTE(LOWER(F6),".",""),",",""),"!",""),"?","")),Vocabulary!$B$2:$B$2629,0),1) -> 28 | G11: =IFERROR(MATCH(TRIM(SUBSTITUTE(SUBSTITUTE(SUBSTITUTE(SUBSTITUTE(LOWER(G6),".",""),",",""),"!",""),"?","")),Vocabulary!$B$2:$B$2629,0),1) -> 1083 | H11: =IFERROR(MATCH(TRIM(SUBSTITUTE(SUBSTITUTE(SUBSTITUTE(SUBSTITUTE(LOWER(H6),".",""),",",""),"!",""),"?","")),Vocabulary!$B$2:$B$2629,0),1) -> 12 | I11: =IFERROR(MATCH(TRIM(SUBSTITUTE(SUBSTITUTE(SUBSTITUTE(SUBSTITUTE(LOWER(I6),".",""),",",""),"!",""),"?","")),Vocabulary!$B$2:$B$2629,0),1) -> 15 | ... K11: =IFERROR(MATCH(TRIM(SUBSTITUTE(SUBSTITUTE(SUBSTITUTE(SUBSTITUTE(LOWER(K6),".",""),",",""),"!",""),"?","")),Vocabulary!$B$2:$B$2629,0),1) -> 67
B13: target token ID: | C13: =IFERROR(MATCH(TRIM(SUBSTITUTE(SUBSTITUTE(SUBSTITUTE(SUBSTITUTE(LOWER(B8),".",""),",",""),"!",""),"?","")),Vocabulary!$B$2:$B$2629,0),1) -> 11
B15: token | C15: d1 | D15: d2 | E15: d3 | F15: d4 | G15: d5 | H15: d6 | I15: d7 | J15: d8 | K15: d9 | L15: d10 | M15: d11 | N15: d12 | O15: d13 | P15: d14 | Q15: d15 | R15: d16
B16: =B6 -> there | C16: =INDEX(Embeddings!$C$2:$R$2629,B$11,COLUMN()-2) -> -0.40301 | D16: =INDEX(Embeddings!$C$2:$R$2629,B$11,COLUMN()-2) -> -1.50844 | E16: =INDEX(Embeddings!$C$2:$R$2629,B$11,COLUMN()-2) -> 0.04131 | F16: =INDEX(Embeddings!$C$2:$R$2629,B$11,COLUMN()-2) -> -1.50042 | G16: =INDEX(Embeddings!$C$2:$R$2629,B$11,COLUMN()-2) -> -0.7171 | H16: =INDEX(Embeddings!$C$2:$R$2629,B$11,COLUMN()-2) -> 0.51543 | I16: =INDEX(Embeddings!$C$2:$R$2629,B$11,COLUMN()-2) -> 0.76644 | J16: =INDEX(Embeddings!$C$2:$R$2629,B$11,COLUMN()-2) -> 0.10743 | K16: =INDEX(Embeddings!$C$2:$R$2629,B$11,COLUMN()-2) -> 0.23841 | L16: =INDEX(Embeddings!$C$2:$R$2629,B$11,COLUMN()-2) -> 0.20922 | M16: =INDEX(Embeddings!$C$2:$R$2629,B$11,COLUMN()-2) -> -0.21415 | N16: =INDEX(Embeddings!$C$2:$R$2629,B$11,COLUMN()-2) -> 0.48935 | O16: =INDEX(Embeddings!$C$2:$R$2629,B$11,COLUMN()-2) -> -1.17285 | P16: =INDEX(Embeddings!$C$2:$R$2629,B$11,COLUMN()-2) -> -0.1599 | Q16: =INDEX(Embeddings!$C$2:$R$2629,B$11,COLUMN()-2) -> -0.50172 | R16: =INDEX(Embeddings!$C$2:$R$2629,B$11,COLUMN()-2) -> -1.22955
B17: =C6 -> was | C17: =INDEX(Embeddings!$C$2:$R$2629,C$11,COLUMN()-2) -> 1.01562 | D17: =INDEX(Embeddings!$C$2:$R$2629,C$11,COLUMN()-2) -> 0.2853 | E17: =INDEX(Embeddings!$C$2:$R$2629,C$11,COLUMN()-2) -> 1.23108 | F17: =INDEX(Embeddings!$C$2:$R$2629,C$11,COLUMN()-2) -> 1.28132 | G17: =INDEX(Embeddings!$C$2:$R$2629,C$11,COLUMN()-2) -> 0.15807 | H17: =INDEX(Embeddings!$C$2:$R$2629,C$11,COLUMN()-2) -> -0.50829 | I17: =INDEX(Embeddings!$C$2:$R$2629,C$11,COLUMN()-2) -> 0.68136 | J17: =INDEX(Embeddings!$C$2:$R$2629,C$11,COLUMN()-2) -> -0.36745 | K17: =INDEX(Embeddings!$C$2:$R$2629,C$11,COLUMN()-2) -> -0.2726 | L17: =INDEX(Embeddings!$C$2:$R$2629,C$11,COLUMN()-2) -> 0.58087 | M17: =INDEX(Embeddings!$C$2:$R$2629,C$11,COLUMN()-2) -> -0.71129 | N17: =INDEX(Embeddings!$C$2:$R$2629,C$11,COLUMN()-2) -> 0.19566 | O17: =INDEX(Embeddings!$C$2:$R$2629,C$11,COLUMN()-2) -> -0.06524 | P17: =INDEX(Embeddings!$C$2:$R$2629,C$11,COLUMN()-2) -> 0.17833 | Q17: =INDEX(Embeddings!$C$2:$R$2629,C$11,COLUMN()-2) -> -0.78746 | R17: =INDEX(Embeddings!$C$2:$R$2629,C$11,COLUMN()-2) -> 0.36907
B18: =D6 -> nothing | C18: =INDEX(Embeddings!$C$2:$R$2629,D$11,COLUMN()-2) -> 0.24121 | D18: =INDEX(Embeddings!$C$2:$R$2629,D$11,COLUMN()-2) -> -1.14959 | E18: =INDEX(Embeddings!$C$2:$R$2629,D$11,COLUMN()-2) -> 1.20992 | F18: =INDEX(Embeddings!$C$2:$R$2629,D$11,COLUMN()-2) -> 0.01043 | G18: =INDEX(Embeddings!$C$2:$R$2629,D$11,COLUMN()-2) -> -0.54161 | H18: =INDEX(Embeddings!$C$2:$R$2629,D$11,COLUMN()-2) -> -0.13122 | I18: =INDEX(Embeddings!$C$2:$R$2629,D$11,COLUMN()-2) -> -0.06199 | J18: =INDEX(Embeddings!$C$2:$R$2629,D$11,COLUMN()-2) -> 1.41663 | K18: =INDEX(Embeddings!$C$2:$R$2629,D$11,COLUMN()-2) -> 0.48902 | L18: =INDEX(Embeddings!$C$2:$R$2629,D$11,COLUMN()-2) -> -0.91963 | M18: =INDEX(Embeddings!$C$2:$R$2629,D$11,COLUMN()-2) -> 0.0858 | N18: =INDEX(Embeddings!$C$2:$R$2629,D$11,COLUMN()-2) -> -1.20417 | O18: =INDEX(Embeddings!$C$2:$R$2629,D$11,COLUMN()-2) -> 0.02562 | P18: =INDEX(Embeddings!$C$2:$R$2629,D$11,COLUMN()-2) -> -0.3223 | Q18: =INDEX(Embeddings!$C$2:$R$2629,D$11,COLUMN()-2) -> 0.33102 | R18: =INDEX(Embeddings!$C$2:$R$2629,D$11,COLUMN()-2) -> -0.30852
B19: =E6 -> so | C19: =INDEX(Embeddings!$C$2:$R$2629,E$11,COLUMN()-2) -> -0.42381 | D19: =INDEX(Embeddings!$C$2:$R$2629,E$11,COLUMN()-2) -> 0.59214 | E19: =INDEX(Embeddings!$C$2:$R$2629,E$11,COLUMN()-2) -> -0.10978 | F19: =INDEX(Embeddings!$C$2:$R$2629,E$11,COLUMN()-2) -> -0.07921 | G19: =INDEX(Embeddings!$C$2:$R$2629,E$11,COLUMN()-2) -> 0.13794 | H19: =INDEX(Embeddings!$C$2:$R$2629,E$11,COLUMN()-2) -> -0.24033 | I19: =INDEX(Embeddings!$C$2:$R$2629,E$11,COLUMN()-2) -> 0.51734 | J19: =INDEX(Embeddings!$C$2:$R$2629,E$11,COLUMN()-2) -> -1.13292 | K19: =INDEX(Embeddings!$C$2:$R$2629,E$11,COLUMN()-2) -> -0.56784 | L19: =INDEX(Embeddings!$C$2:$R$2629,E$11,COLUMN()-2) -> 0.04557 | M19: =INDEX(Embeddings!$C$2:$R$2629,E$11,COLUMN()-2) -> -0.13465 | N19: =INDEX(Embeddings!$C$2:$R$2629,E$11,COLUMN()-2) -> 0.92854 | O19: =INDEX(Embeddings!$C$2:$R$2629,E$11,COLUMN()-2) -> 0.19515 | P19: =INDEX(Embeddings!$C$2:$R$2629,E$11,COLUMN()-2) -> -0.39203 | Q19: =INDEX(Embeddings!$C$2:$R$2629,E$11,COLUMN()-2) -> -0.06775 | R19: =INDEX(Embeddings!$C$2:$R$2629,E$11,COLUMN()-2) -> -0.99232
B20: =F6 -> very | C20: =INDEX(Embeddings!$C$2:$R$2629,F$11,COLUMN()-2) -> -0.37809 | D20: =INDEX(Embeddings!$C$2:$R$2629,F$11,COLUMN()-2) -> 0.4452 | E20: =INDEX(Embeddings!$C$2:$R$2629,F$11,COLUMN()-2) -> -0.5399 | F20: =INDEX(Embeddings!$C$2:$R$2629,F$11,COLUMN()-2) -> 0.13263 | G20: =INDEX(Embeddings!$C$2:$R$2629,F$11,COLUMN()-2) -> 0.44191 | H20: =INDEX(Embeddings!$C$2:$R$2629,F$11,COLUMN()-2) -> 0.90927 | I20: =INDEX(Embeddings!$C$2:$R$2629,F$11,COLUMN()-2) -> -1.64907 | J20: =INDEX(Embeddings!$C$2:$R$2629,F$11,COLUMN()-2) -> -0.17889 | K20: =INDEX(Embeddings!$C$2:$R$2629,F$11,COLUMN()-2) -> -0.33347 | L20: =INDEX(Embeddings!$C$2:$R$2629,F$11,COLUMN()-2) -> -1.15924 | M20: =INDEX(Embeddings!$C$2:$R$2629,F$11,COLUMN()-2) -> 0.12384 | N20: =INDEX(Embeddings!$C$2:$R$2629,F$11,COLUMN()-2) -> 0.8915 | O20: =INDEX(Embeddings!$C$2:$R$2629,F$11,COLUMN()-2) -> 0.25877 | P20: =INDEX(Embeddings!$C$2:$R$2629,F$11,COLUMN()-2) -> -0.23541 | Q20: =INDEX(Embeddings!$C$2:$R$2629,F$11,COLUMN()-2) -> -0.90271 | R20: =INDEX(Embeddings!$C$2:$R$2629,F$11,COLUMN()-2) -> -0.46625
B21: =G6 -> remarkable | C21: =INDEX(Embeddings!$C$2:$R$2629,G$11,COLUMN()-2) -> 1.93622 | D21: =INDEX(Embeddings!$C$2:$R$2629,G$11,COLUMN()-2) -> -0.68936 | E21: =INDEX(Embeddings!$C$2:$R$2629,G$11,COLUMN()-2) -> 0.54856 | F21: =INDEX(Embeddings!$C$2:$R$2629,G$11,COLUMN()-2) -> -0.48967 | G21: =INDEX(Embeddings!$C$2:$R$2629,G$11,COLUMN()-2) -> -0.28349 | H21: =INDEX(Embeddings!$C$2:$R$2629,G$11,COLUMN()-2) -> 0.76515 | I21: =INDEX(Embeddings!$C$2:$R$2629,G$11,COLUMN()-2) -> 0.16178 | J21: =INDEX(Embeddings!$C$2:$R$2629,G$11,COLUMN()-2) -> 4.61985 | K21: =INDEX(Embeddings!$C$2:$R$2629,G$11,COLUMN()-2) -> -0.86611 | L21: =INDEX(Embeddings!$C$2:$R$2629,G$11,COLUMN()-2) -> 0.1819 | M21: =INDEX(Embeddings!$C$2:$R$2629,G$11,COLUMN()-2) -> -2.30708 | N21: =INDEX(Embeddings!$C$2:$R$2629,G$11,COLUMN()-2) -> -2.1742 | O21: =INDEX(Embeddings!$C$2:$R$2629,G$11,COLUMN()-2) -> -4.03665 | P21: =INDEX(Embeddings!$C$2:$R$2629,G$11,COLUMN()-2) -> -1.90836 | Q21: =INDEX(Embeddings!$C$2:$R$2629,G$11,COLUMN()-2) -> 0.5517 | R21: =INDEX(Embeddings!$C$2:$R$2629,G$11,COLUMN()-2) -> -0.12093
B22: =H6 -> in | C22: =INDEX(Embeddings!$C$2:$R$2629,H$11,COLUMN()-2) -> 0.24412 | D22: =INDEX(Embeddings!$C$2:$R$2629,H$11,COLUMN()-2) -> -0.72087 | E22: =INDEX(Embeddings!$C$2:$R$2629,H$11,COLUMN()-2) -> 1.28378 | F22: =INDEX(Embeddings!$C$2:$R$2629,H$11,COLUMN()-2) -> 0.03207 | G22: =INDEX(Embeddings!$C$2:$R$2629,H$11,COLUMN()-2) -> -0.46749 | H22: =INDEX(Embeddings!$C$2:$R$2629,H$11,COLUMN()-2) -> 0.24337 | I22: =INDEX(Embeddings!$C$2:$R$2629,H$11,COLUMN()-2) -> 1.59235 | J22: =INDEX(Embeddings!$C$2:$R$2629,H$11,COLUMN()-2) -> -0.97802 | K22: =INDEX(Embeddings!$C$2:$R$2629,H$11,COLUMN()-2) -> -0.1698 | L22: =INDEX(Embeddings!$C$2:$R$2629,H$11,COLUMN()-2) -> -0.89184 | M22: =INDEX(Embeddings!$C$2:$R$2629,H$11,COLUMN()-2) -> 0.03846 | N22: =INDEX(Embeddings!$C$2:$R$2629,H$11,COLUMN()-2) -> 0.41749 | O22: =INDEX(Embeddings!$C$2:$R$2629,H$11,COLUMN()-2) -> 0.25886 | P22: =INDEX(Embeddings!$C$2:$R$2629,H$11,COLUMN()-2) -> 0.95634 | Q22: =INDEX(Embeddings!$C$2:$R$2629,H$11,COLUMN()-2) -> -1.33422 | R22: =INDEX(Embeddings!$C$2:$R$2629,H$11,COLUMN()-2) -> 0.60227 | U22: max logit | V22: =MAX(V24:V2651) -> 16.16066 | W22: sum of exp | X22: =SUM(W24:W2651) -> 3.6070062
B23: =I6 -> that | C23: =INDEX(Embeddings!$C$2:$R$2629,I$11,COLUMN()-2) -> -0.26994 | D23: =INDEX(Embeddings!$C$2:$R$2629,I$11,COLUMN()-2) -> -0.27285 | E23: =INDEX(Embeddings!$C$2:$R$2629,I$11,COLUMN()-2) -> -0.71564 | F23: =INDEX(Embeddings!$C$2:$R$2629,I$11,COLUMN()-2) -> -0.61836 | G23: =INDEX(Embeddings!$C$2:$R$2629,I$11,COLUMN()-2) -> -0.45482 | H23: =INDEX(Embeddings!$C$2:$R$2629,I$11,COLUMN()-2) -> -0.23998 | I23: =INDEX(Embeddings!$C$2:$R$2629,I$11,COLUMN()-2) -> -0.37378 | J23: =INDEX(Embeddings!$C$2:$R$2629,I$11,COLUMN()-2) -> -0.16345 | K23: =INDEX(Embeddings!$C$2:$R$2629,I$11,COLUMN()-2) -> -0.42537 | L23: =INDEX(Embeddings!$C$2:$R$2629,I$11,COLUMN()-2) -> -0.57902 | M23: =INDEX(Embeddings!$C$2:$R$2629,I$11,COLUMN()-2) -> 0.90195 | N23: =INDEX(Embeddings!$C$2:$R$2629,I$11,COLUMN()-2) -> 0.24819 | O23: =INDEX(Embeddings!$C$2:$R$2629,I$11,COLUMN()-2) -> -0.14958 | P23: =INDEX(Embeddings!$C$2:$R$2629,I$11,COLUMN()-2) -> 0.18556 | Q23: =INDEX(Embeddings!$C$2:$R$2629,I$11,COLUMN()-2) -> -0.20946 | R23: =INDEX(Embeddings!$C$2:$R$2629,I$11,COLUMN()-2) -> -0.5086 | T23: ID | U23: Word | V23: Logit | W23: EXP(L-max) | X23: p | Y23: y (truth)
B24: =J6 -> nor | C24: =INDEX(Embeddings!$C$2:$R$2629,J$11,COLUMN()-2) -> -1.15119 | D24: =INDEX(Embeddings!$C$2:$R$2629,J$11,COLUMN()-2) -> -2.00911 | E24: =INDEX(Embeddings!$C$2:$R$2629,J$11,COLUMN()-2) -> 2.3615 | F24: =INDEX(Embeddings!$C$2:$R$2629,J$11,COLUMN()-2) -> 1.08665 | G24: =INDEX(Embeddings!$C$2:$R$2629,J$11,COLUMN()-2) -> 0.57331 | H24: =INDEX(Embeddings!$C$2:$R$2629,J$11,COLUMN()-2) -> -2.75858 | I24: =INDEX(Embeddings!$C$2:$R$2629,J$11,COLUMN()-2) -> 3.22169 | J24: =INDEX(Embeddings!$C$2:$R$2629,J$11,COLUMN()-2) -> -0.88452 | K24: =INDEX(Embeddings!$C$2:$R$2629,J$11,COLUMN()-2) -> -0.22934 | L24: =INDEX(Embeddings!$C$2:$R$2629,J$11,COLUMN()-2) -> 0.11695 | M24: =INDEX(Embeddings!$C$2:$R$2629,J$11,COLUMN()-2) -> -0.33952 | N24: =INDEX(Embeddings!$C$2:$R$2629,J$11,COLUMN()-2) -> 1.22448 | O24: =INDEX(Embeddings!$C$2:$R$2629,J$11,COLUMN()-2) -> -0.41665 | P24: =INDEX(Embeddings!$C$2:$R$2629,J$11,COLUMN()-2) -> 1.03392 | Q24: =INDEX(Embeddings!$C$2:$R$2629,J$11,COLUMN()-2) -> -0.62461 | R24: =INDEX(Embeddings!$C$2:$R$2629,J$11,COLUMN()-2) -> 1.22691 | T24: 1 | U24: =Vocabulary!B2 -> <unk> | V24: {=MMULT('Output Weights'!$C$2:$R$2629,TRANSPOSE($C$32:$R$32))} -> 0 | W24: =EXP(V24-$V$22) -> 9.5832903e-08 | X24: =W24/$X$22 -> 2.6568544e-08 | Y24: =IF(T24=$C$13,1,0) -> 0
B25: =K6 -> did | C25: =INDEX(Embeddings!$C$2:$R$2629,K$11,COLUMN()-2) -> -0.32301 | D25: =INDEX(Embeddings!$C$2:$R$2629,K$11,COLUMN()-2) -> -0.09104 | E25: =INDEX(Embeddings!$C$2:$R$2629,K$11,COLUMN()-2) -> 1.11213 | F25: =INDEX(Embeddings!$C$2:$R$2629,K$11,COLUMN()-2) -> 1.0146 | G25: =INDEX(Embeddings!$C$2:$R$2629,K$11,COLUMN()-2) -> 0.31299 | H25: =INDEX(Embeddings!$C$2:$R$2629,K$11,COLUMN()-2) -> -0.72875 | I25: =INDEX(Embeddings!$C$2:$R$2629,K$11,COLUMN()-2) -> 0.8719 | J25: =INDEX(Embeddings!$C$2:$R$2629,K$11,COLUMN()-2) -> 0.55997 | K25: =INDEX(Embeddings!$C$2:$R$2629,K$11,COLUMN()-2) -> -1.14787 | L25: =INDEX(Embeddings!$C$2:$R$2629,K$11,COLUMN()-2) -> -0.98815 | M25: =INDEX(Embeddings!$C$2:$R$2629,K$11,COLUMN()-2) -> 0.71389 | N25: =INDEX(Embeddings!$C$2:$R$2629,K$11,COLUMN()-2) -> -0.13227 | O25: =INDEX(Embeddings!$C$2:$R$2629,K$11,COLUMN()-2) -> 0.80422 | P25: =INDEX(Embeddings!$C$2:$R$2629,K$11,COLUMN()-2) -> 2.10415 | Q25: =INDEX(Embeddings!$C$2:$R$2629,K$11,COLUMN()-2) -> 1.04718 | R25: =INDEX(Embeddings!$C$2:$R$2629,K$11,COLUMN()-2) -> -1.27802 | T25: 2 | U25: =Vocabulary!B3 -> the | V25: 15.894399 | W25: =EXP(V25-$V$22) -> 0.76623902 | X25: =W25/$X$22 -> 0.21243075 | Y25: =IF(T25=$C$13,1,0) -> 0
B26: learned attention weights (fixed values here; play with them on the Prompt tab): | T26: 3 | U26: =Vocabulary!B4 -> and | V26: 6.0219485 | W26: =EXP(V26-$V$22) -> 3.9519702e-05 | X26: =W26/$X$22 -> 1.0956372e-05 | Y26: =IF(T26=$C$13,1,0) -> 0
B27: 0.0274 | C27: 0.0382 | D27: 0.0384 | E27: 0.0363 | F27: 0.0419 | G27: 0.052 | H27: 0.0748 | I27: 0.1105 | J27: 0.1788 | K27: 0.4016 | T27: 4 | U27: =Vocabulary!B5 -> to | V27: 13.769127 | W27: =EXP(V27-$V$22) -> 0.091489361 | X27: =W27/$X$22 -> 0.025364348 | Y27: =IF(T27=$C$13,1,0) -> 0
T28: 5 | U28: =Vocabulary!B6 -> a | V28: 13.181439 | W28: =EXP(V28-$V$22) -> 0.050832439 | X28: =W28/$X$22 -> 0.014092695 | Y28: =IF(T28=$C$13,1,0) -> 0
B29: context c = | C29: {=MMULT(B27:K27,C16:R25)} -> -0.24064794 | D29: -0.55013674 | E29: 0.98235451 | F29: 0.5212809 | G29: 0.11735243 | H29: -0.73538433 | I29: 1.0067423 | J29: 0.21043195 | K29: -0.62642023 | L29: -0.55147282 | M29: 0.179123 | N29: 0.15711437 | O29: 0.025688028 | P29: 0.98865569 | Q29: 0.14321083 | R29: -0.39831564 | T29: 6 | U29: =Vocabulary!B7 -> she | V29: 8.7207566 | W29: =EXP(V29-$V$22) -> 0.00058734208 | X29: =W29/$X$22 -> 0.00016283368 | Y29: =IF(T29=$C$13,1,0) -> 0
T30: 7 | U30: =Vocabulary!B8 -> it | V30: 16.16066 | W30: =EXP(V30-$V$22) -> 1 | X30: =W30/$X$22 -> 0.27723823 | Y30: =IF(T30=$C$13,1,0) -> 0
B31: c x W = | C31: {=MMULT(C29:R29,'Hidden Weights'!$C$3:$R$18)} -> -8.9178281 | D31: 13.696411 | E31: -3.6590479 | F31: -4.2541123 | G31: -5.0250493 | H31: -11.157479 | I31: -0.74667388 | J31: -3.6617326 | K31: 5.1657708 | L31: -0.63048196 | M31: -1.9880423 | N31: -3.6878053 | O31: 14.928681 | P31: 2.0403137 | Q31: -18.247869 | R31: 1.2985629 | T31: 8 | U31: =Vocabulary!B9 -> of | V31: 2.2627901 | W31: =EXP(V31-$V$22) -> 9.2094116e-07 | X31: =W31/$X$22 -> 2.553201e-07 | Y31: =IF(T31=$C$13,1,0) -> 0
B32: h = TANH: | C32: =TANH(C31) -> -0.99999996 | D32: =TANH(D31) -> 1 | E32: =TANH(E31) -> -0.99867403 | F32: =TANH(F31) -> -0.99959648 | G32: =TANH(G31) -> -0.99991364 | H32: =TANH(H31) -> -1 | I32: =TANH(I31) -> -0.63316045 | J32: =TANH(J31) -> -0.99868113 | ... R32: =TANH(R31) -> 0.86135274 | T32: 9 | U32: =Vocabulary!B10 -> said | V32: 14.71554 | W32: =EXP(V32-$V$22) -> 0.23571788 | X32: =W32/$X$22 -> 0.065350008 | Y32: =IF(T32=$C$13,1,0) -> 0
T33: 10 | U33: =Vocabulary!B11 -> i | V33: 10.500303 | W33: =EXP(V33-$V$22) -> 0.0034812748 | X33: =W33/$X$22 -> 0.00096514245 | Y33: =IF(T33=$C$13,1,0) -> 0
B34: THE LOSS: HOW SURPRISED WAS THE MODEL BY THE TRUTH? | T34: 11 | U34: =Vocabulary!B12 -> alice | V34: 14.110405 | W34: =EXP(V34-$V$22) -> 0.12870213 | X34: =W34/$X$22 -> 0.03568115 | Y34: =IF(T34=$C$13,1,0) -> 1
B35: The tall table at the right (columns T-Y) scores all 2628 words, exactly like the Prediction tab (temperature 1). | T35: 12 | U35: =Vocabulary!B13 -> in | V35: 10.301198 | W35: =EXP(V35-$V$22) -> 0.0028527779 | X35: =W35/$X$22 -> 0.00079089908 | Y35: =IF(T35=$C$13,1,0) -> 0
B36: p(target): probability given to the true word | F36: =INDEX($X$24:$X$2651,$C$13) -> 0.03568115 | T36: 13 | U36: =Vocabulary!B14 -> you | V36: 14.220028 | W36: =EXP(V36-$V$22) -> 0.1436132 | X36: =W36/$X$22 -> 0.03981507 | Y36: =IF(T36=$C$13,1,0) -> 0
B37: LOSS = -LN(p(target)) | F37: =-LN(F36) -> 3.3331327 | T37: 14 | U37: =Vocabulary!B15 -> was | V37: -0.91838449 | W37: =EXP(V37-$V$22) -> 3.8252985e-08 | X37: =W37/$X$22 -> 1.060519e-08 | Y37: =IF(T37=$C$13,1,0) -> 0
B38: the model's own top pick was: | F38: =INDEX($U$24:$U$2651,MATCH(MAX($X$24:$X$2651),$X$24:$X$2651,0)) -> it | T38: 15 | U38: =Vocabulary!B16 -> that | V38: 11.160273 | W38: =EXP(V38-$V$22) -> 0.0067353417 | X38: =W38/$X$22 -> 0.0018672942 | Y38: =IF(T38=$C$13,1,0) -> 0
B39: A perfect model gives p(target)=100% and loss 0. Blind guessing gives p=1/2628, loss 7.87. Training is nothing more than making this one number smaller, averaged over the whole book. When the top pick is not the target, the gradients on the Backpropagation tab are big. | T39: 16 | U39: =Vocabulary!B17 -> as | V39: 11.186643 | W39: =EXP(V39-$V$22) -> 0.0069153125 | X39: =W39/$X$22 -> 0.001917189 | Y39: =IF(T39=$C$13,1,0) -> 0
T40: 17 | U40: =Vocabulary!B18 -> her | V40: 11.683058 | W40: =EXP(V40-$V$22) -> 0.011360624 | X40: =W40/$X$22 -> 0.0031495992 | Y40: =IF(T40=$C$13,1,0) -> 0
B41: Try it: change the target to "computer" (loss explodes: the model can never predict <unk>-adjacent nonsense) or swap the context words and watch loss, h, and every gradient react. | T41: 18 | U41: =Vocabulary!B19 -> at | V41: 12.997749 | W41: =EXP(V41-$V$22) -> 0.042302443 | X41: =W41/$X$22 -> 0.011727854 | Y41: =IF(T41=$C$13,1,0) -> 0
T42: 19 | U42: =Vocabulary!B20 -> on | V42: 8.8878884 | W42: =EXP(V42-$V$22) -> 0.00069418547 | X42: =W42/$X$22 -> 0.00019245475 | Y42: =IF(T42=$C$13,1,0) -> 0
T43: 20 | U43: =Vocabulary!B21 -> all | V43: 11.953017 | W43: =EXP(V43-$V$22) -> 0.014881406 | X43: =W43/$X$22 -> 0.0041256945 | Y43: =IF(T43=$C$13,1,0) -> 0
T44: 21 | U44: =Vocabulary!B22 -> with | V44: 7.8000758 | W44: =EXP(V44-$V$22) -> 0.00023390771 | X44: =W44/$X$22 -> 6.4848158e-05 | Y44: =IF(T44=$C$13,1,0) -> 0
T45: 22 | U45: =Vocabulary!B23 -> had | V45: 3.5132642 | W45: =EXP(V45-$V$22) -> 3.215925e-06 | X45: =W45/$X$22 -> 8.9157736e-07 | Y45: =IF(T45=$C$13,1,0) -> 0
T46: 23 | U46: =Vocabulary!B24 -> but | V46: 6.786557 | W46: =EXP(V46-$V$22) -> 8.489437e-05 | X46: =W46/$X$22 -> 2.3535965e-05 | Y46: =IF(T46=$C$13,1,0) -> 0
T47: 24 | U47: =Vocabulary!B25 -> for | V47: 13.880719 | W47: =EXP(V47-$V$22) -> 0.10229027 | X47: =W47/$X$22 -> 0.028358773 | Y47: =IF(T47=$C$13,1,0) -> 0
T48: 25 | U48: =Vocabulary!B26 -> so | V48: 13.138501 | W48: =EXP(V48-$V$22) -> 0.048695975 | X48: =W48/$X$22 -> 0.013500386 | Y48: =IF(T48=$C$13,1,0) -> 0
T49: 26 | U49: =Vocabulary!B27 -> be | V49: 5.6434871 | W49: =EXP(V49-$V$22) -> 2.7067613e-05 | X49: =W49/$X$22 -> 7.5041771e-06 | Y49: =IF(T49=$C$13,1,0) -> 0
T50: 27 | U50: =Vocabulary!B28 -> not | V50: 15.421135 | W50: =EXP(V50-$V$22) -> 0.47734083 | X50: =W50/$X$22 -> 0.13233713 | Y50: =IF(T50=$C$13,1,0) -> 0
T51: 28 | U51: =Vocabulary!B29 -> very | V51: 11.555806 | W51: =EXP(V51-$V$22) -> 0.010003168 | X51: =W51/$X$22 -> 0.0027732605 | Y51: =IF(T51=$C$13,1,0) -> 0
T52: 29 | U52: =Vocabulary!B30 -> what | V52: 9.9303138 | W52: =EXP(V52-$V$22) -> 0.0019687708 | X52: =W52/$X$22 -> 0.00054581851 | Y52: =IF(T52=$C$13,1,0) -> 0
T53: 30 | U53: =Vocabulary!B31 -> this | V53: 13.090312 | W53: =EXP(V53-$V$22) -> 0.046405032 | X53: =W53/$X$22 -> 0.012865249 | Y53: =IF(T53=$C$13,1,0) -> 0
... T2651: 2628 | U2651: =Vocabulary!B2629 -> happy | V2651: -15.456182 | W2651: =EXP(V2651-$V$22) -> 1.8577196e-14 | X2651: =W2651/$X$22 -> 5.1503088e-15 | Y2651: =IF(T2651=$C$13,1,0) -> 0

Sheet Backpropagation
B1: BACKPROPAGATION: HOW THE WEIGHTS LEARN
B2: The real gradients for the Training Example, live. Change that tab and every number here follows. Chain rule, as spreadsheet formulas.
B4: STEP 1 · THE ERROR SIGNAL: g = p - y, for every word
B5: Take each word's predicted probability p and subtract 1 if it was the true word. That single subtraction IS the
B6: derivative of cross-entropy loss with respect to each logit. Positive g = scored too high; the target alone goes negative.
B7: target ID | C7: ='Training Example'!$C$13 -> 11 | E7: g at the target | G7: =INDEX($V$24:$V$2651,$C$7) -> -0.96431885 | I7: top-pick ID | K7: =MATCH(MAX('Training Example'!$X$24:$X$2651),'Training Example'!$X$24:$X$2651,0) -> 7
B8: The full g column is the tall table at the right (columns T-V).
B10: STEP 2 · GRADIENT OF THE OUTPUT WEIGHTS: dOut(word) = g(word) x h (two example rows)
B11: word | C11: d1 | D11: d2 | E11: d3 | F11: d4 | G11: d5 | H11: d6 | I11: d7 | J11: d8 | K11: d9 | L11: d10 | M11: d11 | N11: d12 | O11: d13 | P11: d14 | Q11: d15 | R11: d16
B12: =INDEX(Vocabulary!$B$2:$B$2629,$C$7)&" (target)" -> alice (target) | C12: =INDEX($V$24:$V$2651,$C$7)*'Training Example'!C$32 -> 0.96431882 | D12: =INDEX($V$24:$V$2651,$C$7)*'Training Example'!D$32 -> -0.96431885 | E12: =INDEX($V$24:$V$2651,$C$7)*'Training Example'!E$32 -> 0.96304019 | F12: =INDEX($V$24:$V$2651,$C$7)*'Training Example'!F$32 -> 0.96392973 | G12: =INDEX($V$24:$V$2651,$C$7)*'Training Example'!G$32 -> 0.96423557 | H12: =INDEX($V$24:$V$2651,$C$7)*'Training Example'!H$32 -> 0.96431885 | I12: =INDEX($V$24:$V$2651,$C$7)*'Training Example'!I$32 -> 0.61056855 | J12: =INDEX($V$24:$V$2651,$C$7)*'Training Example'!J$32 -> 0.96304704 | ... R12: =INDEX($V$24:$V$2651,$C$7)*'Training Example'!R$32 -> -0.83061868
B13: =INDEX(Vocabulary!$B$2:$B$2629,$K$7)&" (top pick)" -> it (top pick) | C13: =INDEX($V$24:$V$2651,$K$7)*'Training Example'!C$32 -> -0.27723822 | D13: =INDEX($V$24:$V$2651,$K$7)*'Training Example'!D$32 -> 0.27723823 | E13: =INDEX($V$24:$V$2651,$K$7)*'Training Example'!E$32 -> -0.27687062 | F13: =INDEX($V$24:$V$2651,$K$7)*'Training Example'!F$32 -> -0.27712636 | G13: =INDEX($V$24:$V$2651,$K$7)*'Training Example'!G$32 -> -0.27721429 | H13: =INDEX($V$24:$V$2651,$K$7)*'Training Example'!H$32 -> -0.27723823 | I13: =INDEX($V$24:$V$2651,$K$7)*'Training Example'!I$32 -> -0.17553628 | J13: =INDEX($V$24:$V$2651,$K$7)*'Training Example'!J$32 -> -0.27687259 | ... R13: =INDEX($V$24:$V$2651,$K$7)*'Training Example'!R$32 -> 0.23879991
B14: Update rule subtracts the gradient, so the target's row (negative g) moves TOWARD h: its score rises next time. Wrong words with positive g get pushed away. Every one of the 2628 output rows gets this treatment at once.
B16: STEP 3 · BACK INTO THE HIDDEN VECTOR: dh = TRANSPOSE(g) MMULT OutputWeights (MMULT #4)
B17: dh = | C17: {=MMULT(TRANSPOSE($V$24:$V$2651),'Output Weights'!$C$2:$R$2629)} -> 0.76347777 | D17: -0.7232794 | E17: -1.1062617 | F17: 0.97937753 | G17: 0.16185461 | H17: -0.26318683 | I17: 0.56859733 | J17: -0.87429065 | K17: 1.076489 | L17: 0.64911169 | M17: -0.0082782768 | N17: 0.31993917 | O17: -0.16284695 | P17: -1.0055916 | Q17: -2.1457023 | R17: 0.24587539
B18: 16 numbers: how much the loss would drop if each hidden activation nudged down. A 1x2628 times 2628x16 MMULT.
B20: STEP 4 · BACK THROUGH TANH: dpre = dh x (1 - h^2)
B21: dpre = | C21: =C17*(1-'Training Example'!C$32^2) -> 5.4818775e-08 | D21: =D17*(1-'Training Example'!D$32^2) -> -3.6713226e-12 | E21: =E17*(1-'Training Example'!E$32^2) -> -0.0029317925 | F21: =F17*(1-'Training Example'!F$32^2) -> 0.00079024154 | G21: =G17*(1-'Training Example'!G$32^2) -> 2.7954078e-05 | H21: =H17*(1-'Training Example'!H$32^2) -> -2.1431922e-10 | I21: =I17*(1-'Training Example'!I$32^2) -> 0.34065112 | J21: =J17*(1-'Training Example'!J$32^2) -> -0.0023046361 | ... R21: =R17*(1-'Training Example'!R$32^2) -> 0.063453419
B22: The derivative of TANH(x) is 1 - TANH(x)^2. A saturated neuron (h near -1 or 1) passes almost no gradient: it has stopped learning. Compare h on the Training Example tab with dpre here.
T23: ID | U23: Word | V23: g = p - y
T24: 1 | U24: =Vocabulary!B2 -> <unk> | V24: ='Training Example'!X24-'Training Example'!Y24 -> 2.6568544e-08
B25: STEP 5 · GRADIENT OF THE HIDDEN WEIGHTS: dW = TRANSPOSE(c) MMULT dpre (MMULT #5: a 16x16 outer product) | T25: 2 | U25: =Vocabulary!B3 -> the | V25: ='Training Example'!X25-'Training Example'!Y25 -> 0.21243075
C26: to d1 | D26: to d2 | E26: to d3 | F26: to d4 | G26: to d5 | H26: to d6 | I26: to d7 | J26: to d8 | K26: to d9 | L26: to d10 | M26: to d11 | N26: to d12 | O26: to d13 | P26: to d14 | Q26: to d15 | R26: to d16 | T26: 3 | U26: =Vocabulary!B4 -> and | V26: ='Training Example'!X26-'Training Example'!Y26 -> 1.0956372e-05
B27: from d1 | C27: {=MMULT(TRANSPOSE('Training Example'!$C$29:$R$29),C21:R21)} -> -1.3192025e-08 | D27: 8.8349622e-13 | E27: 0.00070552983 | F27: -0.00019017 | G27: -6.7270914e-06 | H27: 5.1575479e-11 | I27: -0.081976992 | J27: 0.00055460595 | K27: -3.3766955e-05 | L27: -0.10750307 | M27: 0.00014402824 | N27: -0.00019265432 | O27: 1.6916023e-14 | P27: 0.015816704 | Q27: 0 | R27: -0.015269935 | T27: 4 | U27: =Vocabulary!B5 -> to | V27: ='Training Example'!X27-'Training Example'!Y27 -> 0.025364348
B28: from d2 | C28: -3.0157822e-08 | D28: 2.0197294e-12 | E28: 0.0016128868 | F28: -0.00043474091 | G28: -1.5378565e-05 | H28: 1.1790488e-10 | I28: -0.1874047 | J28: 0.001267865 | K28: -7.719344e-05 | L28: -0.24575896 | M28: 0.00032925785 | N28: -0.00044042022 | O28: 3.867112e-14 | P28: 0.036158008 | Q28: 0 | R28: -0.034908057 | T28: 5 | U28: =Vocabulary!B6 -> a | V28: ='Training Example'!X28-'Training Example'!Y28 -> 0.014092695
B29: from d3 | C29: 5.3851471e-08 | D29: -3.6065403e-12 | E29: -0.0028800596 | F29: 0.00077629734 | G29: 2.7460815e-05 | H29: -2.1053745e-10 | I29: 0.33464017 | J29: -0.0022639697 | K29: 0.00013784086 | L29: 0.43884076 | M29: -0.00058794098 | N29: 0.00078643863 | O29: -6.9053285e-14 | P29: -0.064565734 | Q29: 0 | R29: 0.062333752 | T29: 6 | U29: =Vocabulary!B7 -> she | V29: ='Training Example'!X29-'Training Example'!Y29 -> 0.00016283368
B30: from d4 | C30: 2.857598e-08 | D30: -1.9137903e-12 | E30: -0.0015282874 | F30: 0.00041193782 | G30: 1.4571927e-05 | H30: -1.1172051e-10 | I30: 0.17757492 | J30: -0.0012013628 | K30: 7.3144479e-05 | L30: 0.23286838 | M30: -0.00031198758 | N30: 0.00041731924 | O30: -3.6642738e-14 | P30: -0.034261444 | Q30: 0 | R30: 0.033077055 | T30: 7 | U30: =Vocabulary!B8 -> it | V30: ='Training Example'!X30-'Training Example'!Y30 -> 0.27723823
B31: from d5 | C31: 6.4331165e-09 | D31: -4.3083863e-13 | E31: -0.00034405298 | F31: 9.2736766e-05 | G31: 3.280479e-06 | H31: -2.5150881e-11 | I31: 0.039976237 | J31: -0.00027045465 | K31: 1.646652e-05 | L31: 0.052424079 | M31: -7.0235646e-05 | N31: 9.3948248e-05 | O31: -8.2491309e-15 | P31: -0.0077130463 | Q31: 0 | R31: 0.007446413 | T31: 8 | U31: =Vocabulary!B9 -> of | V31: ='Training Example'!X31-'Training Example'!Y31 -> 2.553201e-07
B32: from d6 | C32: -4.0312868e-08 | D32: 2.6998331e-12 | E32: 0.0021559942 | F32: -0.00058113125 | G32: -2.0556991e-05 | H32: 1.5760699e-10 | I32: -0.2505095 | J32: 0.0016947933 | K32: -0.00010318679 | L32: -0.3285134 | M32: 0.00044012887 | N32: -0.00058872295 | O32: 5.1692849e-14 | P32: 0.048333497 | Q32: 0 | R32: -0.04666265 | T32: 9 | U32: =Vocabulary!B10 -> said | V32: ='Training Example'!X32-'Training Example'!Y32 -> 0.065350008
B33: from d7 | C33: 5.5188378e-08 | D33: -3.6960756e-12 | E33: -0.0029515594 | F33: 0.00079556956 | G33: 2.8142552e-05 | H33: -2.1576422e-10 | I33: 0.34294788 | J33: -0.0023201746 | K33: 0.00014126288 | L33: 0.44973534 | M33: -0.0006025371 | N33: 0.00080596261 | O33: -7.076759e-14 | P33: -0.066168631 | Q33: 0 | R33: 0.063881239 | T33: 10 | U33: =Vocabulary!B11 -> i | V33: ='Training Example'!X33-'Training Example'!Y33 -> 0.00096514245
B34: from d8 | C34: 1.1535622e-08 | D34: -7.7256358e-13 | E34: -0.00061694282 | F34: 0.00016629207 | G34: 5.8824312e-06 | H34: -4.5099612e-11 | I34: 0.071683881 | J34: -0.00048496908 | K34: 2.9527143e-05 | L34: 0.09400488 | M34: -0.00012594391 | N34: 0.00016846445 | O34: -1.479203e-14 | P34: -0.013830744 | Q34: 0 | R34: 0.013352627 | T34: 11 | U34: =Vocabulary!B12 -> alice | V34: ='Training Example'!X34-'Training Example'!Y34 -> -0.96431885
B35: from d9 | C35: -3.433959e-08 | D35: 2.2997907e-12 | E35: 0.0018365341 | F35: -0.00049502329 | G35: -1.7511e-05 | H35: 1.3425389e-10 | I35: -0.21339076 | J35: 0.0014436707 | K35: -8.7897297e-05 | L35: -0.27983658 | M35: 0.00037491366 | N35: -0.00050149011 | O35: 4.4033365e-14 | P35: 0.041171778 | Q35: 0 | R35: -0.039748505 | T35: 12 | U35: =Vocabulary!B13 -> in | V35: ='Training Example'!X35-'Training Example'!Y35 -> 0.00079089908
B36: from d10 | C36: -3.0231064e-08 | D36: 2.0246346e-12 | E36: 0.0016168039 | F36: -0.00043579673 | G36: -1.5415914e-05 | H36: 1.1819122e-10 | I36: -0.18785983 | J36: 0.0012709442 | K36: -7.7380914e-05 | L36: -0.24635582 | M36: 0.0003300575 | N36: -0.00044148983 | O36: 3.8765038e-14 | P36: 0.036245822 | Q36: 0 | R36: -0.034992836 | T36: 13 | U36: =Vocabulary!B14 -> you | V36: ='Training Example'!X36-'Training Example'!Y36 -> 0.03981507
B37: from d11 | C37: 9.8193037e-09 | D37: -6.5761833e-13 | E37: -0.00052515148 | F37: 0.00014155044 | G37: 5.0072184e-06 | H37: -3.8389502e-11 | I37: 0.061018452 | J37: -0.00041281335 | K37: 2.5133971e-05 | L37: 0.08001844 | M37: -0.00010720545 | N37: 0.00014339961 | O37: -1.259121e-14 | P37: -0.011772948 | Q37: 0 | R37: 0.011365967 | T37: 14 | U37: =Vocabulary!B15 -> was | V37: ='Training Example'!X37-'Training Example'!Y37 -> 1.060519e-08
B38: from d12 | C38: 8.6128171e-09 | D38: -5.7681752e-13 | E38: -0.00046062671 | F38: 0.0001241583 | G38: 4.3919872e-06 | H38: -3.3672628e-11 | I38: 0.053521185 | J38: -0.00036209144 | K38: 2.2045789e-05 | L38: 0.070186666 | M38: -9.4033237e-05 | N38: 0.00012578026 | O38: -1.1044142e-14 | P38: -0.010326419 | Q38: 0 | R38: 0.0099694436 | T38: 15 | U38: =Vocabulary!B16 -> that | V38: ='Training Example'!X38-'Training Example'!Y38 -> 0.0018672942
B39: from d13 | C39: 1.4081862e-09 | D39: -9.4309037e-14 | E39: -7.5311967e-05 | F39: 2.0299747e-05 | G39: 7.1808514e-07 | H39: -5.5054381e-12 | I39: 0.0087506556 | J39: -5.9201558e-05 | K39: 3.6044625e-06 | L39: 0.011475444 | M39: -1.5374332e-05 | N39: 2.0564936e-05 | O39: -1.8057053e-15 | P39: -0.0016883583 | Q39: 0 | R39: 0.0016299932 | T39: 16 | U39: =Vocabulary!B17 -> as | V39: ='Training Example'!X39-'Training Example'!Y39 -> 0.001917189
... B42: from d16 | C42: -2.1835176e-08 | D42: 1.4623452e-12 | E42: 0.0011677788 | F42: -0.00031476557 | G42: -1.1134547e-05 | H42: 8.5366698e-11 | I42: -0.13568667 | J42: 0.00091797263 | K42: -5.5890386e-05 | L42: -0.17793692 | M42: 0.00023839265 | N42: -0.00031887756 | O42: 2.7999061e-14 | P42: 0.026179492 | Q42: 0 | R42: -0.025274489 | T42: 19 | U42: =Vocabulary!B20 -> on | V42: ='Training Example'!X42-'Training Example'!Y42 -> 0.00019245475
B43: Cell (i,k) = c_i x dpre_k. The whole chain rule for a 256-weight matrix, in one MMULT. | T43: 20 | U43: =Vocabulary!B21 -> all | V43: ='Training Example'!X43-'Training Example'!Y43 -> 0.0041256945
T44: 21 | U44: =Vocabulary!B22 -> with | V44: ='Training Example'!X44-'Training Example'!Y44 -> 6.4848158e-05
B45: STEP 6 · GRADIENT REACHING THE EMBEDDINGS: dc = dpre MMULT TRANSPOSE(W) (MMULT #6) | T45: 22 | U45: =Vocabulary!B23 -> had | V45: ='Training Example'!X45-'Training Example'!Y45 -> 8.9157736e-07
B46: dc = | C46: {=MMULT(C21:R21,TRANSPOSE('Hidden Weights'!$C$3:$R$18))} -> -0.42869336 | D46: 1.1501728 | E46: -0.23878981 | F46: 1.5725848 | G46: 1.0171912 | H46: 2.614169 | I46: 0.3403641 | J46: 0.73402313 | K46: 4.8252554 | L46: -0.71472583 | M46: -0.14895576 | N46: 3.0501999 | O46: 1.3788189 | P46: 2.2391691 | Q46: 1.1721967 | R46: -1.094938 | T46: 23 | U46: =Vocabulary!B24 -> but | V46: ='Training Example'!X46-'Training Example'!Y46 -> 2.3535965e-05
B47: dU for word 10 = | C47: =C46*'Training Example'!$K$27 -> -0.17216325 | D47: =D46*'Training Example'!$K$27 -> 0.46190939 | E47: =E46*'Training Example'!$K$27 -> -0.095897987 | F47: =F46*'Training Example'!$K$27 -> 0.63155005 | G47: =G46*'Training Example'!$K$27 -> 0.40850397 | H47: =H46*'Training Example'!$K$27 -> 1.0498503 | I47: =I46*'Training Example'!$K$27 -> 0.13669022 | J47: =J46*'Training Example'!$K$27 -> 0.29478369 | ... R47: =R46*'Training Example'!$K$27 -> -0.43972709 | T47: 24 | U47: =Vocabulary!B25 -> for | V47: ='Training Example'!X47-'Training Example'!Y47 -> 0.028358773
B48: Each context word's embedding receives attention_weight x dc. The latest word (40% attention) learns the most; the oldest (2.7%) barely moves. Attention decides not only what the model reads but also what it learns from. The 10 attention scores get their own gradients the same way. | T48: 25 | U48: =Vocabulary!B26 -> so | V48: ='Training Example'!X48-'Training Example'!Y48 -> 0.013500386
T49: 26 | U49: =Vocabulary!B27 -> be | V49: ='Training Example'!X49-'Training Example'!Y49 -> 7.5041771e-06
B50: STEP 7 · THE UPDATE: new weight = old weight - learning rate x gradient | T50: 27 | U50: =Vocabulary!B28 -> not | V50: ='Training Example'!X50-'Training Example'!Y50 -> 0.13233713
B51: learning rate | C51: 0.05 | D51: <- editable. Real training used Adam, an adaptive per-weight version of exactly this rule. | T51: 28 | U51: =Vocabulary!B29 -> very | V51: ='Training Example'!X51-'Training Example'!Y51 -> 0.0027732605
B52: watch one weight learn: | T52: 29 | U52: =Vocabulary!B30 -> what | V52: ='Training Example'!X52-'Training Example'!Y52 -> 0.00054581851
B53: W[1,1] before | C53: ='Hidden Weights'!C3 -> 1.07289 | D53: gradient | E53: =C27 -> -1.3192025e-08 | F53: after | G53: =C53-$C$51*E53 -> 1.07289 | T53: 30 | U53: =Vocabulary!B31 -> this | V53: ='Training Example'!X53-'Training Example'!Y53 -> 0.012865249
T54: 31 | U54: =Vocabulary!B32 -> they | V54: ='Training Example'!X54-'Training Example'!Y54 -> 0.0049468534
B55: the whole updated 16x16 hidden matrix after this ONE example: | T55: 32 | U55: =Vocabulary!B33 -> little | V55: ='Training Example'!X55-'Training Example'!Y55 -> 1.0478582e-06
C56: to d1 | D56: to d2 | E56: to d3 | F56: to d4 | G56: to d5 | H56: to d6 | I56: to d7 | J56: to d8 | K56: to d9 | L56: to d10 | M56: to d11 | N56: to d12 | O56: to d13 | P56: to d14 | Q56: to d15 | R56: to d16 | T56: 33 | U56: =Vocabulary!B34 -> he | V56: ='Training Example'!X56-'Training Example'!Y56 -> 7.9697939e-05
B57: from d1 | C57: ='Hidden Weights'!C3-$C$51*C27 -> 1.07289 | D57: ='Hidden Weights'!D3-$C$51*D27 -> -2.09808 | E57: ='Hidden Weights'!E3-$C$51*E27 -> -5.8385553 | F57: ='Hidden Weights'!F3-$C$51*F27 -> 1.8256695 | G57: ='Hidden Weights'!G3-$C$51*G27 -> 1.4043303 | H57: ='Hidden Weights'!H3-$C$51*H27 -> 4.43431 | I57: ='Hidden Weights'!I3-$C$51*I27 -> -1.0274912 | J57: ='Hidden Weights'!J3-$C$51*J27 -> 1.7073723 | ... R57: ='Hidden Weights'!R3-$C$51*R27 -> -0.5303265 | T57: 34 | U57: =Vocabulary!B35 -> out | V57: ='Training Example'!X57-'Training Example'!Y57 -> 4.9881161e-06
B58: from d2 | C58: ='Hidden Weights'!C4-$C$51*C28 -> -1.4472 | D58: ='Hidden Weights'!D4-$C$51*D28 -> 2.29555 | E58: ='Hidden Weights'!E4-$C$51*E28 -> -0.77834064 | F58: ='Hidden Weights'!F4-$C$51*F28 -> -2.8660883 | G58: ='Hidden Weights'!G4-$C$51*G28 -> 4.2442708 | H58: ='Hidden Weights'!H4-$C$51*H28 -> 6.19936 | I58: ='Hidden Weights'!I4-$C$51*I28 -> 2.4725002 | J58: ='Hidden Weights'!J4-$C$51*J28 -> -0.046863393 | ... R58: ='Hidden Weights'!R4-$C$51*R28 -> 5.7561954 | T58: 35 | U58: =Vocabulary!B36 -> is | V58: ='Training Example'!X58-'Training Example'!Y58 -> 1.3125598e-07
B59: from d3 | C59: ='Hidden Weights'!C5-$C$51*C29 -> 1.53883 | D59: ='Hidden Weights'!D5-$C$51*D29 -> 3.54409 | E59: ='Hidden Weights'!E5-$C$51*E29 -> 0.386754 | F59: ='Hidden Weights'!F5-$C$51*F29 -> -6.2040488 | G59: ='Hidden Weights'!G5-$C$51*G29 -> 2.4905486 | H59: ='Hidden Weights'!H5-$C$51*H29 -> 1.00243 | I59: ='Hidden Weights'!I5-$C$51*I29 -> -0.34285201 | J59: ='Hidden Weights'!J5-$C$51*J29 -> -6.8965468 | ... R59: ='Hidden Weights'!R5-$C$51*R29 -> -0.0069066876 | T59: 36 | U59: =Vocabulary!B37 -> one | V59: ='Training Example'!X59-'Training Example'!Y59 -> 0.0023257041
B60: from d4 | C60: ='Hidden Weights'!C6-$C$51*C30 -> -0.2441 | D60: ='Hidden Weights'!D6-$C$51*D30 -> 1.04644 | E60: ='Hidden Weights'!E6-$C$51*E30 -> -4.8868536 | F60: ='Hidden Weights'!F6-$C$51*F30 -> 1.2067794 | G60: ='Hidden Weights'!G6-$C$51*G30 -> 2.6075793 | H60: ='Hidden Weights'!H6-$C$51*H30 -> -8.15346 | I60: ='Hidden Weights'!I6-$C$51*I30 -> 0.43766125 | J60: ='Hidden Weights'!J6-$C$51*J30 -> -0.57235993 | ... R60: ='Hidden Weights'!R6-$C$51*R30 -> 4.7967161 | T60: 37 | U60: =Vocabulary!B38 -> down | V60: ='Training Example'!X60-'Training Example'!Y60 -> 8.622444e-08
B61: from d5 | C61: ='Hidden Weights'!C7-$C$51*C31 -> -2.58399 | D61: ='Hidden Weights'!D7-$C$51*D31 -> -1.23619 | E61: ='Hidden Weights'!E7-$C$51*E31 -> 0.8418972 | F61: ='Hidden Weights'!F7-$C$51*F31 -> -1.8147646 | G61: ='Hidden Weights'!G7-$C$51*G31 -> -4.2978302 | H61: ='Hidden Weights'!H7-$C$51*H31 -> -0.99335 | I61: ='Hidden Weights'!I7-$C$51*I31 -> 1.5964712 | J61: ='Hidden Weights'!J7-$C$51*J31 -> 2.5797235 | ... R61: ='Hidden Weights'!R7-$C$51*R31 -> 0.88517768 | T61: 38 | U61: =Vocabulary!B39 -> up | V61: ='Training Example'!X61-'Training Example'!Y61 -> 1.1061351e-05
B62: from d6 | C62: ='Hidden Weights'!C8-$C$51*C32 -> -2.03423 | D62: ='Hidden Weights'!D8-$C$51*D32 -> -1.55476 | E62: ='Hidden Weights'!E8-$C$51*E32 -> -1.3920878 | F62: ='Hidden Weights'!F8-$C$51*F32 -> -4.1494809 | G62: ='Hidden Weights'!G8-$C$51*G32 -> 0.18042103 | H62: ='Hidden Weights'!H8-$C$51*H32 -> -1.14 | I62: ='Hidden Weights'!I8-$C$51*I32 -> 5.3240155 | J62: ='Hidden Weights'!J8-$C$51*J32 -> -0.96564474 | ... R62: ='Hidden Weights'!R8-$C$51*R32 -> -3.8281469 | T62: 39 | U62: =Vocabulary!B40 -> if | V62: ='Training Example'!X62-'Training Example'!Y62 -> 0.001498649
B63: from d7 | C63: ='Hidden Weights'!C9-$C$51*C33 -> -1.8309 | D63: ='Hidden Weights'!D9-$C$51*D33 -> 8.05822 | E63: ='Hidden Weights'!E9-$C$51*E33 -> -0.99285242 | F63: ='Hidden Weights'!F9-$C$51*F33 -> 2.3532502 | G63: ='Hidden Weights'!G9-$C$51*G33 -> -3.4426214 | H63: ='Hidden Weights'!H9-$C$51*H33 -> -0.98219 | I63: ='Hidden Weights'!I9-$C$51*I33 -> 0.80138261 | J63: ='Hidden Weights'!J9-$C$51*J33 -> 0.37338601 | ... R63: ='Hidden Weights'!R9-$C$51*R33 -> -1.8810741 | T63: 40 | U63: =Vocabulary!B41 -> his | V63: ='Training Example'!X63-'Training Example'!Y63 -> 0.00053582202
B64: from d8 | C64: ='Hidden Weights'!C10-$C$51*C34 -> 4.99286 | D64: ='Hidden Weights'!D10-$C$51*D34 -> 2.63416 | E64: ='Hidden Weights'!E10-$C$51*E34 -> 1.5164108 | F64: ='Hidden Weights'!F10-$C$51*F34 -> -5.0269783 | G64: ='Hidden Weights'!G10-$C$51*G34 -> -0.86417029 | H64: ='Hidden Weights'!H10-$C$51*H34 -> -1.79043 | I64: ='Hidden Weights'!I10-$C$51*I34 -> -0.41433419 | J64: ='Hidden Weights'!J10-$C$51*J34 -> 5.4936142 | ... R64: ='Hidden Weights'!R10-$C$51*R34 -> -3.0166776 | T64: 41 | U64: =Vocabulary!B42 -> then | V64: ='Training Example'!X64-'Training Example'!Y64 -> 0.00057563158
B65: from d9 | C65: ='Hidden Weights'!C11-$C$51*C35 -> 5.09246 | D65: ='Hidden Weights'!D11-$C$51*D35 -> -4.4387 | E65: ='Hidden Weights'!E11-$C$51*E35 -> 1.4069182 | F65: ='Hidden Weights'!F11-$C$51*F35 -> 2.4861748 | G65: ='Hidden Weights'!G11-$C$51*G35 -> -0.11052912 | H65: ='Hidden Weights'!H11-$C$51*H35 -> 2.37393 | I65: ='Hidden Weights'!I11-$C$51*I35 -> 1.4982795 | J65: ='Hidden Weights'!J11-$C$51*J35 -> -1.8399422 | ... R65: ='Hidden Weights'!R11-$C$51*R35 -> 0.77676743 | T65: 42 | U65: =Vocabulary!B43 -> about | V65: ='Training Example'!X65-'Training Example'!Y65 -> 7.5493962e-06
B66: from d10 | C66: ='Hidden Weights'!C12-$C$51*C36 -> 4.6015 | D66: ='Hidden Weights'!D12-$C$51*D36 -> 4.29734 | E66: ='Hidden Weights'!E12-$C$51*E36 -> -1.7148008 | F66: ='Hidden Weights'!F12-$C$51*F36 -> 0.36359179 | G66: ='Hidden Weights'!G12-$C$51*G36 -> 0.55119077 | H66: ='Hidden Weights'!H12-$C$51*H36 -> -0.44407 | I66: ='Hidden Weights'!I12-$C$51*I36 -> -2.134837 | J66: ='Hidden Weights'!J12-$C$51*J36 -> -0.57208355 | ... R66: ='Hidden Weights'!R12-$C$51*R36 -> -3.7932604 | T66: 43 | U66: =Vocabulary!B44 -> no | V66: ='Training Example'!X66-'Training Example'!Y66 -> 0.015988699
B67: from d11 | C67: ='Hidden Weights'!C13-$C$51*C37 -> -1.59133 | D67: ='Hidden Weights'!D13-$C$51*D37 -> -4.54558 | E67: ='Hidden Weights'!E13-$C$51*E37 -> 1.8755863 | F67: ='Hidden Weights'!F13-$C$51*F37 -> 1.6329029 | G67: ='Hidden Weights'!G13-$C$51*G37 -> 3.3445397 | H67: ='Hidden Weights'!H13-$C$51*H37 -> -3.45451 | I67: ='Hidden Weights'!I13-$C$51*I37 -> 2.7571791 | J67: ='Hidden Weights'!J13-$C$51*J37 -> -3.1373094 | ... R67: ='Hidden Weights'!R13-$C$51*R37 -> -5.0835583 | T67: 44 | U67: =Vocabulary!B45 -> them | V67: ='Training Example'!X67-'Training Example'!Y67 -> 0.00016455596
B68: from d12 | C68: ='Hidden Weights'!C14-$C$51*C38 -> 1.87289 | D68: ='Hidden Weights'!D14-$C$51*D38 -> 4.73905 | E68: ='Hidden Weights'!E14-$C$51*E38 -> 1.921793 | F68: ='Hidden Weights'!F14-$C$51*F38 -> 3.3598038 | G68: ='Hidden Weights'!G14-$C$51*G38 -> -0.33764022 | H68: ='Hidden Weights'!H14-$C$51*H38 -> 0.18193 | I68: ='Hidden Weights'!I14-$C$51*I38 -> 9.8324039 | J68: ='Hidden Weights'!J14-$C$51*J38 -> -0.1264319 | ... R68: ='Hidden Weights'!R14-$C$51*R38 -> 2.9151315 | T68: 45 | U68: =Vocabulary!B46 -> know | V68: ='Training Example'!X68-'Training Example'!Y68 -> 5.3737894e-07
... B72: from d16 | C72: ='Hidden Weights'!C18-$C$51*C42 -> 1.87189 | D72: ='Hidden Weights'!D18-$C$51*D42 -> -2.02839 | E72: ='Hidden Weights'!E18-$C$51*E42 -> 0.072281611 | F72: ='Hidden Weights'!F18-$C$51*F42 -> -0.42805426 | G72: ='Hidden Weights'!G18-$C$51*G42 -> 10.575791 | H72: ='Hidden Weights'!H18-$C$51*H42 -> -0.78499 | I72: ='Hidden Weights'!I18-$C$51*I42 -> 1.2993943 | J72: ='Hidden Weights'!J18-$C$51*J42 -> 4.6934541 | ... R72: ='Hidden Weights'!R18-$C$51*R42 -> -0.68416628 | T72: 49 | U72: =Vocabulary!B50 -> went | V72: ='Training Example'!X72-'Training Example'!Y72 -> 1.3784776e-06
T73: 50 | U73: =Vocabulary!B51 -> again | V73: ='Training Example'!X73-'Training Example'!Y73 -> 9.3434305e-06
B74: That is one step, for one example, for one of the three weight matrices. Real training: this exact procedure on all 84,362 parameters, for 26,673 examples per epoch, for 120 epochs. Every number on the Embeddings, Hidden Weights and Output Weights tabs is where that process came to rest. Crank the learning rate up to 0.5 and watch the updated matrix overshoot: that is training instability, live. | T74: 51 | U74: =Vocabulary!B52 -> herself | V74: ='Training Example'!X74-'Training Example'!Y74 -> 1.0500286e-07
T75: 52 | U75: =Vocabulary!B53 -> do | V75: ='Training Example'!X75-'Training Example'!Y75 -> 2.7219969e-05
T76: 53 | U76: =Vocabulary!B54 -> have | V76: ='Training Example'!X76-'Training Example'!Y76 -> 1.2918871e-05
T77: 54 | U77: =Vocabulary!B55 -> when | V77: ='Training Example'!X77-'Training Example'!Y77 -> 4.1094075e-06
T78: 55 | U78: =Vocabulary!B56 -> or | V78: ='Training Example'!X78-'Training Example'!Y78 -> 1.2507367e-07
T79: 56 | U79: =Vocabulary!B57 -> could | V79: ='Training Example'!X79-'Training Example'!Y79 -> 3.9409764e-08
T80: 57 | U80: =Vocabulary!B58 -> there | V80: ='Training Example'!X80-'Training Example'!Y80 -> 0.0015617364
T81: 58 | U81: =Vocabulary!B59 -> thought | V81: ='Training Example'!X81-'Training Example'!Y81 -> 4.236864e-05
T82: 59 | U82: =Vocabulary!B60 -> off | V82: ='Training Example'!X82-'Training Example'!Y82 -> 3.7033133e-06
T83: 60 | U83: =Vocabulary!B61 -> time | V83: ='Training Example'!X83-'Training Example'!Y83 -> 1.3182533e-09
T84: 61 | U84: =Vocabulary!B62 -> how | V84: ='Training Example'!X84-'Training Example'!Y84 -> 4.5384704e-06
T85: 62 | U85: =Vocabulary!B63 -> me | V85: ='Training Example'!X85-'Training Example'!Y85 -> 0.00078462085
T86: 63 | U86: =Vocabulary!B64 -> queen | V86: ='Training Example'!X86-'Training Example'!Y86 -> 2.0585601e-09
... T2651: 2628 | U2651: =Vocabulary!B2629 -> happy | V2651: ='Training Example'!X2651-'Training Example'!Y2651 -> 5.1503088e-15

Sheet Gradient Descent Lab
B1: GRADIENT DESCENT LAB: TEACH THE MODEL A WORD
B2: Pick a context and the word you WANT next. Twenty live gradient steps tune the output weights until the model agrees.
B4: THE SETUP (yellow = yours). Default: chapter 8 opens "A large rose-tree stood near the entrance of the garden..."
B5: w1 | C5: w2 | D5: w3 | E5: w4 | F5: w5 | G5: w6 | H5: w7 | I5: w8 | J5: w9 | K5: w10 | AB5: machine room: embeddings (10x16), attention, c, pre, h
B6: a | C6: large | D6: rose | E6: tree | F6: stood | G6: near | H6: the | I6: entrance | J6: of | K6: the
B7: or paste a sentence: | C7: A large rose tree stood near the entrance of the... | M7: =IF($C$7="",0,LEN(TRIM($C$7))-LEN(SUBSTITUTE(TRIM($C$7)," ",""))+1) -> 10
B8: the word you WANT next: | C8: garden | D8: <- the book says "garden". The sentence cell is filled, so it wins; clear it to use the word cells. | AB8: =IF(B$12=1,0,INDEX(Embeddings!$C$2:$R$2629,B$12,1)) -> 0.44645 | AC8: =IF(B$12=1,0,INDEX(Embeddings!$C$2:$R$2629,B$12,2)) -> 0.35822 | AD8: =IF(B$12=1,0,INDEX(Embeddings!$C$2:$R$2629,B$12,3)) -> -0.33882 | AE8: =IF(B$12=1,0,INDEX(Embeddings!$C$2:$R$2629,B$12,4)) -> 0.46646 | AF8: =IF(B$12=1,0,INDEX(Embeddings!$C$2:$R$2629,B$12,5)) -> -0.49398 | AG8: =IF(B$12=1,0,INDEX(Embeddings!$C$2:$R$2629,B$12,6)) -> -0.35397 | AH8: =IF(B$12=1,0,INDEX(Embeddings!$C$2:$R$2629,B$12,7)) -> -1.67177 | AI8: =IF(B$12=1,0,INDEX(Embeddings!$C$2:$R$2629,B$12,8)) -> -1.32692 | AJ8: =IF(B$12=1,0,INDEX(Embeddings!$C$2:$R$2629,B$12,9)) -> -0.02545 | AK8: =IF(B$12=1,0,INDEX(Embeddings!$C$2:$R$2629,B$12,10)) -> 0.24869 | AL8: =IF(B$12=1,0,INDEX(Embeddings!$C$2:$R$2629,B$12,11)) -> 0.63082 | AM8: =IF(B$12=1,0,INDEX(Embeddings!$C$2:$R$2629,B$12,12)) -> -0.58007 | AN8: =IF(B$12=1,0,INDEX(Embeddings!$C$2:$R$2629,B$12,13)) -> -0.04389 | AO8: =IF(B$12=1,0,INDEX(Embeddings!$C$2:$R$2629,B$12,14)) -> 0.52169 | AP8: =IF(B$12=1,0,INDEX(Embeddings!$C$2:$R$2629,B$12,15)) -> -0.25329 | AQ8: =IF(B$12=1,0,INDEX(Embeddings!$C$2:$R$2629,B$12,16)) -> 1.71116
AB9: =IF(C$12=1,0,INDEX(Embeddings!$C$2:$R$2629,C$12,1)) -> 0.84415 | AC9: =IF(C$12=1,0,INDEX(Embeddings!$C$2:$R$2629,C$12,2)) -> 0.91441 | AD9: =IF(C$12=1,0,INDEX(Embeddings!$C$2:$R$2629,C$12,3)) -> 0.0203 | AE9: =IF(C$12=1,0,INDEX(Embeddings!$C$2:$R$2629,C$12,4)) -> -1.36892 | AF9: =IF(C$12=1,0,INDEX(Embeddings!$C$2:$R$2629,C$12,5)) -> -0.93301 | AG9: =IF(C$12=1,0,INDEX(Embeddings!$C$2:$R$2629,C$12,6)) -> 1.08527 | AH9: =IF(C$12=1,0,INDEX(Embeddings!$C$2:$R$2629,C$12,7)) -> 0.00119 | AI9: =IF(C$12=1,0,INDEX(Embeddings!$C$2:$R$2629,C$12,8)) -> 0.50904 | AJ9: =IF(C$12=1,0,INDEX(Embeddings!$C$2:$R$2629,C$12,9)) -> -0.96211 | AK9: =IF(C$12=1,0,INDEX(Embeddings!$C$2:$R$2629,C$12,10)) -> 0.30132 | AL9: =IF(C$12=1,0,INDEX(Embeddings!$C$2:$R$2629,C$12,11)) -> -0.24446 | AM9: =IF(C$12=1,0,INDEX(Embeddings!$C$2:$R$2629,C$12,12)) -> -0.5436 | AN9: =IF(C$12=1,0,INDEX(Embeddings!$C$2:$R$2629,C$12,13)) -> -0.61356 | AO9: =IF(C$12=1,0,INDEX(Embeddings!$C$2:$R$2629,C$12,14)) -> 0.13765 | AP9: =IF(C$12=1,0,INDEX(Embeddings!$C$2:$R$2629,C$12,15)) -> -0.6154 | AQ9: =IF(C$12=1,0,INDEX(Embeddings!$C$2:$R$2629,C$12,16)) -> 0.10653
B10: FORWARD PASS (frozen model): the context becomes a hidden vector h | AB10: =IF(D$12=1,0,INDEX(Embeddings!$C$2:$R$2629,D$12,1)) -> -2.65445 | AC10: =IF(D$12=1,0,INDEX(Embeddings!$C$2:$R$2629,D$12,2)) -> 0.69373 | AD10: =IF(D$12=1,0,INDEX(Embeddings!$C$2:$R$2629,D$12,3)) -> -0.11834 | AE10: =IF(D$12=1,0,INDEX(Embeddings!$C$2:$R$2629,D$12,4)) -> 2.38321 | AF10: =IF(D$12=1,0,INDEX(Embeddings!$C$2:$R$2629,D$12,5)) -> -0.39587 | AG10: =IF(D$12=1,0,INDEX(Embeddings!$C$2:$R$2629,D$12,6)) -> -2.69759 | AH10: =IF(D$12=1,0,INDEX(Embeddings!$C$2:$R$2629,D$12,7)) -> 0.59131 | AI10: =IF(D$12=1,0,INDEX(Embeddings!$C$2:$R$2629,D$12,8)) -> -0.00366 | AJ10: =IF(D$12=1,0,INDEX(Embeddings!$C$2:$R$2629,D$12,9)) -> -1.11391 | AK10: =IF(D$12=1,0,INDEX(Embeddings!$C$2:$R$2629,D$12,10)) -> -0.04272 | AL10: =IF(D$12=1,0,INDEX(Embeddings!$C$2:$R$2629,D$12,11)) -> 1.4403 | AM10: =IF(D$12=1,0,INDEX(Embeddings!$C$2:$R$2629,D$12,12)) -> 2.71419 | AN10: =IF(D$12=1,0,INDEX(Embeddings!$C$2:$R$2629,D$12,13)) -> -0.33637 | AO10: =IF(D$12=1,0,INDEX(Embeddings!$C$2:$R$2629,D$12,14)) -> 1.35974 | AP10: =IF(D$12=1,0,INDEX(Embeddings!$C$2:$R$2629,D$12,15)) -> 1.64899 | AQ10: =IF(D$12=1,0,INDEX(Embeddings!$C$2:$R$2629,D$12,16)) -> -0.47884
B11: =IF($C$7="",TRIM(SUBSTITUTE(SUBSTITUTE(SUBSTITUTE(SUBSTITUTE(LOWER(B6),".",""),",",""),"!",""),"?","")),IF($M$7-10+1<1,"",TRIM(SUBSTITUTE(SUBSTITUTE(SUBSTITUTE(SUBSTITUTE(LOWER(TRIM(MID(SUBSTITUTE(TRIM($C$7)," ",REPT(" ",LEN($C$7))),($M$7-10+1-1)*LEN($C$7)+1,LEN($C$7)))),".",""),",",""),"!",""),"?","")))) -> a | C11: =IF($C$7="",TRIM(SUBSTITUTE(SUBSTITUTE(SUBSTITUTE(SUBSTITUTE(LOWER(C6),".",""),",",""),"!",""),"?","")),IF($M$7-10+2<1,"",TRIM(SUBSTITUTE(SUBSTITUTE(SUBSTITUTE(SUBSTITUTE(LOWER(TRIM(MID(SUBSTITUTE(TRIM($C$7)," ",REPT(" ",LEN($C$7))),($M$7-10+2-1)*LEN($C$7)+1,LEN($C$7)))),".",""),",",""),"!",""),"?","")))) -> large | D11: =IF($C$7="",TRIM(SUBSTITUTE(SUBSTITUTE(SUBSTITUTE(SUBSTITUTE(LOWER(D6),".",""),",",""),"!",""),"?","")),IF($M$7-10+3<1,"",TRIM(SUBSTITUTE(SUBSTITUTE(SUBSTITUTE(SUBSTITUTE(LOWER(TRIM(MID(SUBSTITUTE(TRIM($C$7)," ",REPT(" ",LEN($C$7))),($M$7-10+3-1)*LEN($C$7)+1,LEN($C$7)))),".",""),",",""),"!",""),"?","")))) -> rose | E11: =IF($C$7="",TRIM(SUBSTITUTE(SUBSTITUTE(SUBSTITUTE(SUBSTITUTE(LOWER(E6),".",""),",",""),"!",""),"?","")),IF($M$7-10+4<1,"",TRIM(SUBSTITUTE(SUBSTITUTE(SUBSTITUTE(SUBSTITUTE(LOWER(TRIM(MID(SUBSTITUTE(TRIM($C$7)," ",REPT(" ",LEN($C$7))),($M$7-10+4-1)*LEN($C$7)+1,LEN($C$7)))),".",""),",",""),"!",""),"?","")))) -> tree | F11: =IF($C$7="",TRIM(SUBSTITUTE(SUBSTITUTE(SUBSTITUTE(SUBSTITUTE(LOWER(F6),".",""),",",""),"!",""),"?","")),IF($M$7-10+5<1,"",TRIM(SUBSTITUTE(SUBSTITUTE(SUBSTITUTE(SUBSTITUTE(LOWER(TRIM(MID(SUBSTITUTE(TRIM($C$7)," ",REPT(" ",LEN($C$7))),($M$7-10+5-1)*LEN($C$7)+1,LEN($C$7)))),".",""),",",""),"!",""),"?","")))) -> stood | G11: =IF($C$7="",TRIM(SUBSTITUTE(SUBSTITUTE(SUBSTITUTE(SUBSTITUTE(LOWER(G6),".",""),",",""),"!",""),"?","")),IF($M$7-10+6<1,"",TRIM(SUBSTITUTE(SUBSTITUTE(SUBSTITUTE(SUBSTITUTE(LOWER(TRIM(MID(SUBSTITUTE(TRIM($C$7)," ",REPT(" ",LEN($C$7))),($M$7-10+6-1)*LEN($C$7)+1,LEN($C$7)))),".",""),",",""),"!",""),"?","")))) -> near | H11: =IF($C$7="",TRIM(SUBSTITUTE(SUBSTITUTE(SUBSTITUTE(SUBSTITUTE(LOWER(H6),".",""),",",""),"!",""),"?","")),IF($M$7-10+7<1,"",TRIM(SUBSTITUTE(SUBSTITUTE(SUBSTITUTE(SUBSTITUTE(LOWER(TRIM(MID(SUBSTITUTE(TRIM($C$7)," ",REPT(" ",LEN($C$7))),($M$7-10+7-1)*LEN($C$7)+1,LEN($C$7)))),".",""),",",""),"!",""),"?","")))) -> the | I11: =IF($C$7="",TRIM(SUBSTITUTE(SUBSTITUTE(SUBSTITUTE(SUBSTITUTE(LOWER(I6),".",""),",",""),"!",""),"?","")),IF($M$7-10+8<1,"",TRIM(SUBSTITUTE(SUBSTITUTE(SUBSTITUTE(SUBSTITUTE(LOWER(TRIM(MID(SUBSTITUTE(TRIM($C$7)," ",REPT(" ",LEN($C$7))),($M$7-10+8-1)*LEN($C$7)+1,LEN($C$7)))),".",""),",",""),"!",""),"?","")))) -> entrance | J11: =IF($C$7="",TRIM(SUBSTITUTE(SUBSTITUTE(SUBSTITUTE(SUBSTITUTE(LOWER(J6),".",""),",",""),"!",""),"?","")),IF($M$7-10+9<1,"",TRIM(SUBSTITUTE(SUBSTITUTE(SUBSTITUTE(SUBSTITUTE(LOWER(TRIM(MID(SUBSTITUTE(TRIM($C$7)," ",REPT(" ",LEN($C$7))),($M$7-10+9-1)*LEN($C$7)+1,LEN($C$7)))),".",""),",",""),"!",""),"?","")))) -> of | K11: =IF($C$7="",TRIM(SUBSTITUTE(SUBSTITUTE(SUBSTITUTE(SUBSTITUTE(LOWER(K6),".",""),",",""),"!",""),"?","")),IF($M$7-10+10<1,"",TRIM(SUBSTITUTE(SUBSTITUTE(SUBSTITUTE(SUBSTITUTE(LOWER(TRIM(MID(SUBSTITUTE(TRIM($C$7)," ",REPT(" ",LEN($C$7))),($M$7-10+10-1)*LEN($C$7)+1,LEN($C$7)))),".",""),",",""),"!",""),"?","")))) -> the | AB11: =IF(E$12=1,0,INDEX(Embeddings!$C$2:$R$2629,E$12,1)) -> 0.52705 | AC11: =IF(E$12=1,0,INDEX(Embeddings!$C$2:$R$2629,E$12,2)) -> 0.22724 | AD11: =IF(E$12=1,0,INDEX(Embeddings!$C$2:$R$2629,E$12,3)) -> 0.90916 | AE11: =IF(E$12=1,0,INDEX(Embeddings!$C$2:$R$2629,E$12,4)) -> -2.41625 | AF11: =IF(E$12=1,0,INDEX(Embeddings!$C$2:$R$2629,E$12,5)) -> -0.63509 | AG11: =IF(E$12=1,0,INDEX(Embeddings!$C$2:$R$2629,E$12,6)) -> 0.32985 | AH11: =IF(E$12=1,0,INDEX(Embeddings!$C$2:$R$2629,E$12,7)) -> 0.91204 | AI11: =IF(E$12=1,0,INDEX(Embeddings!$C$2:$R$2629,E$12,8)) -> 0.29357 | AJ11: =IF(E$12=1,0,INDEX(Embeddings!$C$2:$R$2629,E$12,9)) -> -0.84728 | AK11: =IF(E$12=1,0,INDEX(Embeddings!$C$2:$R$2629,E$12,10)) -> -0.42239 | AL11: =IF(E$12=1,0,INDEX(Embeddings!$C$2:$R$2629,E$12,11)) -> -1.2833 | AM11: =IF(E$12=1,0,INDEX(Embeddings!$C$2:$R$2629,E$12,12)) -> 0.78417 | AN11: =IF(E$12=1,0,INDEX(Embeddings!$C$2:$R$2629,E$12,13)) -> -1.01629 | AO11: =IF(E$12=1,0,INDEX(Embeddings!$C$2:$R$2629,E$12,14)) -> -0.21775 | AP11: =IF(E$12=1,0,INDEX(Embeddings!$C$2:$R$2629,E$12,15)) -> 0.19047 | AQ11: =IF(E$12=1,0,INDEX(Embeddings!$C$2:$R$2629,E$12,16)) -> -0.70696
B12: =IFERROR(MATCH(B11,Vocabulary!$B$2:$B$2629,0),1) -> 5 | C12: =IFERROR(MATCH(C11,Vocabulary!$B$2:$B$2629,0),1) -> 136 | D12: =IFERROR(MATCH(D11,Vocabulary!$B$2:$B$2629,0),1) -> 831 | E12: =IFERROR(MATCH(E11,Vocabulary!$B$2:$B$2629,0),1) -> 468 | F12: =IFERROR(MATCH(F11,Vocabulary!$B$2:$B$2629,0),1) -> 522 | G12: =IFERROR(MATCH(G11,Vocabulary!$B$2:$B$2629,0),1) -> 241 | H12: =IFERROR(MATCH(H11,Vocabulary!$B$2:$B$2629,0),1) -> 2 | I12: =IFERROR(MATCH(I11,Vocabulary!$B$2:$B$2629,0),1) -> 2167 | ... K12: =IFERROR(MATCH(K11,Vocabulary!$B$2:$B$2629,0),1) -> 2 | AB12: =IF(F$12=1,0,INDEX(Embeddings!$C$2:$R$2629,F$12,1)) -> 0.8838 | AC12: =IF(F$12=1,0,INDEX(Embeddings!$C$2:$R$2629,F$12,2)) -> 0.43635 | AD12: =IF(F$12=1,0,INDEX(Embeddings!$C$2:$R$2629,F$12,3)) -> -0.16972 | AE12: =IF(F$12=1,0,INDEX(Embeddings!$C$2:$R$2629,F$12,4)) -> -1.29881 | AF12: =IF(F$12=1,0,INDEX(Embeddings!$C$2:$R$2629,F$12,5)) -> 0.69048 | AG12: =IF(F$12=1,0,INDEX(Embeddings!$C$2:$R$2629,F$12,6)) -> -0.35703 | AH12: =IF(F$12=1,0,INDEX(Embeddings!$C$2:$R$2629,F$12,7)) -> 1.73072 | AI12: =IF(F$12=1,0,INDEX(Embeddings!$C$2:$R$2629,F$12,8)) -> 1.52729 | AJ12: =IF(F$12=1,0,INDEX(Embeddings!$C$2:$R$2629,F$12,9)) -> -1.66508 | AK12: =IF(F$12=1,0,INDEX(Embeddings!$C$2:$R$2629,F$12,10)) -> 0.92672 | AL12: =IF(F$12=1,0,INDEX(Embeddings!$C$2:$R$2629,F$12,11)) -> -1.999 | AM12: =IF(F$12=1,0,INDEX(Embeddings!$C$2:$R$2629,F$12,12)) -> 0.7912 | AN12: =IF(F$12=1,0,INDEX(Embeddings!$C$2:$R$2629,F$12,13)) -> -0.19781 | AO12: =IF(F$12=1,0,INDEX(Embeddings!$C$2:$R$2629,F$12,14)) -> 1.45238 | AP12: =IF(F$12=1,0,INDEX(Embeddings!$C$2:$R$2629,F$12,15)) -> 0.85442 | AQ12: =IF(F$12=1,0,INDEX(Embeddings!$C$2:$R$2629,F$12,16)) -> 2.49513
B13: target ID: | C13: =IFERROR(MATCH(TRIM(SUBSTITUTE(SUBSTITUTE(SUBSTITUTE(SUBSTITUTE(LOWER($C$8),".",""),",",""),"!",""),"?","")),Vocabulary!$B$2:$B$2629,0),1) -> 236 | AB13: =IF(G$12=1,0,INDEX(Embeddings!$C$2:$R$2629,G$12,1)) -> -1.04237 | AC13: =IF(G$12=1,0,INDEX(Embeddings!$C$2:$R$2629,G$12,2)) -> -1.03437 | AD13: =IF(G$12=1,0,INDEX(Embeddings!$C$2:$R$2629,G$12,3)) -> 2.17788 | AE13: =IF(G$12=1,0,INDEX(Embeddings!$C$2:$R$2629,G$12,4)) -> -0.50569 | AF13: =IF(G$12=1,0,INDEX(Embeddings!$C$2:$R$2629,G$12,5)) -> 0.2314 | AG13: =IF(G$12=1,0,INDEX(Embeddings!$C$2:$R$2629,G$12,6)) -> -0.56056 | AH13: =IF(G$12=1,0,INDEX(Embeddings!$C$2:$R$2629,G$12,7)) -> 1.52571 | AI13: =IF(G$12=1,0,INDEX(Embeddings!$C$2:$R$2629,G$12,8)) -> 1.17546 | AJ13: =IF(G$12=1,0,INDEX(Embeddings!$C$2:$R$2629,G$12,9)) -> -1.29137 | AK13: =IF(G$12=1,0,INDEX(Embeddings!$C$2:$R$2629,G$12,10)) -> -0.64728 | AL13: =IF(G$12=1,0,INDEX(Embeddings!$C$2:$R$2629,G$12,11)) -> -0.08613 | AM13: =IF(G$12=1,0,INDEX(Embeddings!$C$2:$R$2629,G$12,12)) -> -2.49692 | AN13: =IF(G$12=1,0,INDEX(Embeddings!$C$2:$R$2629,G$12,13)) -> -0.16278 | AO13: =IF(G$12=1,0,INDEX(Embeddings!$C$2:$R$2629,G$12,14)) -> 0.20488 | AP13: =IF(G$12=1,0,INDEX(Embeddings!$C$2:$R$2629,G$12,15)) -> -0.54276 | AQ13: =IF(G$12=1,0,INDEX(Embeddings!$C$2:$R$2629,G$12,16)) -> 0.27519
AB14: =IF(H$12=1,0,INDEX(Embeddings!$C$2:$R$2629,H$12,1)) -> -0.24612 | AC14: =IF(H$12=1,0,INDEX(Embeddings!$C$2:$R$2629,H$12,2)) -> -0.69257 | AD14: =IF(H$12=1,0,INDEX(Embeddings!$C$2:$R$2629,H$12,3)) -> -1.11074 | AE14: =IF(H$12=1,0,INDEX(Embeddings!$C$2:$R$2629,H$12,4)) -> -0.52835 | AF14: =IF(H$12=1,0,INDEX(Embeddings!$C$2:$R$2629,H$12,5)) -> -0.49587 | AG14: =IF(H$12=1,0,INDEX(Embeddings!$C$2:$R$2629,H$12,6)) -> 0.16979 | AH14: =IF(H$12=1,0,INDEX(Embeddings!$C$2:$R$2629,H$12,7)) -> -1.56429 | AI14: =IF(H$12=1,0,INDEX(Embeddings!$C$2:$R$2629,H$12,8)) -> -0.73668 | AJ14: =IF(H$12=1,0,INDEX(Embeddings!$C$2:$R$2629,H$12,9)) -> 0.62002 | AK14: =IF(H$12=1,0,INDEX(Embeddings!$C$2:$R$2629,H$12,10)) -> 0.80283 | AL14: =IF(H$12=1,0,INDEX(Embeddings!$C$2:$R$2629,H$12,11)) -> -0.61923 | AM14: =IF(H$12=1,0,INDEX(Embeddings!$C$2:$R$2629,H$12,12)) -> -0.87934 | AN14: =IF(H$12=1,0,INDEX(Embeddings!$C$2:$R$2629,H$12,13)) -> -0.30187 | AO14: =IF(H$12=1,0,INDEX(Embeddings!$C$2:$R$2629,H$12,14)) -> 0.67991 | AP14: =IF(H$12=1,0,INDEX(Embeddings!$C$2:$R$2629,H$12,15)) -> -0.28704 | AQ14: =IF(H$12=1,0,INDEX(Embeddings!$C$2:$R$2629,H$12,16)) -> 0.23597
B15: h = | C15: =AB25 -> 0.8698108 | D15: =AC25 -> -0.99999444 | E15: =AD25 -> -0.99999974 | F15: =AE25 -> -0.61155812 | G15: =AF25 -> 0.02693654 | H15: =AG25 -> 0.6806961 | I15: =AH25 -> -0.99999936 | J15: =AI25 -> 0.97571588 | ... R15: =AQ25 -> -0.98845619 | AB15: =IF(I$12=1,0,INDEX(Embeddings!$C$2:$R$2629,I$12,1)) -> -1.62054 | AC15: =IF(I$12=1,0,INDEX(Embeddings!$C$2:$R$2629,I$12,2)) -> 0.32197 | AD15: =IF(I$12=1,0,INDEX(Embeddings!$C$2:$R$2629,I$12,3)) -> 0.33347 | AE15: =IF(I$12=1,0,INDEX(Embeddings!$C$2:$R$2629,I$12,4)) -> -1.36933 | AF15: =IF(I$12=1,0,INDEX(Embeddings!$C$2:$R$2629,I$12,5)) -> -3.55721 | AG15: =IF(I$12=1,0,INDEX(Embeddings!$C$2:$R$2629,I$12,6)) -> -1.57966 | AH15: =IF(I$12=1,0,INDEX(Embeddings!$C$2:$R$2629,I$12,7)) -> -0.53821 | AI15: =IF(I$12=1,0,INDEX(Embeddings!$C$2:$R$2629,I$12,8)) -> -1.28232 | AJ15: =IF(I$12=1,0,INDEX(Embeddings!$C$2:$R$2629,I$12,9)) -> 1.65059 | AK15: =IF(I$12=1,0,INDEX(Embeddings!$C$2:$R$2629,I$12,10)) -> 3.13298 | AL15: =IF(I$12=1,0,INDEX(Embeddings!$C$2:$R$2629,I$12,11)) -> -1.00601 | AM15: =IF(I$12=1,0,INDEX(Embeddings!$C$2:$R$2629,I$12,12)) -> -1.6697 | AN15: =IF(I$12=1,0,INDEX(Embeddings!$C$2:$R$2629,I$12,13)) -> -0.5284 | AO15: =IF(I$12=1,0,INDEX(Embeddings!$C$2:$R$2629,I$12,14)) -> 5.67629 | AP15: =IF(I$12=1,0,INDEX(Embeddings!$C$2:$R$2629,I$12,15)) -> -3.36633 | AQ15: =IF(I$12=1,0,INDEX(Embeddings!$C$2:$R$2629,I$12,16)) -> -1.84133
B16: computed in the machine room at columns AB-AQ: embeddings block, learned attention, MMULT, MMULT, TANH, exactly as on the Prompt tab. | AB16: =IF(J$12=1,0,INDEX(Embeddings!$C$2:$R$2629,J$12,1)) -> -0.05844 | AC16: =IF(J$12=1,0,INDEX(Embeddings!$C$2:$R$2629,J$12,2)) -> -0.69847 | AD16: =IF(J$12=1,0,INDEX(Embeddings!$C$2:$R$2629,J$12,3)) -> -0.01318 | AE16: =IF(J$12=1,0,INDEX(Embeddings!$C$2:$R$2629,J$12,4)) -> 0.69573 | AF16: =IF(J$12=1,0,INDEX(Embeddings!$C$2:$R$2629,J$12,5)) -> 0.40065 | AG16: =IF(J$12=1,0,INDEX(Embeddings!$C$2:$R$2629,J$12,6)) -> -0.26492 | AH16: =IF(J$12=1,0,INDEX(Embeddings!$C$2:$R$2629,J$12,7)) -> 1.42647 | AI16: =IF(J$12=1,0,INDEX(Embeddings!$C$2:$R$2629,J$12,8)) -> -0.65642 | AJ16: =IF(J$12=1,0,INDEX(Embeddings!$C$2:$R$2629,J$12,9)) -> -0.65223 | AK16: =IF(J$12=1,0,INDEX(Embeddings!$C$2:$R$2629,J$12,10)) -> -0.7729 | AL16: =IF(J$12=1,0,INDEX(Embeddings!$C$2:$R$2629,J$12,11)) -> -0.26861 | AM16: =IF(J$12=1,0,INDEX(Embeddings!$C$2:$R$2629,J$12,12)) -> -0.03118 | AN16: =IF(J$12=1,0,INDEX(Embeddings!$C$2:$R$2629,J$12,13)) -> 0.01131 | AO16: =IF(J$12=1,0,INDEX(Embeddings!$C$2:$R$2629,J$12,14)) -> 0.69797 | AP16: =IF(J$12=1,0,INDEX(Embeddings!$C$2:$R$2629,J$12,15)) -> -0.25873 | AQ16: =IF(J$12=1,0,INDEX(Embeddings!$C$2:$R$2629,J$12,16)) -> 0.80276
AB17: =IF(K$12=1,0,INDEX(Embeddings!$C$2:$R$2629,K$12,1)) -> -0.24612 | AC17: =IF(K$12=1,0,INDEX(Embeddings!$C$2:$R$2629,K$12,2)) -> -0.69257 | AD17: =IF(K$12=1,0,INDEX(Embeddings!$C$2:$R$2629,K$12,3)) -> -1.11074 | AE17: =IF(K$12=1,0,INDEX(Embeddings!$C$2:$R$2629,K$12,4)) -> -0.52835 | AF17: =IF(K$12=1,0,INDEX(Embeddings!$C$2:$R$2629,K$12,5)) -> -0.49587 | AG17: =IF(K$12=1,0,INDEX(Embeddings!$C$2:$R$2629,K$12,6)) -> 0.16979 | AH17: =IF(K$12=1,0,INDEX(Embeddings!$C$2:$R$2629,K$12,7)) -> -1.56429 | AI17: =IF(K$12=1,0,INDEX(Embeddings!$C$2:$R$2629,K$12,8)) -> -0.73668 | AJ17: =IF(K$12=1,0,INDEX(Embeddings!$C$2:$R$2629,K$12,9)) -> 0.62002 | AK17: =IF(K$12=1,0,INDEX(Embeddings!$C$2:$R$2629,K$12,10)) -> 0.80283 | AL17: =IF(K$12=1,0,INDEX(Embeddings!$C$2:$R$2629,K$12,11)) -> -0.61923 | AM17: =IF(K$12=1,0,INDEX(Embeddings!$C$2:$R$2629,K$12,12)) -> -0.87934 | AN17: =IF(K$12=1,0,INDEX(Embeddings!$C$2:$R$2629,K$12,13)) -> -0.30187 | AO17: =IF(K$12=1,0,INDEX(Embeddings!$C$2:$R$2629,K$12,14)) -> 0.67991 | AP17: =IF(K$12=1,0,INDEX(Embeddings!$C$2:$R$2629,K$12,15)) -> -0.28704 | AQ17: =IF(K$12=1,0,INDEX(Embeddings!$C$2:$R$2629,K$12,16)) -> 0.23597
B18: BEFORE TUNING
B19: top pick: | C19: =INDEX($U$24:$U$2651,MATCH(MAX($X$24:$X$2651),$X$24:$X$2651,0)) -> garden | E19: p(your word): | G19: =INDEX($X$24:$X$2651,$C$13) -> 0.27792202 | I19: its rank: | K19: =1+SUMPRODUCT(($X$24:$X$2651>INDEX($X$24:$X$2651,$C$13))*1) -> 1 | M19: loss: | O19: =-LN(G19) -> 1.2804147 | AB19: 0.0274 | AC19: 0.0382 | AD19: 0.0384 | AE19: 0.0363 | AF19: 0.0419 | AG19: 0.052 | AH19: 0.0748 | AI19: 0.1105 | AJ19: 0.1788 | AK19: 0.4016
B21: TWENTY STEPS OF GRADIENT DESCENT, LIVE | AB21: {=MMULT(AB19:AK19,AB8:AQ17)} -> -0.36226203 | AC21: -0.37511954 | AD21: -0.36857615 | AE21: -0.39504275 | AF21: -0.60413525 | AG21: -0.24499621 | AH21: -0.38774072 | AI21: -0.49129747 | AJ21: 0.11325057 | AK21: 0.59699031 | AL21: -0.52575978 | AM21: -0.60965214 | AN21: -0.29137815 | AO21: 1.2113069 | AP21: -0.50762272 | AQ21: 0.17824358
B22: We tune just TWO rows of the Output Weights: your word's and its strongest rival's, with the exact Backpropagation | T22: sum of exp | W22: =SUM(W24:W2651) -> 6505768.8
B23: rule, new = old - lr x g x h. Each step changes a row's logit by -lr x g x ||h||^2 (g = p - 1 for your word, g = p for | T23: ID | U23: Word | V23: Logit | W23: exp (raw) | X23: p | Y23: exp (not yours) | Z23: exp (neither) | AB23: {=MMULT(AB21:AQ21,'Hidden Weights'!$C$3:$R$18)} -> 1.3323019 | AC23: -6.396426 | AD23: -7.9195738 | AE23: -0.7114066 | AF23: 0.026943058 | AG23: 0.83041 | AH23: -7.4795903 | AI23: 2.1994318 | AJ23: -10.54409 | AK23: -0.22376811 | AL23: 13.071439 | AM23: -10.2068 | AN23: 5.6252731 | AO23: -1.7204436 | AP23: 0.92823784 | AQ23: -2.5744822
B24: the rival). Everything else is frozen, so all other scores are constant and this table is exact, not a cartoon. | T24: 1 | U24: =Vocabulary!B2 -> <unk> | V24: {=MMULT('Output Weights'!$C$2:$R$2629,TRANSPOSE($C$15:$R$15))} -> 0 | W24: =EXP(V24) -> 1 | X24: =W24/$W$22 -> 1.5370974e-07 | Y24: =IF(T24=$C$13,0,W24) -> 1 | Z24: =IF(OR(T24=$C$13,T24=$N$25),0,W24) -> 1
B25: learning rate | C25: 0.1 | E25: ||h||^2 | G25: =SUMPRODUCT($C$15:$R$15,$C$15:$R$15) -> 11.984349 | I25: rival: | K25: =INDEX($U$24:$U$2651,$N$25) -> door | N25: =MATCH(MAX($Y$24:$Y$2651),$Y$24:$Y$2651,0) -> 151 | O25: <- rival ID | T25: 2 | U25: =Vocabulary!B3 -> the | V25: 2.2515819 | W25: =EXP(V25) -> 9.5027568 | X25: =W25/$W$22 -> 1.4606662e-06 | Y25: =IF(T25=$C$13,0,W25) -> 9.5027568 | Z25: =IF(OR(T25=$C$13,T25=$N$25),0,W25) -> 9.5027568 | AB25: =TANH(AB23) -> 0.8698108 | AC25: =TANH(AC23) -> -0.99999444 | AD25: =TANH(AD23) -> -0.99999974 | AE25: =TANH(AE23) -> -0.61155812 | AF25: =TANH(AF23) -> 0.02693654 | AG25: =TANH(AG23) -> 0.6806961 | AH25: =TANH(AH23) -> -0.99999936 | AI25: =TANH(AI23) -> 0.97571588 | ... AQ25: =TANH(AQ23) -> -0.98845619
B26: S_rest (all other words' exp, frozen) | F26: =SUM($W$24:$W$2651)-EXP(C29)-EXP(D29) -> 4244162.8 | T26: 3 | U26: =Vocabulary!B4 -> and | V26: 3.9754378 | W26: =EXP(V26) -> 53.273437 | X26: =W26/$W$22 -> 8.1886459e-06 | Y26: =IF(T26=$C$13,0,W26) -> 53.273437 | Z26: =IF(OR(T26=$C$13,T26=$N$25),0,W26) -> 53.273437
T27: 4 | U27: =Vocabulary!B5 -> to | V27: -4.983897 | W27: =EXP(V27) -> 0.0068473267 | X27: =W27/$W$22 -> 1.0525008e-09 | Y27: =IF(T27=$C$13,0,W27) -> 0.0068473267 | Z27: =IF(OR(T27=$C$13,T27=$N$25),0,W27) -> 0.0068473267
B28: step | C28: logit (yours) | D28: logit (rival) | E28: p (yours) | F28: p (rival) | G28: loss | H28: p (yours) as a bar | I28: cum 1-p | J28: cum p riv | T28: 5 | U28: =Vocabulary!B6 -> a | V28: -1.167689 | W28: =EXP(V28) -> 0.31108503 | X28: =W28/$W$22 -> 4.7816797e-08 | Y28: =IF(T28=$C$13,0,W28) -> 0.31108503 | Z28: =IF(OR(T28=$C$13,T28=$N$25),0,W28) -> 0.31108503
B29: 0 | C29: =INDEX($V$24:$V$2651,$C$13) -> 14.407785 | D29: =INDEX($V$24:$V$2651,$N$25) -> 13.024772 | E29: =EXP(C29)/(EXP(C29)+EXP(D29)+$F$26) -> 0.27792202 | F29: =EXP(D29)/(EXP(C29)+EXP(D29)+$F$26) -> 0.06970884 | G29: =-LN(E29) -> 1.2804147 | H29: =REPT("|",ROUND(E29*40,0)) -> ||||||||||| | I29: =1-E29 -> 0.72207798 | J29: =F29 -> 0.06970884 | T29: 6 | U29: =Vocabulary!B7 -> she | V29: -3.5651973 | W29: =EXP(V29) -> 0.028291402 | X29: =W29/$W$22 -> 4.3486639e-09 | Y29: =IF(T29=$C$13,0,W29) -> 0.028291402 | Z29: =IF(OR(T29=$C$13,T29=$N$25),0,W29) -> 0.028291402
B30: 1 | C30: =C29+$C$25*(1-E29)*$G$25 -> 15.273149 | D30: =D29-$C$25*F29*$G$25 -> 12.94123 | E30: =EXP(C30)/(EXP(C30)+EXP(D30)+$F$26) -> 0.47959592 | F30: =EXP(D30)/(EXP(C30)+EXP(D30)+$F$26) -> 0.046573211 | G30: =-LN(E30) -> 0.73481136 | H30: =REPT("|",ROUND(E30*40,0)) -> ||||||||||||||||||| | I30: =I29+(1-E30) -> 1.2424821 | J30: =J29+F30 -> 0.11628205 | T30: 7 | U30: =Vocabulary!B8 -> it | V30: -2.5495165 | W30: =EXP(V30) -> 0.078119431 | X30: =W30/$W$22 -> 1.2007717e-08 | Y30: =IF(T30=$C$13,0,W30) -> 0.078119431 | Z30: =IF(OR(T30=$C$13,T30=$N$25),0,W30) -> 0.078119431
B31: 2 | C31: =C30+$C$25*(1-E30)*$G$25 -> 15.896819 | D31: =D30-$C$25*F30*$G$25 -> 12.885415 | E31: =EXP(C31)/(EXP(C31)+EXP(D31)+$F$26) -> 0.63341117 | F31: =EXP(D31)/(EXP(C31)+EXP(D31)+$F$26) -> 0.031178101 | G31: =-LN(E31) -> 0.45663552 | H31: =REPT("|",ROUND(E31*40,0)) -> ||||||||||||||||||||||||| | I31: =I30+(1-E31) -> 1.6090709 | J31: =J30+F31 -> 0.14746015 | T31: 8 | U31: =Vocabulary!B9 -> of | V31: 8.6565676 | W31: =EXP(V31) -> 5747.7722 | X31: =W31/$W$22 -> 0.00088348854 | Y31: =IF(T31=$C$13,0,W31) -> 5747.7722 | Z31: =IF(OR(T31=$C$13,T31=$N$25),0,W31) -> 5747.7722
B32: 3 | C32: =C31+$C$25*(1-E31)*$G$25 -> 16.336152 | D32: =D31-$C$25*F31*$G$25 -> 12.84805 | E32: =EXP(C32)/(EXP(C32)+EXP(D32)+$F$26) -> 0.72895672 | F32: =EXP(D32)/(EXP(C32)+EXP(D32)+$F$26) -> 0.022276065 | G32: =-LN(E32) -> 0.31614092 | H32: =REPT("|",ROUND(E32*40,0)) -> ||||||||||||||||||||||||||||| | I32: =I31+(1-E32) -> 1.8801142 | J32: =J31+F32 -> 0.16973622 | T32: 9 | U32: =Vocabulary!B10 -> said | V32: -2.4687932 | W32: =EXP(V32) -> 0.084686998 | X32: =W32/$W$22 -> 1.3017216e-08 | Y32: =IF(T32=$C$13,0,W32) -> 0.084686998 | Z32: =IF(OR(T32=$C$13,T32=$N$25),0,W32) -> 0.084686998
B33: 4 | C33: =C32+$C$25*(1-E32)*$G$25 -> 16.66098 | D33: =D32-$C$25*F32*$G$25 -> 12.821354 | E33: =EXP(C33)/(EXP(C33)+EXP(D33)+$F$26) -> 0.78857063 | F33: =EXP(D33)/(EXP(C33)+EXP(D33)+$F$26) -> 0.016955567 | G33: =-LN(E33) -> 0.2375333 | H33: =REPT("|",ROUND(E33*40,0)) -> |||||||||||||||||||||||||||||||| | I33: =I32+(1-E33) -> 2.0915435 | J33: =J32+F33 -> 0.18669178 | T33: 10 | U33: =Vocabulary!B11 -> i | V33: -2.2448219 | W33: =EXP(V33) -> 0.10594641 | X33: =W33/$W$22 -> 1.6284994e-08 | Y33: =IF(T33=$C$13,0,W33) -> 0.10594641 | Z33: =IF(OR(T33=$C$13,T33=$N$25),0,W33) -> 0.10594641
B34: 5 | C34: =C33+$C$25*(1-E33)*$G$25 -> 16.914364 | D34: =D33-$C$25*F33*$G$25 -> 12.801034 | E34: =EXP(C34)/(EXP(C34)+EXP(D34)+$F$26) -> 0.82797309 | F34: =EXP(D34)/(EXP(C34)+EXP(D34)+$F$26) -> 0.013540029 | G34: =-LN(E34) -> 0.18877462 | H34: =REPT("|",ROUND(E34*40,0)) -> ||||||||||||||||||||||||||||||||| | I34: =I33+(1-E34) -> 2.2635704 | J34: =J33+F34 -> 0.20023181 | T34: 11 | U34: =Vocabulary!B12 -> alice | V34: 0.74508739 | W34: =EXP(V34) -> 2.1066255 | X34: =W34/$W$22 -> 3.2380885e-07 | Y34: =IF(T34=$C$13,0,W34) -> 2.1066255 | Z34: =IF(OR(T34=$C$13,T34=$N$25),0,W34) -> 2.1066255
B35: 6 | C35: =C34+$C$25*(1-E34)*$G$25 -> 17.120527 | D35: =D34-$C$25*F34*$G$25 -> 12.784807 | E35: =EXP(C35)/(EXP(C35)+EXP(D35)+$F$26) -> 0.85554375 | F35: =EXP(D35)/(EXP(C35)+EXP(D35)+$F$26) -> 0.011201157 | G35: =-LN(E35) -> 0.15601805 | H35: =REPT("|",ROUND(E35*40,0)) -> |||||||||||||||||||||||||||||||||| | I35: =I34+(1-E35) -> 2.4080267 | J35: =J34+F35 -> 0.21143297 | T35: 12 | U35: =Vocabulary!B13 -> in | V35: -1.6307566 | W35: =EXP(V35) -> 0.1957814 | X35: =W35/$W$22 -> 3.0093507e-08 | Y35: =IF(T35=$C$13,0,W35) -> 0.1957814 | Z35: =IF(OR(T35=$C$13,T35=$N$25),0,W35) -> 0.1957814
B36: 7 | C36: =C35+$C$25*(1-E35)*$G$25 -> 17.293648 | D36: =D35-$C$25*F35*$G$25 -> 12.771383 | E36: =EXP(C36)/(EXP(C36)+EXP(D36)+$F$26) -> 0.8757643 | F36: =EXP(D36)/(EXP(C36)+EXP(D36)+$F$26) -> 0.0095146391 | G36: =-LN(E36) -> 0.13265829 | H36: =REPT("|",ROUND(E36*40,0)) -> ||||||||||||||||||||||||||||||||||| | I36: =I35+(1-E36) -> 2.5322624 | J36: =J35+F36 -> 0.22094761 | T36: 13 | U36: =Vocabulary!B14 -> you | V36: -5.7575626 | W36: =EXP(V36) -> 0.0031588015 | X36: =W36/$W$22 -> 4.8553854e-10 | Y36: =IF(T36=$C$13,0,W36) -> 0.0031588015 | Z36: =IF(OR(T36=$C$13,T36=$N$25),0,W36) -> 0.0031588015
B37: 8 | C37: =C36+$C$25*(1-E36)*$G$25 -> 17.442537 | D37: =D36-$C$25*F36*$G$25 -> 12.75998 | E37: =EXP(C37)/(EXP(C37)+EXP(D37)+$F$26) -> 0.89116276 | F37: =EXP(D37)/(EXP(C37)+EXP(D37)+$F$26) -> 0.0082479986 | G37: =-LN(E37) -> 0.1152282 | H37: =REPT("|",ROUND(E37*40,0)) -> |||||||||||||||||||||||||||||||||||| | I37: =I36+(1-E37) -> 2.6410996 | J37: =J36+F37 -> 0.22919561 | T37: 14 | U37: =Vocabulary!B15 -> was | V37: -2.5573224 | W37: =EXP(V37) -> 0.077512008 | X37: =W37/$W$22 -> 1.191435e-08 | Y37: =IF(T37=$C$13,0,W37) -> 0.077512008 | Z37: =IF(OR(T37=$C$13,T37=$N$25),0,W37) -> 0.077512008
B38: 9 | C38: =C37+$C$25*(1-E37)*$G$25 -> 17.572971 | D38: =D37-$C$25*F37*$G$25 -> 12.750096 | E38: =EXP(C38)/(EXP(C38)+EXP(D38)+$F$26) -> 0.90324864 | F38: =EXP(D38)/(EXP(C38)+EXP(D38)+$F$26) -> 0.0072653926 | G38: =-LN(E38) -> 0.10175741 | H38: =REPT("|",ROUND(E38*40,0)) -> |||||||||||||||||||||||||||||||||||| | I38: =I37+(1-E38) -> 2.737851 | J38: =J37+F38 -> 0.236461 | T38: 15 | U38: =Vocabulary!B16 -> that | V38: -0.97487474 | W38: =EXP(V38) -> 0.3772396 | X38: =W38/$W$22 -> 5.79854e-08 | Y38: =IF(T38=$C$13,0,W38) -> 0.3772396 | Z38: =IF(OR(T38=$C$13,T38=$N$25),0,W38) -> 0.3772396
B39: 10 | C39: =C38+$C$25*(1-E38)*$G$25 -> 17.688921 | D39: =D38-$C$25*F38*$G$25 -> 12.741389 | E39: =EXP(C39)/(EXP(C39)+EXP(D39)+$F$26) -> 0.91297038 | F39: =EXP(D39)/(EXP(C39)+EXP(D39)+$F$26) -> 0.0064829172 | G39: =-LN(E39) -> 0.091051839 | H39: =REPT("|",ROUND(E39*40,0)) -> ||||||||||||||||||||||||||||||||||||| | I39: =I38+(1-E39) -> 2.8248806 | J39: =J38+F39 -> 0.24294392 | T39: 16 | U39: =Vocabulary!B17 -> as | V39: -2.2293064 | W39: =EXP(V39) -> 0.10760303 | X39: =W39/$W$22 -> 1.6539634e-08 | Y39: =IF(T39=$C$13,0,W39) -> 0.10760303 | Z39: =IF(OR(T39=$C$13,T39=$N$25),0,W39) -> 0.10760303
B40: 11 | C40: =C39+$C$25*(1-E39)*$G$25 -> 17.793221 | D40: =D39-$C$25*F39*$G$25 -> 12.733619 | E40: =EXP(C40)/(EXP(C40)+EXP(D40)+$F$26) -> 0.92095042 | F40: =EXP(D40)/(EXP(C40)+EXP(D40)+$F$26) -> 0.0058462748 | G40: =-LN(E40) -> 0.082349077 | H40: =REPT("|",ROUND(E40*40,0)) -> ||||||||||||||||||||||||||||||||||||| | I40: =I39+(1-E40) -> 2.9039302 | J40: =J39+F40 -> 0.24879019 | T40: 17 | U40: =Vocabulary!B18 -> her | V40: 1.3633255 | W40: =EXP(V40) -> 3.9091716 | X40: =W40/$W$22 -> 6.0087774e-07 | Y40: =IF(T40=$C$13,0,W40) -> 3.9091716 | Z40: =IF(OR(T40=$C$13,T40=$N$25),0,W40) -> 3.9091716
B41: 12 | C41: =C40+$C$25*(1-E40)*$G$25 -> 17.887957 | D41: =D40-$C$25*F40*$G$25 -> 12.726613 | E41: =EXP(C41)/(EXP(C41)+EXP(D41)+$F$26) -> 0.92761269 | F41: =EXP(D41)/(EXP(C41)+EXP(D41)+$F$26) -> 0.0053189217 | G41: =-LN(E41) -> 0.075140997 | H41: =REPT("|",ROUND(E41*40,0)) -> ||||||||||||||||||||||||||||||||||||| | I41: =I40+(1-E41) -> 2.9763175 | J41: =J40+F41 -> 0.25410911 | T41: 18 | U41: =Vocabulary!B19 -> at | V41: 3.290347 | W41: =EXP(V41) -> 26.852179 | X41: =W41/$W$22 -> 4.1274414e-06 | Y41: =IF(T41=$C$13,0,W41) -> 26.852179 | Z41: =IF(OR(T41=$C$13,T41=$N$25),0,W41) -> 26.852179
... B49: 20 | C49: =C48+$C$25*(1-E48)*$G$25 -> 18.435558 | D49: =D48-$C$25*F48*$G$25 -> 12.687017 | E49: =EXP(C49)/(EXP(C49)+EXP(D49)+$F$26) -> 0.95693568 | F49: =EXP(D49)/(EXP(C49)+EXP(D49)+$F$26) -> 0.0030501635 | G49: =-LN(E49) -> 0.044019103 | H49: =REPT("|",ROUND(E49*40,0)) -> |||||||||||||||||||||||||||||||||||||| | I49: =I48+(1-E49) -> 3.403925 | J49: =J48+F49 -> 0.28488002 | T49: 26 | U49: =Vocabulary!B27 -> be | V49: -5.863772 | W49: =EXP(V49) -> 0.0028405092 | X49: =W49/$W$22 -> 4.3661392e-10 | Y49: =IF(T49=$C$13,0,W49) -> 0.0028405092 | Z49: =IF(OR(T49=$C$13,T49=$N$25),0,W49) -> 0.0028405092
B50: Each row is one application of new = old - lr x gradient. Watch the loss column: that curve IS gradient descent. The last two columns accumulate the update coefficients used below. | T50: 27 | U50: =Vocabulary!B28 -> not | V50: -4.8642492 | W50: =EXP(V50) -> 0.0077176203 | X50: =W50/$W$22 -> 1.1862734e-09 | Y50: =IF(T50=$C$13,0,W50) -> 0.0077176203 | Z50: =IF(OR(T50=$C$13,T50=$N$25),0,W50) -> 0.0077176203
T51: 28 | U51: =Vocabulary!B29 -> very | V51: 0.24200889 | W51: =EXP(V51) -> 1.2738055 | X51: =W51/$W$22 -> 1.9579631e-07 | Y51: =IF(T51=$C$13,0,W51) -> 1.2738055 | Z51: =IF(OR(T51=$C$13,T51=$N$25),0,W51) -> 1.2738055
B52: THE RESULT | T52: 29 | U52: =Vocabulary!B30 -> what | V52: -3.4580558 | W52: =EXP(V52) -> 0.031490929 | X52: =W52/$W$22 -> 4.8404623e-09 | Y52: =IF(T52=$C$13,0,W52) -> 0.031490929 | Z52: =IF(OR(T52=$C$13,T52=$N$25),0,W52) -> 0.031490929
B53: p(your word): | D53: =E29 -> 0.27792202 | E53: before -> | G53: =E49 -> 0.95693568 | H53: after 20 steps. loss: | K53: =G29 -> 1.2804147 | L53: -> | M53: =G49 -> 0.044019103 | T53: 30 | U53: =Vocabulary!B31 -> this | V53: -0.98885475 | W53: =EXP(V53) -> 0.37200248 | X53: =W53/$W$22 -> 5.7180404e-08 | Y53: =IF(T53=$C$13,0,W53) -> 0.37200248 | Z53: =IF(OR(T53=$C$13,T53=$N$25),0,W53) -> 0.37200248
B54: AFTER TUNING, THE MODEL SAYS: | F54: =IF(EXP(C49)>=MAX(EXP(D49),MAX($Z$24:$Z$2651)),INDEX($U$24:$U$2651,$C$13),IF(EXP(D49)>=MAX($Z$24:$Z$2651),INDEX($U$24:$U$2651,$N$25),INDEX($U$24:$U$2651,MATCH(MAX($Z$24:$Z$2651),$Z$24:$Z$2651,0)))) -> garden | T54: 31 | U54: =Vocabulary!B32 -> they | V54: -3.5842757 | W54: =EXP(V54) -> 0.027756765 | X54: =W54/$W$22 -> 4.2664851e-09 | Y54: =IF(T54=$C$13,0,W54) -> 0.027756765 | Z54: =IF(OR(T54=$C$13,T54=$N$25),0,W54) -> 0.027756765
B55: Not your word yet? Raise the learning rate, or accept that 20 steps was not enough: the table shows exactly how far it got. Steps here are bigger than real training steps on purpose, so you can see the curve. | T55: 32 | U55: =Vocabulary!B33 -> little | V55: 5.4208671 | W55: =EXP(V55) -> 226.07506 | X55: =W55/$W$22 -> 3.4749938e-05 | Y55: =IF(T55=$C$13,0,W55) -> 226.07506 | Z55: =IF(OR(T55=$C$13,T55=$N$25),0,W55) -> 226.07506
T56: 33 | U56: =Vocabulary!B34 -> he | V56: -3.3033735 | W56: =EXP(V56) -> 0.03675895 | X56: =W56/$W$22 -> 5.6502085e-09 | Y56: =IF(T56=$C$13,0,W56) -> 0.03675895 | Z56: =IF(OR(T56=$C$13,T56=$N$25),0,W56) -> 0.03675895
B57: THE WEIGHTS THAT CHANGED (only these 32 numbers moved; every other tab is untouched) | T57: 34 | U57: =Vocabulary!B35 -> out | V57: -4.7758507 | W57: =EXP(V57) -> 0.0084309085 | X57: =W57/$W$22 -> 1.2959127e-09 | Y57: =IF(T57=$C$13,0,W57) -> 0.0084309085 | Z57: =IF(OR(T57=$C$13,T57=$N$25),0,W57) -> 0.0084309085
C58: d1 | D58: d2 | E58: d3 | F58: d4 | G58: d5 | H58: d6 | I58: d7 | J58: d8 | K58: d9 | L58: d10 | M58: d11 | N58: d12 | O58: d13 | P58: d14 | Q58: d15 | R58: d16 | T58: 35 | U58: =Vocabulary!B36 -> is | V58: -4.9889541 | W58: =EXP(V58) -> 0.0068127863 | X58: =W58/$W$22 -> 1.0471916e-09 | Y58: =IF(T58=$C$13,0,W58) -> 0.0068127863 | Z58: =IF(OR(T58=$C$13,T58=$N$25),0,W58) -> 0.0068127863
B59: ="Out[ "&INDEX($U$24:$U$2651,$C$13)&" ] before" -> Out[ garden ] before | C59: =INDEX('Output Weights'!$C$2:$R$2629,$C$13,1) -> 0.86511 | D59: =INDEX('Output Weights'!$C$2:$R$2629,$C$13,2) -> -2.3992 | E59: =INDEX('Output Weights'!$C$2:$R$2629,$C$13,3) -> -1.13196 | F59: =INDEX('Output Weights'!$C$2:$R$2629,$C$13,4) -> 0.15569 | G59: =INDEX('Output Weights'!$C$2:$R$2629,$C$13,5) -> 0.32929 | H59: =INDEX('Output Weights'!$C$2:$R$2629,$C$13,6) -> 1.69987 | I59: =INDEX('Output Weights'!$C$2:$R$2629,$C$13,7) -> -1.88206 | J59: =INDEX('Output Weights'!$C$2:$R$2629,$C$13,8) -> 3.16424 | K59: =INDEX('Output Weights'!$C$2:$R$2629,$C$13,9) -> -1.80571 | L59: =INDEX('Output Weights'!$C$2:$R$2629,$C$13,10) -> -0.01986 | M59: =INDEX('Output Weights'!$C$2:$R$2629,$C$13,11) -> -0.82815 | N59: =INDEX('Output Weights'!$C$2:$R$2629,$C$13,12) -> 3.00789 | O59: =INDEX('Output Weights'!$C$2:$R$2629,$C$13,13) -> 1.32563 | P59: =INDEX('Output Weights'!$C$2:$R$2629,$C$13,14) -> -2.59388 | Q59: =INDEX('Output Weights'!$C$2:$R$2629,$C$13,15) -> 2.07523 | R59: =INDEX('Output Weights'!$C$2:$R$2629,$C$13,16) -> -0.8468 | T59: 36 | U59: =Vocabulary!B37 -> one | V59: -0.35078128 | W59: =EXP(V59) -> 0.70413774 | X59: =W59/$W$22 -> 1.0823283e-07 | Y59: =IF(T59=$C$13,0,W59) -> 0.70413774 | Z59: =IF(OR(T59=$C$13,T59=$N$25),0,W59) -> 0.70413774
B60: ="Out[ "&INDEX($U$24:$U$2651,$C$13)&" ] AFTER" -> Out[ garden ] AFTER | C60: =C59+$C$25*$I$48*C$15 -> 1.1574413 | D60: =D59+$C$25*$I$48*D$15 -> -2.7352842 | E60: =E59+$C$25*$I$48*E$15 -> -1.468046 | F60: =F59+$C$25*$I$48*F$15 -> -0.049846161 | G60: =G59+$C$25*$I$48*G$15 -> 0.338343 | H60: =H59+$C$25*$I$48*H$15 -> 1.9286425 | I60: =I59+$C$25*$I$48*I$15 -> -2.2181458 | J60: =J59+$C$25*$I$48*J$15 -> 3.4921645 | ... R60: =R59+$C$25*$I$48*R$15 -> -1.1790063 | T60: 37 | U60: =Vocabulary!B38 -> down | V60: -6.0536926 | W60: =EXP(V60) -> 0.0023491713 | X60: =W60/$W$22 -> 3.6109051e-10 | Y60: =IF(T60=$C$13,0,W60) -> 0.0023491713 | Z60: =IF(OR(T60=$C$13,T60=$N$25),0,W60) -> 0.0023491713
B61: ="Out[ "&INDEX($U$24:$U$2651,$N$25)&" ] before" -> Out[ door ] before | C61: =INDEX('Output Weights'!$C$2:$R$2629,$N$25,1) -> 0.31581 | D61: =INDEX('Output Weights'!$C$2:$R$2629,$N$25,2) -> -0.98275 | E61: =INDEX('Output Weights'!$C$2:$R$2629,$N$25,3) -> -0.48677 | F61: =INDEX('Output Weights'!$C$2:$R$2629,$N$25,4) -> -0.21642 | G61: =INDEX('Output Weights'!$C$2:$R$2629,$N$25,5) -> -0.13785 | H61: =INDEX('Output Weights'!$C$2:$R$2629,$N$25,6) -> 0.94521 | I61: =INDEX('Output Weights'!$C$2:$R$2629,$N$25,7) -> -2.43317 | J61: =INDEX('Output Weights'!$C$2:$R$2629,$N$25,8) -> 0.64034 | K61: =INDEX('Output Weights'!$C$2:$R$2629,$N$25,9) -> -1.16563 | L61: =INDEX('Output Weights'!$C$2:$R$2629,$N$25,10) -> -0.91131 | M61: =INDEX('Output Weights'!$C$2:$R$2629,$N$25,11) -> 2.87198 | N61: =INDEX('Output Weights'!$C$2:$R$2629,$N$25,12) -> -1.26935 | O61: =INDEX('Output Weights'!$C$2:$R$2629,$N$25,13) -> 1.24733 | P61: =INDEX('Output Weights'!$C$2:$R$2629,$N$25,14) -> 0.4433 | Q61: =INDEX('Output Weights'!$C$2:$R$2629,$N$25,15) -> 0.49105 | R61: =INDEX('Output Weights'!$C$2:$R$2629,$N$25,16) -> -0.76194 | T61: 38 | U61: =Vocabulary!B39 -> up | V61: -7.4369112 | W61: =EXP(V61) -> 0.00058910202 | X61: =W61/$W$22 -> 9.0550715e-11 | Y61: =IF(T61=$C$13,0,W61) -> 0.00058910202 | Z61: =IF(OR(T61=$C$13,T61=$N$25),0,W61) -> 0.00058910202
B62: ="Out[ "&INDEX($U$24:$U$2651,$N$25)&" ] AFTER" -> Out[ door ] AFTER | C62: =C61-$C$25*$J$48*C$15 -> 0.29129613 | D62: =D61-$C$25*$J$48*D$15 -> -0.95456717 | E62: =E61-$C$25*$J$48*E$15 -> -0.45858702 | F62: =F61-$C$25*$J$48*F$15 -> -0.19918447 | G62: =G61-$C$25*$J$48*G$15 -> -0.13860915 | H62: =H61-$C$25*$J$48*H$15 -> 0.92602595 | I62: =I61-$C$25*$J$48*I$15 -> -2.404987 | J62: =J61-$C$25*$J$48*J$15 -> 0.61284141 | ... R62: =R61-$C$25*$J$48*R$15 -> -0.73408235 | T62: 39 | U62: =Vocabulary!B40 -> if | V62: -2.1345208 | W62: =EXP(V62) -> 0.11830127 | X62: =W62/$W$22 -> 1.8184057e-08 | Y62: =IF(T62=$C$13,0,W62) -> 0.11830127 | Z62: =IF(OR(T62=$C$13,T62=$N$25),0,W62) -> 0.11830127
B63: check: updated row times h = | F63: =SUMPRODUCT($C$60:$R$60,$C$15:$R$15) -> 18.435558 | G63: and the final logit in the table: | J63: =C49 -> 18.435558 | K63: identical: the weights and the descent table agree. | T63: 40 | U63: =Vocabulary!B41 -> his | V63: 1.2610505 | W63: =EXP(V63) -> 3.5291269 | X63: =W63/$W$22 -> 5.4246117e-07 | Y63: =IF(T63=$C$13,0,W63) -> 3.5291269 | Z63: =IF(OR(T63=$C$13,T63=$N$25),0,W63) -> 3.5291269
T64: 41 | U64: =Vocabulary!B42 -> then | V64: -1.3403392 | W64: =EXP(V64) -> 0.26175686 | X64: =W64/$W$22 -> 4.0234578e-08 | Y64: =IF(T64=$C$13,0,W64) -> 0.26175686 | Z64: =IF(OR(T64=$C$13,T64=$N$25),0,W64) -> 0.26175686
B65: WHAT THIS TEACHES | T65: 42 | U65: =Vocabulary!B43 -> about | V65: -4.2200818 | W65: =EXP(V65) -> 0.014697443 | X65: =W65/$W$22 -> 2.25914e-09 | Y65: =IF(T65=$C$13,0,W65) -> 0.014697443 | Z65: =IF(OR(T65=$C$13,T65=$N$25),0,W65) -> 0.014697443
B66: This is fine-tuning: take a trained model, show it what you want, and let gradient descent adjust the weights. | T66: 43 | U66: =Vocabulary!B44 -> no | V66: -2.9236074 | W66: =EXP(V66) -> 0.053739479 | X66: =W66/$W$22 -> 8.2602811e-09 | Y66: =IF(T66=$C$13,0,W66) -> 0.053739479 | Z66: =IF(OR(T66=$C$13,T66=$N$25),0,W66) -> 0.053739479
B67: Here only 2 of the 2,628 output rows moved, and the base tabs stay frozen, so the rest of the workbook is intact. | T67: 44 | U67: =Vocabulary!B45 -> them | V67: -3.4506077 | W67: =EXP(V67) -> 0.03172635 | X67: =W67/$W$22 -> 4.8766489e-09 | Y67: =IF(T67=$C$13,0,W67) -> 0.03172635 | Z67: =IF(OR(T67=$C$13,T67=$N$25),0,W67) -> 0.03172635
B68: Real training updates every matrix a little (see Backpropagation) for every example, cycling the whole book so | T68: 45 | U68: =Vocabulary!B46 -> know | V68: -2.1026106 | W68: =EXP(V68) -> 0.12213716 | X68: =W68/$W$22 -> 1.877367e-08 | Y68: =IF(T68=$C$13,0,W68) -> 0.12213716 | Z68: =IF(OR(T68=$C$13,T68=$N$25),0,W68) -> 0.12213716
B69: no single sentence dominates. That balance is the hard part: set the learning rate to 1.0 and the rival gets | T69: 46 | U69: =Vocabulary!B47 -> like | V69: 1.902885 | W69: =EXP(V69) -> 6.7052108 | X69: =W69/$W$22 -> 1.0306562e-06 | Y69: =IF(T69=$C$13,0,W69) -> 6.7052108 | Z69: =IF(OR(T69=$C$13,T69=$N$25),0,W69) -> 6.7052108
B70: crushed so hard it may vanish from predictions it deserved elsewhere. Overfit one example, damage the rest; | T70: 47 | U70: =Vocabulary!B48 -> were | V70: -0.65295389 | W70: =EXP(V70) -> 0.52050599 | X70: =W70/$W$22 -> 8.0006838e-08 | Y70: =IF(T70=$C$13,0,W70) -> 0.52050599 | Z70: =IF(OR(T70=$C$13,T70=$N$25),0,W70) -> 0.52050599
B71: in large models this is called catastrophic forgetting, and it is why real fine-tuning mixes in general data. | T71: 48 | U71: =Vocabulary!B49 -> would | V71: -5.4834307 | W71: =EXP(V71) -> 0.0041550503 | X71: =W71/$W$22 -> 6.3867169e-10 | Y71: =IF(T71=$C$13,0,W71) -> 0.0041550503 | Z71: =IF(OR(T71=$C$13,T71=$N$25),0,W71) -> 0.0041550503
B72: Why was the model ever shaky here? 84,362 parameters must compress 26,673 examples, and "of the" precedes | T72: 49 | U72: =Vocabulary!B50 -> went | V72: -1.5010832 | W72: =EXP(V72) -> 0.22288859 | X72: =W72/$W$22 -> 3.4260146e-08 | Y72: =IF(T72=$C$13,0,W72) -> 0.22288859 | Z72: =IF(OR(T72=$C$13,T72=$N$25),0,W72) -> 0.22288859
B73: over a hundred different words in the book, while this sentence occurs once. Capacity goes to common patterns | T73: 50 | U73: =Vocabulary!B51 -> again | V73: 1.8075426 | W73: =EXP(V73) -> 6.0954503 | X73: =W73/$W$22 -> 9.3693006e-07 | Y73: =IF(T73=$C$13,0,W73) -> 6.0954503 | Z73: =IF(OR(T73=$C$13,T73=$N$25),0,W73) -> 6.0954503
B74: first: exactly why bigger models miss less. You just fixed one of the compromises by hand. | T74: 51 | U74: =Vocabulary!B52 -> herself | V74: -1.1652414 | W74: =EXP(V74) -> 0.31184737 | X74: =W74/$W$22 -> 4.7933976e-08 | Y74: =IF(T74=$C$13,0,W74) -> 0.31184737 | Z74: =IF(OR(T74=$C$13,T74=$N$25),0,W74) -> 0.31184737
T75: 52 | U75: =Vocabulary!B53 -> do | V75: -10.675484 | W75: =EXP(V75) -> 2.3104475e-05 | X75: =W75/$W$22 -> 3.5513828e-12 | Y75: =IF(T75=$C$13,0,W75) -> 2.3104475e-05 | Z75: =IF(OR(T75=$C$13,T75=$N$25),0,W75) -> 2.3104475e-05
T76: 53 | U76: =Vocabulary!B54 -> have | V76: -6.6320903 | W76: =EXP(V76) -> 0.0013174064 | X76: =W76/$W$22 -> 2.0249819e-10 | Y76: =IF(T76=$C$13,0,W76) -> 0.0013174064 | Z76: =IF(OR(T76=$C$13,T76=$N$25),0,W76) -> 0.0013174064
T77: 54 | U77: =Vocabulary!B55 -> when | V77: -7.1874466 | W77: =EXP(V77) -> 0.00075601707 | X77: =W77/$W$22 -> 1.1620718e-10 | Y77: =IF(T77=$C$13,0,W77) -> 0.00075601707 | Z77: =IF(OR(T77=$C$13,T77=$N$25),0,W77) -> 0.00075601707
T78: 55 | U78: =Vocabulary!B56 -> or | V78: -3.0959778 | W78: =EXP(V78) -> 0.045230763 | X78: =W78/$W$22 -> 6.9524085e-09 | Y78: =IF(T78=$C$13,0,W78) -> 0.045230763 | Z78: =IF(OR(T78=$C$13,T78=$N$25),0,W78) -> 0.045230763
T79: 56 | U79: =Vocabulary!B57 -> could | V79: -6.5289648 | W79: =EXP(V79) -> 0.001460517 | X79: =W79/$W$22 -> 2.2449569e-10 | Y79: =IF(T79=$C$13,0,W79) -> 0.001460517 | Z79: =IF(OR(T79=$C$13,T79=$N$25),0,W79) -> 0.001460517
T80: 57 | U80: =Vocabulary!B58 -> there | V80: -0.81815289 | W80: =EXP(V80) -> 0.44124593 | X80: =W80/$W$22 -> 6.7823795e-08 | Y80: =IF(T80=$C$13,0,W80) -> 0.44124593 | Z80: =IF(OR(T80=$C$13,T80=$N$25),0,W80) -> 0.44124593
T81: 58 | U81: =Vocabulary!B59 -> thought | V81: 1.8763191 | W81: =EXP(V81) -> 6.5294262 | X81: =W81/$W$22 -> 1.0036364e-06 | Y81: =IF(T81=$C$13,0,W81) -> 6.5294262 | Z81: =IF(OR(T81=$C$13,T81=$N$25),0,W81) -> 6.5294262
T82: 59 | U82: =Vocabulary!B60 -> off | V82: -6.6252335 | W82: =EXP(V82) -> 0.0013264706 | X82: =W82/$W$22 -> 2.0389145e-10 | Y82: =IF(T82=$C$13,0,W82) -> 0.0013264706 | Z82: =IF(OR(T82=$C$13,T82=$N$25),0,W82) -> 0.0013264706
T83: 60 | U83: =Vocabulary!B61 -> time | V83: 11.097778 | W83: =EXP(V83) -> 66024.323 | X83: =W83/$W$22 -> 0.010148581 | Y83: =IF(T83=$C$13,0,W83) -> 66024.323 | Z83: =IF(OR(T83=$C$13,T83=$N$25),0,W83) -> 66024.323
T84: 61 | U84: =Vocabulary!B62 -> how | V84: -5.3889183 | W84: =EXP(V84) -> 0.0045669107 | X84: =W84/$W$22 -> 7.0197864e-10 | Y84: =IF(T84=$C$13,0,W84) -> 0.0045669107 | Z84: =IF(OR(T84=$C$13,T84=$N$25),0,W84) -> 0.0045669107
T85: 62 | U85: =Vocabulary!B63 -> me | V85: -0.37219436 | W85: =EXP(V85) -> 0.68922027 | X85: =W85/$W$22 -> 1.0593987e-07 | Y85: =IF(T85=$C$13,0,W85) -> 0.68922027 | Z85: =IF(OR(T85=$C$13,T85=$N$25),0,W85) -> 0.68922027
T86: 63 | U86: =Vocabulary!B64 -> queen | V86: 8.674655 | W86: =EXP(V86) -> 5852.6803 | X86: =W86/$W$22 -> 0.00089961394 | Y86: =IF(T86=$C$13,0,W86) -> 5852.6803 | Z86: =IF(OR(T86=$C$13,T86=$N$25),0,W86) -> 5852.6803
... T2651: 2628 | U2651: =Vocabulary!B2629 -> happy | V2651: 0.60853706 | W2651: =EXP(V2651) -> 1.8377409 | X2651: =W2651/$W$22 -> 2.8247867e-07 | Y2651: =IF(T2651=$C$13,0,W2651) -> 1.8377409 | Z2651: =IF(OR(T2651=$C$13,T2651=$N$25),0,W2651) -> 1.8377409

Sheet Circuits & Activations
B1: CIRCUITS AND ACTIVATIONS: WHY DID IT SAY THAT?
B2: Weights are the model's frozen knowledge. Activations are its passing thoughts. A circuit is the path between them.
B4: WEIGHTS VS ACTIVATIONS
B5: WEIGHTS live on the Embeddings, Hidden Weights and Output Weights tabs. They were fixed by training and do not
B6: change when you type. ACTIVATIONS are everything computed from your prompt: the embedding rows, the context c,
B7: the hidden vector h, the logits, the probabilities. Same weights, different prompt, different activations.
B8: Interpretability research asks: which weights, carrying which activations, cause which behavior? Such a causal
B9: pathway is called a CIRCUIT. In big models finding circuits is hard science; here the model is small enough
B10: to trace one completely, live, below.
B12: A LIVE CIRCUIT TRACE, HOP 1: HIDDEN NEURONS -> THE PREDICTED WORD
B13: the Prompt tab currently predicts: | C13: =Prompt!C48 -> be | D13: token ID: | E13: =MATCH(Prompt!C48,Vocabulary!$B$2:$B$2629,0) -> 26
B14: Its logit is just a dot product: SUM over 16 dims of h[dim] x OutputWeight[word,dim]. Here is every term:
B16: dim | C16: h (activation) | D16: Out[word,dim] | E16: contribution | F16: contribution bar | G16: abs
B17: 1 | C17: =INDEX(Prompt!$C$39:$R$39,1,B17) -> -0.8604061 | D17: =INDEX('Output Weights'!$C$2:$R$2629,$E$13,B17) -> -1.22571 | E17: =C17*D17 -> 1.0546084 | F17: =IF(E17<0,"-","+")&REPT("|",MIN(30,ROUND(ABS(E17)*8,0))) -> +|||||||| | G17: =ABS(E17) -> 1.0546084
B18: 2 | C18: =INDEX(Prompt!$C$39:$R$39,1,B18) -> 0.99999997 | D18: =INDEX('Output Weights'!$C$2:$R$2629,$E$13,B18) -> 1.82047 | E18: =C18*D18 -> 1.82047 | F18: =IF(E18<0,"-","+")&REPT("|",MIN(30,ROUND(ABS(E18)*8,0))) -> +||||||||||||||| | G18: =ABS(E18) -> 1.82047
B19: 3 | C19: =INDEX(Prompt!$C$39:$R$39,1,B19) -> 0.99994505 | D19: =INDEX('Output Weights'!$C$2:$R$2629,$E$13,B19) -> 0.87978 | E19: =C19*D19 -> 0.87973165 | F19: =IF(E19<0,"-","+")&REPT("|",MIN(30,ROUND(ABS(E19)*8,0))) -> +||||||| | G19: =ABS(E19) -> 0.87973165
B20: 4 | C20: =INDEX(Prompt!$C$39:$R$39,1,B20) -> 0.61989773 | D20: =INDEX('Output Weights'!$C$2:$R$2629,$E$13,B20) -> 0.71552 | E20: =C20*D20 -> 0.44354922 | F20: =IF(E20<0,"-","+")&REPT("|",MIN(30,ROUND(ABS(E20)*8,0))) -> +|||| | G20: =ABS(E20) -> 0.44354922
B21: 5 | C21: =INDEX(Prompt!$C$39:$R$39,1,B21) -> -0.99999112 | D21: =INDEX('Output Weights'!$C$2:$R$2629,$E$13,B21) -> -1.06669 | E21: =C21*D21 -> 1.0666805 | F21: =IF(E21<0,"-","+")&REPT("|",MIN(30,ROUND(ABS(E21)*8,0))) -> +||||||||| | G21: =ABS(E21) -> 1.0666805
B22: 6 | C22: =INDEX(Prompt!$C$39:$R$39,1,B22) -> -0.99922028 | D22: =INDEX('Output Weights'!$C$2:$R$2629,$E$13,B22) -> -2.97638 | E22: =C22*D22 -> 2.9740592 | F22: =IF(E22<0,"-","+")&REPT("|",MIN(30,ROUND(ABS(E22)*8,0))) -> +|||||||||||||||||||||||| | G22: =ABS(E22) -> 2.9740592
B23: 7 | C23: =INDEX(Prompt!$C$39:$R$39,1,B23) -> 0.35845788 | D23: =INDEX('Output Weights'!$C$2:$R$2629,$E$13,B23) -> -0.1106 | E23: =C23*D23 -> -0.039645441 | F23: =IF(E23<0,"-","+")&REPT("|",MIN(30,ROUND(ABS(E23)*8,0))) -> - | G23: =ABS(E23) -> 0.039645441
B24: 8 | C24: =INDEX(Prompt!$C$39:$R$39,1,B24) -> -1 | D24: =INDEX('Output Weights'!$C$2:$R$2629,$E$13,B24) -> -1.83537 | E24: =C24*D24 -> 1.83537 | F24: =IF(E24<0,"-","+")&REPT("|",MIN(30,ROUND(ABS(E24)*8,0))) -> +||||||||||||||| | G24: =ABS(E24) -> 1.83537
B25: 9 | C25: =INDEX(Prompt!$C$39:$R$39,1,B25) -> 0.99974844 | D25: =INDEX('Output Weights'!$C$2:$R$2629,$E$13,B25) -> 0.56034 | E25: =C25*D25 -> 0.56019904 | F25: =IF(E25<0,"-","+")&REPT("|",MIN(30,ROUND(ABS(E25)*8,0))) -> +|||| | G25: =ABS(E25) -> 0.56019904
B26: 10 | C26: =INDEX(Prompt!$C$39:$R$39,1,B26) -> 0.99999982 | D26: =INDEX('Output Weights'!$C$2:$R$2629,$E$13,B26) -> 2.43892 | E26: =C26*D26 -> 2.4389196 | F26: =IF(E26<0,"-","+")&REPT("|",MIN(30,ROUND(ABS(E26)*8,0))) -> +|||||||||||||||||||| | G26: =ABS(E26) -> 2.4389196
B27: 11 | C27: =INDEX(Prompt!$C$39:$R$39,1,B27) -> 0.99978519 | D27: =INDEX('Output Weights'!$C$2:$R$2629,$E$13,B27) -> 1.40286 | E27: =C27*D27 -> 1.4025586 | F27: =IF(E27<0,"-","+")&REPT("|",MIN(30,ROUND(ABS(E27)*8,0))) -> +||||||||||| | G27: =ABS(E27) -> 1.4025586
B28: 12 | C28: =INDEX(Prompt!$C$39:$R$39,1,B28) -> -0.91045831 | D28: =INDEX('Output Weights'!$C$2:$R$2629,$E$13,B28) -> 0.62649 | E28: =C28*D28 -> -0.57039302 | F28: =IF(E28<0,"-","+")&REPT("|",MIN(30,ROUND(ABS(E28)*8,0))) -> -||||| | G28: =ABS(E28) -> 0.57039302
... B32: 16 | C32: =INDEX(Prompt!$C$39:$R$39,1,B32) -> -0.99773922 | D32: =INDEX('Output Weights'!$C$2:$R$2629,$E$13,B32) -> -1.87818 | E32: =C32*D32 -> 1.8739339 | F32: =IF(E32<0,"-","+")&REPT("|",MIN(30,ROUND(ABS(E32)*8,0))) -> +||||||||||||||| | G32: =ABS(E32) -> 1.8739339
B33: sum of contributions = the word's logit: | E33: =SUM(E17:E32) -> 18.396011
B34: Check it against this word's Logit on the Prediction tab: identical. A few dims usually dominate; they are the circuit for this prediction. Change the prompt and watch different neurons take over.
B36: HOP 2: WHICH CONTEXT DIMENSIONS FEED THE MOST INFLUENTIAL NEURON?
B37: most influential hidden dim k* = | D37: =MATCH(MAX(G17:G32),G17:G32,0) -> 6
B38: That neuron's value is h[k*] = TANH(pre[k*]), and pre[k*] = SUM over i of c[i] x W[i,k*]. Every term:
B40: dim i | C40: c (activation) | D40: W[i,k*] (weight) | E40: contribution | F40: contribution bar
B41: 1 | C41: =INDEX(Prompt!$C$35:$R$35,1,B41) -> -0.62842094 | D41: =INDEX('Hidden Weights'!$C$3:$R$18,B41,$D$37) -> 4.43431 | E41: =C41*D41 -> -2.7866133 | F41: =IF(E41<0,"-","+")&REPT("|",MIN(30,ROUND(ABS(E41)*20,0))) -> -||||||||||||||||||||||||||||||
B42: 2 | C42: =INDEX(Prompt!$C$35:$R$35,1,B42) -> -0.24546148 | D42: =INDEX('Hidden Weights'!$C$3:$R$18,B42,$D$37) -> 6.19936 | E42: =C42*D42 -> -1.5217041 | F42: =IF(E42<0,"-","+")&REPT("|",MIN(30,ROUND(ABS(E42)*20,0))) -> -||||||||||||||||||||||||||||||
B43: 3 | C43: =INDEX(Prompt!$C$35:$R$35,1,B43) -> 1.257038 | D43: =INDEX('Hidden Weights'!$C$3:$R$18,B43,$D$37) -> 1.00243 | E43: =C43*D43 -> 1.2600926 | F43: =IF(E43<0,"-","+")&REPT("|",MIN(30,ROUND(ABS(E43)*20,0))) -> +|||||||||||||||||||||||||
B44: 4 | C44: =INDEX(Prompt!$C$35:$R$35,1,B44) -> 0.10870256 | D44: =INDEX('Hidden Weights'!$C$3:$R$18,B44,$D$37) -> -8.15346 | E44: =C44*D44 -> -0.88630195 | F44: =IF(E44<0,"-","+")&REPT("|",MIN(30,ROUND(ABS(E44)*20,0))) -> -||||||||||||||||||
B45: 5 | C45: =INDEX(Prompt!$C$35:$R$35,1,B45) -> -0.39605677 | D45: =INDEX('Hidden Weights'!$C$3:$R$18,B45,$D$37) -> -0.99335 | E45: =C45*D45 -> 0.39342299 | F45: =IF(E45<0,"-","+")&REPT("|",MIN(30,ROUND(ABS(E45)*20,0))) -> +||||||||
B46: 6 | C46: =INDEX(Prompt!$C$35:$R$35,1,B46) -> -0.45676224 | D46: =INDEX('Hidden Weights'!$C$3:$R$18,B46,$D$37) -> -1.14 | E46: =C46*D46 -> 0.52070895 | F46: =IF(E46<0,"-","+")&REPT("|",MIN(30,ROUND(ABS(E46)*20,0))) -> +||||||||||
B47: 7 | C47: =INDEX(Prompt!$C$35:$R$35,1,B47) -> 0.35345643 | D47: =INDEX('Hidden Weights'!$C$3:$R$18,B47,$D$37) -> -0.98219 | E47: =C47*D47 -> -0.34716137 | F47: =IF(E47<0,"-","+")&REPT("|",MIN(30,ROUND(ABS(E47)*20,0))) -> -|||||||
B48: 8 | C48: =INDEX(Prompt!$C$35:$R$35,1,B48) -> -0.35777534 | D48: =INDEX('Hidden Weights'!$C$3:$R$18,B48,$D$37) -> -1.79043 | E48: =C48*D48 -> 0.6405717 | F48: =IF(E48<0,"-","+")&REPT("|",MIN(30,ROUND(ABS(E48)*20,0))) -> +|||||||||||||
B49: 9 | C49: =INDEX(Prompt!$C$35:$R$35,1,B49) -> 0.4239627 | D49: =INDEX('Hidden Weights'!$C$3:$R$18,B49,$D$37) -> 2.37393 | E49: =C49*D49 -> 1.0064578 | F49: =IF(E49<0,"-","+")&REPT("|",MIN(30,ROUND(ABS(E49)*20,0))) -> +||||||||||||||||||||
B50: 10 | C50: =INDEX(Prompt!$C$35:$R$35,1,B50) -> 0.4227204 | D50: =INDEX('Hidden Weights'!$C$3:$R$18,B50,$D$37) -> -0.44407 | E50: =C50*D50 -> -0.18771745 | F50: =IF(E50<0,"-","+")&REPT("|",MIN(30,ROUND(ABS(E50)*20,0))) -> -||||
B51: 11 | C51: =INDEX(Prompt!$C$35:$R$35,1,B51) -> 0.91069347 | D51: =INDEX('Hidden Weights'!$C$3:$R$18,B51,$D$37) -> -3.45451 | E51: =C51*D51 -> -3.1459997 | F51: =IF(E51<0,"-","+")&REPT("|",MIN(30,ROUND(ABS(E51)*20,0))) -> -||||||||||||||||||||||||||||||
B52: 12 | C52: =INDEX(Prompt!$C$35:$R$35,1,B52) -> 0.28775189 | D52: =INDEX('Hidden Weights'!$C$3:$R$18,B52,$D$37) -> 0.18193 | E52: =C52*D52 -> 0.052350702 | F52: =IF(E52<0,"-","+")&REPT("|",MIN(30,ROUND(ABS(E52)*20,0))) -> +|
... B56: 16 | C56: =INDEX(Prompt!$C$35:$R$35,1,B56) -> -1.2777709 | D56: =INDEX('Hidden Weights'!$C$3:$R$18,B56,$D$37) -> -0.78499 | E56: =C56*D56 -> 1.0030374 | F56: =IF(E56<0,"-","+")&REPT("|",MIN(30,ROUND(ABS(E56)*20,0))) -> +||||||||||||||||||||
B57: sum = pre-activation of neuron k*: | E57: =SUM(E41:E56) -> -3.9246647
B58: Matches the "c x W" row (dim k*) on the Prompt tab. You have now traced a full two-hop circuit: context dims -> one neuron -> the predicted word. Add the attention step (which words built c) and the path runs input to output.
B60: WHAT THIS MEANS, AND REAL CIRCUITS
B61: In this tiny model one neuron rarely means one clean concept: dims get reused for many words. Big models do
B62: this too, aggressively: far more concepts than neurons, stored as overlapping directions. That is called
B63: superposition, and it is why interpreting real LLMs is hard. Researchers have still isolated famous circuits,
B64: like induction heads: attention patterns that spot "A B ... A" and predict "B", a mechanism behind in-context
B65: learning. The decompositions above are the same technique (direct logit attribution) those researchers use,
B66: just on a model small enough that nothing can hide.

Sheet How It Works
B1: HOW THIS TINY LLM WORKS
B3: THE BIG PICTURE
B4: A language model does one thing: given some words, assign a probability to every possible next word.
B5: Chatbots repeat that step, feeding each chosen word back in. This workbook is that single step, opened up,
B6: plus the thing most demos skip: the training step that created the weights, live on two tabs.
B8: STEP A: TOKENIZE
B9: Words are looked up in the Vocabulary tab with =IFERROR(MATCH(word, Vocabulary!B:B, 0), 1).
B10: The row number IS the token ID. Unknown words get ID 1, <unk>, whose embedding is all zeros.
B11: Real LLMs use subword pieces so nothing is ever unknown; details on the Tokenizer tab.
B13: STEP B: EMBED (10 x 16 BLOCK)
B14: Each of the 10 token IDs looks up a learned row of 16 numbers in the Embeddings tab with INDEX.
B15: Words used similarly ended up with similar vectors because that reduced training loss. Nobody chose them.
... B61: But every step, forward and backward, is the real thing at 1:10,000,000 scale.

Sheet Tokenizer
B1: TOKENIZER: FROM TEXT TO NUMBERS
B2: Models cannot read letters. The first job is turning text into token IDs.
B4: When the book was prepared, all text was lowercased and split on anything that is not a letter or an
B5: apostrophe. So "Rabbit-hole!" became two tokens, "rabbit" and "hole". Every distinct word got one row in the
B6: Vocabulary tab, ordered by frequency, and that row number is its token ID forever.
B7: The Prompt and Training Example tabs clean your typing the same way: lowercase, strip . , ! ? and spaces, then MATCH.
B9: LIVE DEMO: TYPE ANYTHING IN THE YELLOW CELL
B10: Curiouser! | C10: <- your raw text
B11: =LOWER(B10) -> curiouser! | C11: step 1: LOWER() lowercases it
B12: =SUBSTITUTE(SUBSTITUTE(SUBSTITUTE(SUBSTITUTE(B11,".",""),",",""),"!",""),"?","") -> curiouser | C12: step 2: SUBSTITUTE() strips . , ! ?
B13: =TRIM(B12) -> curiouser | C13: step 3: TRIM() removes stray spaces
B14: =IFERROR(MATCH(B13,Vocabulary!$B$2:$B$2629,0),1) -> 1135 | C14: step 4: MATCH() finds its Vocabulary row: the token ID (unknown -> 1, <unk>)
B15: =INDEX(Vocabulary!$B$2:$B$2629,B14) -> curiouser | C15: step 5: INDEX() reads back the token
B16: =INDEX(Vocabulary!$C$2:$C$2629,B14) -> 2 | C16: bonus: how often the book uses it
B18: Real LLMs use subword tokenization (byte pair encoding): rare words split into common pieces, so the model
B19: never meets a truly unknown word. With word-level tokens like ours, anything outside the book becomes <unk>,
B20: token 1, whose embedding is all zeros: present but silent.

Sheet Vocabulary
A1: Token ID | B1: Word | C1: Count | D1: Share | F1: Every distinct word in Alice in Wonderland, ordered by frequency. Row number = token ID. Token 1 is <unk>, the catch-all for words the book never uses.
A2: 1 | B2: <unk> | C2: 0 | D2: =C2/SUM($C$2:$C$2629) -> 0
A3: 2 | B3: the | C3: 1643 | D3: =C3/SUM($C$2:$C$2629) -> 0.061574785
A4: 3 | B4: and | C4: 872 | D4: =C4/SUM($C$2:$C$2629) -> 0.032679984
A5: 4 | B5: to | C5: 729 | D5: =C5/SUM($C$2:$C$2629) -> 0.027320766
A6: 5 | B6: a | C6: 632 | D6: =C6/SUM($C$2:$C$2629) -> 0.023685493
A7: 6 | B7: she | C7: 541 | D7: =C7/SUM($C$2:$C$2629) -> 0.020275082
A8: 7 | B8: it | C8: 530 | D8: =C8/SUM($C$2:$C$2629) -> 0.019862834
A9: 8 | B9: of | C9: 514 | D9: =C9/SUM($C$2:$C$2629) -> 0.019263201
A10: 9 | B10: said | C10: 462 | D10: =C10/SUM($C$2:$C$2629) -> 0.017314395
A11: 10 | B11: i | C11: 410 | D11: =C11/SUM($C$2:$C$2629) -> 0.015365589
A12: 11 | B12: alice | C12: 386 | D12: =C12/SUM($C$2:$C$2629) -> 0.014466139
A13: 12 | B13: in | C13: 368 | D13: =C13/SUM($C$2:$C$2629) -> 0.013791553
... A2629: 2628 | B2629: happy | C2629: 1 | D2629: =C2629/SUM($C$2:$C$2629) -> 3.7477045e-05

Sheet Embeddings
A1: Token ID | B1: Word | C1: d1 | D1: d2 | E1: d3 | F1: d4 | G1: d5 | H1: d6 | I1: d7 | J1: d8 | K1: d9 | L1: d10 | M1: d11 | N1: d12 | O1: d13 | P1: d14 | Q1: d15 | R1: d16 | T1: Learned INPUT embeddings: what each token means to the model. Row 2 is <unk>: zeros on purpose. These numbers were set by the gradient updates you can watch on the Backpropagation tab.
A2: 1 | B2: <unk> | C2: 0 | D2: 0 | E2: 0 | F2: 0 | G2: 0 | H2: 0 | I2: 0 | J2: 0 | K2: 0 | L2: 0 | M2: 0 | N2: 0 | O2: 0 | P2: 0 | Q2: 0 | R2: 0
A3: 2 | B3: the | C3: -0.24612 | D3: -0.69257 | E3: -1.11074 | F3: -0.52835 | G3: -0.49587 | H3: 0.16979 | I3: -1.56429 | J3: -0.73668 | K3: 0.62002 | L3: 0.80283 | M3: -0.61923 | N3: -0.87934 | O3: -0.30187 | P3: 0.67991 | Q3: -0.28704 | R3: 0.23597
A4: 3 | B4: and | C4: -0.25765 | D4: -0.27206 | E4: 1.0304 | F4: -0.35624 | G4: 0.0815 | H4: 0.64867 | I4: 0.45802 | J4: -0.48542 | K4: -0.40933 | L4: 0.10557 | M4: -0.48216 | N4: -0.51501 | O4: 0.07698 | P4: -0.14712 | Q4: 0.73348 | R4: -0.33239
A5: 4 | B5: to | C5: -0.89256 | D5: -0.23936 | E5: 0.51513 | F5: -0.37822 | G5: -0.31321 | H5: -0.48965 | I5: 0.98986 | J5: 0.1703 | K5: -0.42958 | L5: -0.25407 | M5: 1.6354 | N5: 0.28704 | O5: 0.60453 | P5: 1.55138 | Q5: 0.41237 | R5: 0.42672
A6: 5 | B6: a | C6: 0.44645 | D6: 0.35822 | E6: -0.33882 | F6: 0.46646 | G6: -0.49398 | H6: -0.35397 | I6: -1.67177 | J6: -1.32692 | K6: -0.02545 | L6: 0.24869 | M6: 0.63082 | N6: -0.58007 | O6: -0.04389 | P6: 0.52169 | Q6: -0.25329 | R6: 1.71116
A7: 6 | B7: she | C7: 0.58939 | D7: -0.032 | E7: 1.29894 | F7: -0.73718 | G7: -0.61515 | H7: 0.10221 | I7: -0.9534 | J7: 0.11271 | K7: 0.88084 | L7: 0.48162 | M7: -0.11465 | N7: 0.3557 | O7: -1.34677 | P7: -0.23398 | Q7: 0.80498 | R7: 0.70431
A8: 7 | B8: it | C8: 0.64978 | D8: -0.37327 | E8: -0.06494 | F8: -1.14919 | G8: 0.24692 | H8: 0.12358 | I8: -0.22484 | J8: 0.77162 | K8: 0.02832 | L8: 0.15956 | M8: 0.18753 | N8: -0.02053 | O8: -0.82008 | P8: -0.45595 | Q8: 0.19626 | R8: -0.5113
A9: 8 | B9: of | C9: -0.05844 | D9: -0.69847 | E9: -0.01318 | F9: 0.69573 | G9: 0.40065 | H9: -0.26492 | I9: 1.42647 | J9: -0.65642 | K9: -0.65223 | L9: -0.7729 | M9: -0.26861 | N9: -0.03118 | O9: 0.01131 | P9: 0.69797 | Q9: -0.25873 | R9: 0.80276
A10: 9 | B10: said | C10: -2.21786 | D10: 0.60313 | E10: -0.65743 | F10: 1.6003 | G10: 0.06833 | H10: 0.29803 | I10: 1.1348 | J10: 0.55625 | K10: -0.71007 | L10: -0.79737 | M10: -1.51727 | N10: -0.78639 | O10: -0.21638 | P10: -0.24406 | Q10: -0.08519 | R10: -0.42079
A11: 10 | B11: i | C11: -0.45772 | D11: -0.6143 | E11: 0.36666 | F11: 0.14778 | G11: -0.06465 | H11: 0.74835 | I11: -1.47305 | J11: 0.64672 | K11: -0.58108 | L11: 0.91448 | M11: 0.56548 | N11: 0.82683 | O11: -1.2928 | P11: -0.24921 | Q11: 0.71257 | R11: -0.83596
A12: 11 | B12: alice | C12: 0.17213 | D12: -0.01437 | E12: 0.84414 | F12: -0.6405 | G12: -0.5382 | H12: -0.46627 | I12: -0.97981 | J12: -0.22578 | K12: 1.15935 | L12: 0.35188 | M12: -0.55251 | N12: 0.95287 | O12: -0.38266 | P12: -0.28762 | Q12: -0.2028 | R12: -0.35594
A13: 12 | B13: in | C13: 0.24412 | D13: -0.72087 | E13: 1.28378 | F13: 0.03207 | G13: -0.46749 | H13: 0.24337 | I13: 1.59235 | J13: -0.97802 | K13: -0.1698 | L13: -0.89184 | M13: 0.03846 | N13: 0.41749 | O13: 0.25886 | P13: 0.95634 | Q13: -1.33422 | R13: 0.60227
... A2629: 2628 | B2629: happy | C2629: 1.4927 | D2629: -0.84884 | E2629: 1.45681 | F2629: 1.10799 | G2629: 1.97938 | H2629: 1.01558 | I2629: 3.35485 | J2629: -2.0228 | K2629: 3.57832 | L2629: -1.4684 | M2629: 2.50151 | N2629: -3.44536 | O2629: 2.06855 | P2629: 2.61329 | Q2629: 2.26385 | R2629: -0.65372

Sheet Output Weights
A1: Token ID | B1: Word | C1: d1 | D1: d2 | E1: d3 | F1: d4 | G1: d5 | H1: d6 | I1: d7 | J1: d8 | K1: d9 | L1: d10 | M1: d11 | N1: d12 | O1: d13 | P1: d14 | Q1: d15 | R1: d16 | T1: Learned OUTPUT projection: each word's detector. Its logit = dot product of this row with h, computed for all rows at once by MMULT #3 on the Prediction tab. The Backpropagation tab shows how these rows get pulled toward or pushed away from h.
A2: 1 | B2: <unk> | C2: 0 | D2: 0 | E2: 0 | F2: 0 | G2: 0 | H2: 0 | I2: 0 | J2: 0 | K2: 0 | L2: 0 | M2: 0 | N2: 0 | O2: 0 | P2: 0 | Q2: 0 | R2: 0
A3: 2 | B3: the | C3: -0.17571 | D3: 1.70363 | E3: -0.98837 | F3: -2.40823 | G3: -1.60686 | H3: -0.52271 | I3: -0.34776 | J3: 0.07473 | K3: -1.97877 | L3: -2.49415 | M3: -0.52973 | N3: -1.74845 | O3: 1.84495 | P3: 0.84028 | Q3: -3.4296 | R3: 0.68301
A4: 3 | B4: and | C4: 3.0232 | D4: 1.83644 | E4: 0.67001 | F4: -2.02697 | G4: -1.36151 | H4: 1.05452 | I4: 1.80746 | J4: 2.10124 | K4: -0.85019 | L4: -2.206 | M4: -1.2268 | N4: -1.65464 | O4: 2.68123 | P4: 1.03607 | Q4: -0.91787 | R4: 1.12741
A5: 4 | B5: to | C5: 1.58064 | D5: 1.99949 | E5: -1.47044 | F5: -1.86667 | G5: -1.30436 | H5: -0.82755 | I5: -1.2785 | J5: -1.28672 | K5: -0.57953 | L5: 0.28696 | M5: -2.55025 | N5: -0.63583 | O5: -0.69434 | P5: 2.43266 | Q5: -0.05097 | R5: 2.00785
A6: 5 | B6: a | C6: 0.92693 | D6: 1.28494 | E6: -2.32238 | F6: -1.52763 | G6: -1.28795 | H6: -0.58321 | I6: 1.00519 | J6: -2.1038 | K6: -2.01604 | L6: -0.8595 | M6: -0.70361 | N6: -1.26656 | O6: 0.59405 | P6: 0.32208 | Q6: -3.47555 | R6: 0.99125
A7: 6 | B7: she | C7: -0.01336 | D7: 1.17307 | E7: 1.75661 | F7: -1.12414 | G7: -1.52355 | H7: 0.90801 | I7: 0.34626 | J7: -0.61776 | K7: -1.1226 | L7: -2.21427 | M7: -0.57535 | N7: -0.9054 | O7: 0.99637 | P7: 0.85174 | Q7: -2.96216 | R7: 0.9259
A8: 7 | B8: it | C8: -0.18624 | D8: 0.89655 | E8: -1.32871 | F8: -0.20802 | G8: -0.41849 | H8: -0.54899 | I8: -0.99494 | J8: -1.39008 | K8: -0.97471 | L8: -1.17577 | M8: -1.32939 | N8: -2.42709 | O8: 1.04241 | P8: 2.48247 | Q8: -2.47252 | R8: 1.45825
A9: 8 | B9: of | C9: 2.3836 | D9: 2.1755 | E9: -0.40279 | F9: -0.52132 | G9: 1.50674 | H9: 1.85671 | I9: -1.64752 | J9: -1.73311 | K9: -2.12865 | L9: 0.69541 | M9: -0.57445 | N9: -2.09527 | O9: 2.64535 | P9: 1.80601 | Q9: 0.97391 | R9: -1.63659
A10: 9 | B10: said | C10: 0.51845 | D10: -0.19076 | E10: -0.35653 | F10: -0.0364 | G10: -0.2223 | H10: -0.70897 | I10: -1.3184 | J10: -1.95086 | K10: 1.8386 | L10: -1.82399 | M10: 0.40209 | N10: -2.54156 | O10: 0.89712 | P10: 1.6851 | Q10: -2.64079 | R10: 1.32691
A11: 10 | B11: i | C11: 1.28541 | D11: 1.36753 | E11: 1.06591 | F11: 0.40294 | G11: -1.67848 | H11: -1.08018 | I11: -0.00394 | J11: -0.18679 | K11: 0.07673 | L11: -0.60889 | M11: -1.03062 | N11: -3.11939 | O11: 0.92933 | P11: -0.22606 | Q11: -2.96067 | R11: 0.86095
A12: 11 | B12: alice | C12: -0.77036 | D12: 1.79249 | E12: -0.095 | F12: -1.94784 | G12: -1.19858 | H12: -0.47311 | I12: -1.30387 | J12: -0.27918 | K12: -1.66986 | L12: -1.82367 | M12: -0.76198 | N12: -2.12157 | O12: 1.18864 | P12: 2.50711 | Q12: -0.06527 | R12: 0.98749
A13: 12 | B13: in | C13: 1.69744 | D13: 2.86269 | E13: -1.08477 | F13: -1.04489 | G13: -0.66336 | H13: 0.4036 | I13: -0.69493 | J13: 0.71938 | K13: -0.91968 | L13: -1.17922 | M13: -0.39836 | N13: -0.77613 | O13: 0.30466 | P13: 1.94141 | Q13: -2.07608 | R13: 2.17281
... A2629: 2628 | B2629: happy | C2629: 0.20572 | D2629: -1.82729 | E2629: 2.77823 | F2629: 1.10205 | G2629: -0.08192 | H2629: -0.08623 | I2629: 0.16743 | J2629: -1.38771 | K2629: -0.43515 | L2629: 0.55349 | M2629: 1.11667 | N2629: 1.00793 | O2629: -2.45881 | P2629: -2.32115 | Q2629: 1.15067 | R2629: -2.6878

Sheet Hidden Weights
B1: HIDDEN LAYER WEIGHTS W (16 x 16)
C2: to d1 | D2: to d2 | E2: to d3 | F2: to d4 | G2: to d5 | H2: to d6 | I2: to d7 | J2: to d8 | K2: to d9 | L2: to d10 | M2: to d11 | N2: to d12 | O2: to d13 | P2: to d14 | Q2: to d15 | R2: to d16
B3: from d1 | C3: 1.07289 | D3: -2.09808 | E3: -5.83852 | F3: 1.82566 | G3: 1.40433 | H3: 4.43431 | I3: -1.03159 | J3: 1.7074 | K3: 5.79736 | L3: -0.14628 | M3: -0.31046 | N3: 3.50823 | O3: -2.98793 | P3: -0.0501 | Q3: -1.67329 | R3: -0.53109
B4: from d2 | C4: -1.4472 | D4: 2.29555 | E4: -0.77826 | F4: -2.86611 | G4: 4.24427 | H4: 6.19936 | I4: 2.46313 | J4: -0.0468 | K4: -2.10011 | L4: 0.75591 | M4: -2.5851 | N4: 4.08459 | O4: 1.65206 | P4: 6.03241 | Q4: 3.78836 | R4: 5.75445
B5: from d3 | C5: 1.53883 | D5: 3.54409 | E5: 0.38661 | F5: -6.20401 | G5: 2.49055 | H5: 1.00243 | I5: -0.32612 | J5: -6.89666 | K5: 3.30634 | L5: -0.66792 | M5: -0.5134 | N5: 0.0672 | O5: 2.01802 | P5: -2.4369 | Q5: -4.57646 | R5: -0.00379
B6: from d4 | C6: -0.2441 | D6: 1.04644 | E6: -4.88693 | F6: 1.2068 | G6: 2.60758 | H6: -8.15346 | I6: 0.44654 | J6: -0.57242 | K6: 0.55912 | L6: 2.08604 | M6: -4.17616 | N6: 1.78265 | O6: 1.13404 | P6: -2.48665 | Q6: 2.87792 | R6: 4.79837
B7: from d5 | C7: -2.58399 | D7: -1.23619 | E7: 0.84188 | F7: -1.81476 | G7: -4.29783 | H7: -0.99335 | I7: 1.59847 | J7: 2.57971 | K7: 2.88032 | L7: 0.29041 | M7: 1.00189 | N7: 4.4007 | O7: 1.75222 | P7: -4.46382 | Q7: 1.59852 | R7: 0.88555
B8: from d6 | C8: -2.03423 | D8: -1.55476 | E8: -1.39198 | F8: -4.14951 | G8: 0.18042 | H8: -1.14 | I8: 5.31149 | J8: -0.96556 | K8: -1.817 | L8: 2.18225 | M8: 0.59143 | N8: 1.03485 | O8: -8.57342 | P8: -1.06119 | Q8: 1.65597 | R8: -3.83048
B9: from d7 | C9: -1.8309 | D9: 8.05822 | E9: -0.993 | F9: 2.35329 | G9: -3.44262 | H9: -0.98219 | I9: 0.81853 | J9: 0.37327 | K9: -3.23353 | L9: 0.56856 | M9: -1.65632 | N9: 5.72789 | O9: 1.1378 | P9: 1.25123 | Q9: -7.33024 | R9: -1.87788
B10: from d8 | C10: 4.99286 | D10: 2.63416 | E10: 1.51638 | F10: -5.02697 | G10: -0.86417 | H10: -1.79043 | I10: -0.41075 | J10: 5.49359 | K10: 2.85591 | L10: 3.05129 | M10: -4.51986 | N10: -2.1208 | O10: 1.09086 | P10: 4.23072 | Q10: -0.86034 | R10: -3.01601
B11: from d9 | C11: 5.09246 | D11: -4.4387 | E11: 1.40701 | F11: 2.48615 | G11: -0.11053 | H11: 2.37393 | I11: 1.48761 | J11: -1.83987 | K11: -2.36189 | L11: 9.12894 | M11: 0.62908 | N11: 1.58038 | O11: 1.73122 | P11: -2.86938 | Q11: -1.93621 | R11: 0.77478
B12: from d10 | C12: 4.6015 | D12: 4.29734 | E12: -1.71472 | F12: 0.36357 | G12: 0.55119 | H12: -0.44407 | I12: -2.14423 | J12: -0.57202 | K12: 0.18424 | L12: 0.45271 | M12: 5.88673 | N12: 2.92571 | O12: 0.41684 | P12: -0.74226 | Q12: 6.48799 | R12: -3.79501
B13: from d11 | C13: -1.59133 | D13: -4.54558 | E13: 1.87556 | F13: 1.63291 | G13: 3.34454 | H13: -3.45451 | I13: 2.76023 | J13: -3.13733 | K13: 2.35223 | L13: -0.94828 | M13: 0.62288 | N13: 3.44557 | O13: 4.53551 | P13: 5.3086 | Q13: 0.47136 | R13: -5.08299
B14: from d12 | C14: 1.87289 | D14: 4.73905 | E14: 1.92177 | F14: 3.35981 | G14: -0.33764 | H14: 0.18193 | I14: 9.83508 | J14: -0.12645 | K14: 3.82759 | L14: -0.92452 | M14: 2.48136 | N14: -3.02713 | O14: -1.37254 | P14: 1.00516 | Q14: -0.1071 | R14: 2.91563
... B18: from d16 | C18: 1.87189 | D18: -2.02839 | E18: 0.07234 | F18: -0.42807 | G18: 10.57579 | H18: -0.78499 | I18: 1.29261 | J18: 4.6935 | K18: -2.40376 | L18: -3.91553 | M18: 0.8004 | N18: 1.96768 | O18: 0.43488 | P18: -4.07296 | Q18: -1.15469 | R18: -0.68543
B21: Used as MMULT(c, W) then TANH on the Prompt tab. Its gradient dW, and its updated version after one training
B22: step, are computed live on the Backpropagation tab. No individual number has a story; the matrix works as a
B23: whole, and the Circuits & Activations tab shows how to read pieces of it anyway.

Sheet Prediction
A1: SCORING ALL 2628 WORDS AT ONCE
A2: Column C is one MMULT array formula: Output Weights (2628 x 16) times TRANSPOSE(h from the Prompt tab) = 2628 logits.
A3: max logit | B3: =MAX(C6:C2633) -> 18.396011 | C3: sum of exp | D3: =SUM(D6:D2633) -> 1.2665688 | E3: temperature | F3: =Prompt!$C$45 -> 1
A5: Token ID | B5: Word | C5: Logit (MMULT) | D5: EXP((L-max)/T) | E5: Probability | F5: Rank helper | H5: Rank helper = probability + tokenID x 1E-10 (tie-break), with <unk> forced to -1 so it can never be predicted. The Prompt tab ranks this column with LARGE + MATCH.
A6: 1 | B6: =Vocabulary!B2 -> <unk> | C6: {=MMULT('Output Weights'!$C$2:$R$2629,TRANSPOSE(Prompt!$C$39:$R$39))} -> 0 | D6: =EXP((C6-$B$3)/$F$3) -> 1.0249764e-08 | E6: =D6/$D$3 -> 8.0925441e-09 | F6: =IF(A6=1,-1,E6+A6*0.0000000001) -> -1
A7: 2 | B7: =Vocabulary!B3 -> the | C7: 3.3264444 | D7: =EXP((C7-$B$3)/$F$3) -> 2.8534503e-07 | E7: =D7/$D$3 -> 2.2528979e-07 | F7: =IF(A7=1,-1,E7+A7*0.0000000001) -> 2.2548979e-07
A8: 3 | B8: =Vocabulary!B4 -> and | C8: -1.7626956 | D8: =EXP((C8-$B$3)/$F$3) -> 1.7586722e-09 | E8: =D8/$D$3 -> 1.3885327e-09 | F8: =IF(A8=1,-1,E8+A8*0.0000000001) -> 1.6885327e-09
A9: 4 | B9: =Vocabulary!B5 -> to | C9: -1.5058854 | D9: =EXP((C9-$B$3)/$F$3) -> 2.273611e-09 | E9: =D9/$D$3 -> 1.7950947e-09 | F9: =IF(A9=1,-1,E9+A9*0.0000000001) -> 2.1950947e-09
A10: 5 | B10: =Vocabulary!B6 -> a | C10: 2.530211 | D10: =EXP((C10-$B$3)/$F$3) -> 1.2869762e-07 | E10: =D10/$D$3 -> 1.0161124e-07 | F10: =IF(A10=1,-1,E10+A10*0.0000000001) -> 1.0211124e-07
A11: 6 | B11: =Vocabulary!B7 -> she | C11: 4.4011534 | D11: =EXP((C11-$B$3)/$F$3) -> 8.3581564e-07 | E11: =D11/$D$3 -> 6.5990543e-07 | F11: =IF(A11=1,-1,E11+A11*0.0000000001) -> 6.6050543e-07
A12: 7 | B12: =Vocabulary!B8 -> it | C12: 4.8721938 | D12: =EXP((C12-$B$3)/$F$3) -> 1.3386923e-06 | E12: =D12/$D$3 -> 1.056944e-06 | F12: =IF(A12=1,-1,E12+A12*0.0000000001) -> 1.057644e-06
A13: 8 | B13: =Vocabulary!B9 -> of | C13: 2.1900088 | D13: =EXP((C13-$B$3)/$F$3) -> 9.1584631e-08 | E13: =D13/$D$3 -> 7.2309241e-08 | F13: =IF(A13=1,-1,E13+A13*0.0000000001) -> 7.3109241e-08
A14: 9 | B14: =Vocabulary!B10 -> said | C14: 8.0220409 | D14: =EXP((C14-$B$3)/$F$3) -> 3.1235033e-05 | E14: =D14/$D$3 -> 2.4661141e-05 | F14: =IF(A14=1,-1,E14+A14*0.0000000001) -> 2.4662041e-05
A15: 10 | B15: =Vocabulary!B11 -> i | C15: 8.6027747 | D15: =EXP((C15-$B$3)/$F$3) -> 5.5827919e-05 | E15: =D15/$D$3 -> 4.4078077e-05 | F15: =IF(A15=1,-1,E15+A15*0.0000000001) -> 4.4079077e-05
A16: 11 | B16: =Vocabulary!B12 -> alice | C16: 3.0880781 | D16: =EXP((C16-$B$3)/$F$3) -> 2.2482736e-07 | E16: =D16/$D$3 -> 1.7750899e-07 | F16: =IF(A16=1,-1,E16+A16*0.0000000001) -> 1.7860899e-07
A17: 12 | B17: =Vocabulary!B13 -> in | C17: -0.67499319 | D17: =EXP((C17-$B$3)/$F$3) -> 5.2187687e-09 | E17: =D17/$D$3 -> 4.1203988e-09 | F17: =IF(A17=1,-1,E17+A17*0.0000000001) -> 5.3203988e-09
A18: 13 | B18: =Vocabulary!B14 -> you | C18: 9.8026674 | D18: =EXP((C18-$B$3)/$F$3) -> 0.00018533533 | E18: =D18/$D$3 -> 0.00014632867 | F18: =IF(A18=1,-1,E18+A18*0.0000000001) -> 0.00014632997
... A2633: 2628 | B2633: =Vocabulary!B2629 -> happy | C2633: 0.14136658 | D2633: =EXP((C2633-$B$3)/$F$3) -> 1.1806158e-08 | E2633: =D2633/$D$3 -> 9.3213712e-09 | F2633: =IF(A2633=1,-1,E2633+A2633*0.0000000001) -> 2.7212137e-07
